Workbook

Sheet IPEA_razao_capital_produto
A1: Data | B1: Capital fixo – relação capital-produto - - - Instituto de Pesquisa Econômica Aplicada - DIMAC_CFRCP
A2: 1947 | B2: 1.693885
A3: 1948 | B3: 1.625036
A4: 1949 | B4: 1.598943
A5: 1950 | B5: 1.591206
A6: 1951 | B6: 1.657188
A7: 1952 | B7: 1.679438
A8: 1953 | B8: 1.719262
A9: 1954 | B9: 1.735781
A10: 1955 | B10: 1.693564
A11: 1956 | B11: 1.756697
A12: 1957 | B12: 1.753561
A13: 1958 | B13: 1.715914
... A80: 2025 | B80: 2.044473

Sheet FGV_NUCI
A1: ANO | B1: Data | C1: Sondagem Industrial - Nível de Utilização da Capacidade Instalada Sem Ajuste Sazonal (CNAE 2.0)(1416216) | G1: ANO | H1: MÉDIA ANUAL
A2: =YEAR(B2) -> 2001 | B2: 36892 | C2: 81 | G2: 2001 | H2: =AVERAGEIF($A:$A,$G2,$C:$C) -> 80.133333
A3: =YEAR(B3) -> 2001 | B3: 36923 | C3: 81.8 | G3: 2002 | H3: =AVERAGEIF($A:$A,$G3,$C:$C) -> 78.616667
A4: =YEAR(B4) -> 2001 | B4: 36951 | C4: 81.3 | G4: 2003 | H4: =AVERAGEIF($A:$A,$G4,$C:$C) -> 79.441667
A5: =YEAR(B5) -> 2001 | B5: 36982 | C5: 80.7 | G5: 2004 | H5: =AVERAGEIF($A:$A,$G5,$C:$C) -> 81.558333
A6: =YEAR(B6) -> 2001 | B6: 37012 | C6: 80.2 | G6: 2005 | H6: =AVERAGEIF($A:$A,$G6,$C:$C) -> 81.516667
A7: =YEAR(B7) -> 2001 | B7: 37043 | C7: 79.6 | G7: 2006 | H7: =AVERAGEIF($A:$A,$G7,$C:$C) -> 81.533333
A8: =YEAR(B8) -> 2001 | B8: 37073 | C8: 79 | G8: 2007 | H8: =AVERAGEIF($A:$A,$G8,$C:$C) -> 83.55
A9: =YEAR(B9) -> 2001 | B9: 37104 | C9: 79.2 | G9: 2008 | H9: =AVERAGEIF($A:$A,$G9,$C:$C) -> 84.316667
A10: =YEAR(B10) -> 2001 | B10: 37135 | C10: 79.4 | G10: 2009 | H10: =AVERAGEIF($A:$A,$G10,$C:$C) -> 79.091667
A11: =YEAR(B11) -> 2001 | B11: 37165 | C11: 79.7 | G11: 2010 | H11: =AVERAGEIF($A:$A,$G11,$C:$C) -> 83.733333
A12: =YEAR(B12) -> 2001 | B12: 37196 | C12: 79.8 | G12: 2011 | H12: =AVERAGEIF($A:$A,$G12,$C:$C) -> 82.841667
A13: =YEAR(B13) -> 2001 | B13: 37226 | C13: 79.9 | G13: 2012 | H13: =AVERAGEIF($A:$A,$G13,$C:$C) -> 82.291667
... A27: =YEAR(B27) -> 2003 | B27: 37653 | C27: 80 | G27: 2026 | H27: =AVERAGEIF($A:$A,$G27,$C:$C) -> 81.775
A28: =YEAR(B28) -> 2003 | B28: 37681 | C28: 79.3
A29: =YEAR(B29) -> 2003 | B29: 37712 | C29: 78.3
A30: =YEAR(B30) -> 2003 | B30: 37742 | C30: 78.1
A31: =YEAR(B31) -> 2003 | B31: 37773 | C31: 77.8
A32: =YEAR(B32) -> 2003 | B32: 37803 | C32: 77.4
A33: =YEAR(B33) -> 2003 | B33: 37834 | C33: 78.8
A34: =YEAR(B34) -> 2003 | B34: 37865 | C34: 80
A35: =YEAR(B35) -> 2003 | B35: 37895 | C35: 81.4
A36: =YEAR(B36) -> 2003 | B36: 37926 | C36: 81.4
A37: =YEAR(B37) -> 2003 | B37: 37956 | C37: 81.4
A38: =YEAR(B38) -> 2004 | B38: 37987 | C38: 80
A39: =YEAR(B39) -> 2004 | B39: 38018 | C39: 80.8
... A309: =YEAR(B309) -> 2026 | B309: 46235 | C309: 83.6

Sheet parametro_v_un
B1: razão capital produto | C1: NUCI | E1: razão capital produto de pleno emprego
A2: 2013 | B2: =VLOOKUP(A2,IPEA_razao_capital_produto!A:B,2,0) -> 2.110154 | C2: =VLOOKUP(A2,FGV_NUCI!G:H,2,0) -> 82.533333 | E2: =B2*C2/100 -> 1.7415804
A3: 2014 | B3: =VLOOKUP(A3,IPEA_razao_capital_produto!A:B,2,0) -> 2.148066 | C3: =VLOOKUP(A3,FGV_NUCI!G:H,2,0) -> 81.208333 | E3: =B3*C3/100 -> 1.7444086
A4: 2015 | B4: =VLOOKUP(A4,IPEA_razao_capital_produto!A:B,2,0) -> 2.243766 | C4: =VLOOKUP(A4,FGV_NUCI!G:H,2,0) -> 76.366667 | E4: =B4*C4/100 -> 1.7134893
A5: 2016 | B5: =VLOOKUP(A5,IPEA_razao_capital_produto!A:B,2,0) -> 2.314663 | C5: =VLOOKUP(A5,FGV_NUCI!G:H,2,0) -> 73.866667 | E5: =B5*C5/100 -> 1.7097644
A6: 2017 | B6: =VLOOKUP(A6,IPEA_razao_capital_produto!A:B,2,0) -> 2.275823 | C6: =VLOOKUP(A6,FGV_NUCI!G:H,2,0) -> 74.4 | E6: =B6*C6/100 -> 1.6932123
A7: 2018 | B7: =VLOOKUP(A7,IPEA_razao_capital_produto!A:B,2,0) -> 2.229757 | C7: =VLOOKUP(A7,FGV_NUCI!G:H,2,0) -> 75.858333 | E7: =B7*C7/100 -> 1.6914565
A8: 2019 | B8: =VLOOKUP(A8,IPEA_razao_capital_produto!A:B,2,0) -> 2.206414 | C8: =VLOOKUP(A8,FGV_NUCI!G:H,2,0) -> 75.108333 | E8: =B8*C8/100 -> 1.6572008
A9: 2020 | B9: =VLOOKUP(A9,IPEA_razao_capital_produto!A:B,2,0) -> 2.277428 | C9: =VLOOKUP(A9,FGV_NUCI!G:H,2,0) -> 73.05 | E9: =B9*C9/100 -> 1.6636612
A10: 2021 | B10: =VLOOKUP(A10,IPEA_razao_capital_produto!A:B,2,0) -> 2.189191 | C10: =VLOOKUP(A10,FGV_NUCI!G:H,2,0) -> 79.4 | E10: =B10*C10/100 -> 1.7382177
A11: 2022 | B11: =VLOOKUP(A11,IPEA_razao_capital_produto!A:B,2,0) -> 2.142031 | C11: =VLOOKUP(A11,FGV_NUCI!G:H,2,0) -> 80.666667 | E11: =B11*C11/100 -> 1.727905
A12: 2023 | B12: =VLOOKUP(A12,IPEA_razao_capital_produto!A:B,2,0) -> 2.086347 | C12: =VLOOKUP(A12,FGV_NUCI!G:H,2,0) -> 80.333333 | E12: =B12*C12/100 -> 1.6760321
A13: 2024 | B13: =VLOOKUP(A13,IPEA_razao_capital_produto!A:B,2,0) -> 2.036712 | C13: =VLOOKUP(A13,FGV_NUCI!G:H,2,0) -> 82.116667 | E13: =B13*C13/100 -> 1.67248
A14: 2025 | B14: =VLOOKUP(A14,IPEA_razao_capital_produto!A:B,2,0) -> 2.044473 | C14: =VLOOKUP(A14,FGV_NUCI!G:H,2,0) -> 81.958333 | E14: =B14*C14/100 -> 1.675616
A16: média 2013-25 | C16: =AVERAGE(C2:C14) -> 78.220513 | E16: =AVERAGE(E2:E14) -> 1.7003865

Sheet BCB_expec_IPCA
C1: IPCA - variação % - Mediana - Período de 01/01/2013 a 31/12/2020 - Base: Expectativas informadas nos últimos 30 dias
A2: MÊS | B2: ANO | C2: Data | D2: Infl. 12 m | E2: Infl. 12 m suav. | G2: MÊS | H2: ANO | I2: DATA | J2: EXPECTATIVA MÉDIA DE IPCA
A3: =MONTH(C3) -> 1 | B3: =YEAR(C3) -> 2013 | C3: 41276 | D3: 5.67 | E3: 5.52 | G3: =MONTH(I3) -> 1 | H3: =YEAR(I3) -> 2013 | I3: 41275 | J3: =AVERAGEIFS(D:D,A:A,G3,B:B,H3) -> 5.6436364
A4: =MONTH(C4) -> 1 | B4: =YEAR(C4) -> 2013 | C4: 41277 | D4: 5.67 | E4: 5.52 | G4: =MONTH(I4) -> 2 | H4: =YEAR(I4) -> 2013 | I4: 41306 | J4: =AVERAGEIFS(D:D,A:A,G4,B:B,H4) -> 5.4972222
A5: =MONTH(C5) -> 1 | B5: =YEAR(C5) -> 2013 | C5: 41278 | D5: 5.67 | E5: 5.52 | G5: =MONTH(I5) -> 3 | H5: =YEAR(I5) -> 2013 | I5: 41334 | J5: =AVERAGEIFS(D:D,A:A,G5,B:B,H5) -> 5.449
A6: =MONTH(C6) -> 1 | B6: =YEAR(C6) -> 2013 | C6: 41281 | D6: 5.67 | E6: 5.5 | G6: =MONTH(I6) -> 4 | H6: =YEAR(I6) -> 2013 | I6: 41365 | J6: =AVERAGEIFS(D:D,A:A,G6,B:B,H6) -> 5.4613636
A7: =MONTH(C7) -> 1 | B7: =YEAR(C7) -> 2013 | C7: 41282 | D7: 5.69 | E7: 5.53 | G7: =MONTH(I7) -> 5 | H7: =YEAR(I7) -> 2013 | I7: 41395 | J7: =AVERAGEIFS(D:D,A:A,G7,B:B,H7) -> 5.5885714
A8: =MONTH(C8) -> 1 | B8: =YEAR(C8) -> 2013 | C8: 41283 | D8: 5.71 | E8: 5.52 | G8: =MONTH(I8) -> 6 | H8: =YEAR(I8) -> 2013 | I8: 41426 | J8: =AVERAGEIFS(D:D,A:A,G8,B:B,H8) -> 5.6945
A9: =MONTH(C9) -> 1 | B9: =YEAR(C9) -> 2013 | C9: 41284 | D9: 5.51 | E9: 5.54 | G9: =MONTH(I9) -> 7 | H9: =YEAR(I9) -> 2013 | I9: 41456 | J9: =AVERAGEIFS(D:D,A:A,G9,B:B,H9) -> 5.6482609
A10: =MONTH(C10) -> 1 | B10: =YEAR(C10) -> 2013 | C10: 41285 | D10: 5.53 | E10: 5.53 | G10: =MONTH(I10) -> 8 | H10: =YEAR(I10) -> 2013 | I10: 41487 | J10: =AVERAGEIFS(D:D,A:A,G10,B:B,H10) -> 5.9313636
A11: =MONTH(C11) -> 1 | B11: =YEAR(C11) -> 2013 | C11: 41288 | D11: 5.58 | E11: 5.55 | G11: =MONTH(I11) -> 9 | H11: =YEAR(I11) -> 2013 | I11: 41518 | J11: =AVERAGEIFS(D:D,A:A,G11,B:B,H11) -> 6.18
A12: =MONTH(C12) -> 1 | B12: =YEAR(C12) -> 2013 | C12: 41289 | D12: 5.58 | E12: 5.55 | G12: =MONTH(I12) -> 10 | H12: =YEAR(I12) -> 2013 | I12: 41548 | J12: =AVERAGEIFS(D:D,A:A,G12,B:B,H12) -> 6.2482609
A13: =MONTH(C13) -> 1 | B13: =YEAR(C13) -> 2013 | C13: 41290 | D13: 5.59 | E13: 5.54 | G13: =MONTH(I13) -> 11 | H13: =YEAR(I13) -> 2013 | I13: 41579 | J13: =AVERAGEIFS(D:D,A:A,G13,B:B,H13) -> 6.1995
A14: =MONTH(C14) -> 1 | B14: =YEAR(C14) -> 2013 | C14: 41291 | D14: 5.61 | E14: 5.55 | G14: =MONTH(I14) -> 12 | H14: =YEAR(I14) -> 2013 | I14: 41609 | J14: =AVERAGEIFS(D:D,A:A,G14,B:B,H14) -> 6.1057143
... A158: =MONTH(C158) -> 8 | B158: =YEAR(C158) -> 2013 | C158: 41500 | D158: 5.98 | E158: 5.97 | G158: =MONTH(I158) -> 12 | H158: =YEAR(I158) -> 2025 | I158: 45992 | J158: =AVERAGEIFS(D:D,A:A,G158,B:B,H158) -> 3.9991909
A159: =MONTH(C159) -> 8 | B159: =YEAR(C159) -> 2013 | C159: 41501 | D159: 5.95 | E159: 5.96
A160: =MONTH(C160) -> 8 | B160: =YEAR(C160) -> 2013 | C160: 41502 | D160: 5.96 | E160: 5.97
A161: =MONTH(C161) -> 8 | B161: =YEAR(C161) -> 2013 | C161: 41505 | D161: 5.99 | E161: 5.98
A162: =MONTH(C162) -> 8 | B162: =YEAR(C162) -> 2013 | C162: 41506 | D162: 6.01 | E162: 6.01
A163: =MONTH(C163) -> 8 | B163: =YEAR(C163) -> 2013 | C163: 41507 | D163: 6.01 | E163: 6.01
A164: =MONTH(C164) -> 8 | B164: =YEAR(C164) -> 2013 | C164: 41508 | D164: 6.01 | E164: 6.06
A165: =MONTH(C165) -> 8 | B165: =YEAR(C165) -> 2013 | C165: 41509 | D165: 6.02 | E165: 6.08
A166: =MONTH(C166) -> 8 | B166: =YEAR(C166) -> 2013 | C166: 41512 | D166: 6.02 | E166: 6.09
A167: =MONTH(C167) -> 8 | B167: =YEAR(C167) -> 2013 | C167: 41513 | D167: 6.02 | E167: 6.1
A168: =MONTH(C168) -> 8 | B168: =YEAR(C168) -> 2013 | C168: 41514 | D168: 6.02 | E168: 6.1
A169: =MONTH(C169) -> 8 | B169: =YEAR(C169) -> 2013 | C169: 41515 | D169: 6.04 | E169: 6.11
A170: =MONTH(C170) -> 8 | B170: =YEAR(C170) -> 2013 | C170: 41516 | D170: 6.08 | E170: 6.12
... A3447: =MONTH(C3447) -> 9 | B3447: =YEAR(C3447) -> 2026 | C3447: 46283 | D3447: 4.6948 | E3447: 4.6232

Sheet BCB_ipca_acum12m
A1: Data | B1: 13522 - Índice nacional de preços ao consumidor - amplo (IPCA) - em 12 meses - %
A2: 29556 | B2: 99.25
A3: 29587 | B3: 99.67
A4: 29618 | B4: 103.07
A5: 29646 | B5: 101.03
A6: 29677 | B6: 103.27
A7: 29707 | B7: 103
A8: 29738 | B8: 103.41
A9: 29768 | B9: 104.78
A10: 29799 | B10: 105.85
A11: 29830 | B11: 107.88
A12: 29860 | B12: 99.52
A13: 29891 | B13: 96.89
... A550: 46235 | B550: 4.22
A551: Fonte | B551: IBGE

Sheet BCB_selic
A1: MÊS | B1: ANO | C1: Data | D1: 432 - Taxa de juros - Meta Selic definida pelo Copom - % a.a. | G1: MÊS | H1: ANO | I1: DATA | J1: SELIC MÉDIA MENSAL
A2: =MONTH(C2) -> 1 | B2: =YEAR(C2) -> 2013 | C2: 41275 | D2: 7.25 | G2: =MONTH(I2) -> 1 | H2: =YEAR(I2) -> 2013 | I2: 41275 | J2: =AVERAGEIFS(D:D,A:A,G2,B:B,H2) -> 7.25
A3: =MONTH(C3) -> 1 | B3: =YEAR(C3) -> 2013 | C3: 41276 | D3: 7.25 | G3: =MONTH(I3) -> 2 | H3: =YEAR(I3) -> 2013 | I3: 41306 | J3: =AVERAGEIFS(D:D,A:A,G3,B:B,H3) -> 7.25
A4: =MONTH(C4) -> 1 | B4: =YEAR(C4) -> 2013 | C4: 41277 | D4: 7.25 | G4: =MONTH(I4) -> 3 | H4: =YEAR(I4) -> 2013 | I4: 41334 | J4: =AVERAGEIFS(D:D,A:A,G4,B:B,H4) -> 7.25
A5: =MONTH(C5) -> 1 | B5: =YEAR(C5) -> 2013 | C5: 41278 | D5: 7.25 | G5: =MONTH(I5) -> 4 | H5: =YEAR(I5) -> 2013 | I5: 41365 | J5: =AVERAGEIFS(D:D,A:A,G5,B:B,H5) -> 7.3583333
A6: =MONTH(C6) -> 1 | B6: =YEAR(C6) -> 2013 | C6: 41279 | D6: 7.25 | G6: =MONTH(I6) -> 5 | H6: =YEAR(I6) -> 2013 | I6: 41395 | J6: =AVERAGEIFS(D:D,A:A,G6,B:B,H6) -> 7.5322581
A7: =MONTH(C7) -> 1 | B7: =YEAR(C7) -> 2013 | C7: 41280 | D7: 7.25 | G7: =MONTH(I7) -> 6 | H7: =YEAR(I7) -> 2013 | I7: 41426 | J7: =AVERAGEIFS(D:D,A:A,G7,B:B,H7) -> 8
A8: =MONTH(C8) -> 1 | B8: =YEAR(C8) -> 2013 | C8: 41281 | D8: 7.25 | G8: =MONTH(I8) -> 7 | H8: =YEAR(I8) -> 2013 | I8: 41456 | J8: =AVERAGEIFS(D:D,A:A,G8,B:B,H8) -> 8.3387097
A9: =MONTH(C9) -> 1 | B9: =YEAR(C9) -> 2013 | C9: 41282 | D9: 7.25 | G9: =MONTH(I9) -> 8 | H9: =YEAR(I9) -> 2013 | I9: 41487 | J9: =AVERAGEIFS(D:D,A:A,G9,B:B,H9) -> 8.5483871
A10: =MONTH(C10) -> 1 | B10: =YEAR(C10) -> 2013 | C10: 41283 | D10: 7.25 | G10: =MONTH(I10) -> 9 | H10: =YEAR(I10) -> 2013 | I10: 41518 | J10: =AVERAGEIFS(D:D,A:A,G10,B:B,H10) -> 9
A11: =MONTH(C11) -> 1 | B11: =YEAR(C11) -> 2013 | C11: 41284 | D11: 7.25 | G11: =MONTH(I11) -> 10 | H11: =YEAR(I11) -> 2013 | I11: 41548 | J11: =AVERAGEIFS(D:D,A:A,G11,B:B,H11) -> 9.3548387
A12: =MONTH(C12) -> 1 | B12: =YEAR(C12) -> 2013 | C12: 41285 | D12: 7.25 | G12: =MONTH(I12) -> 11 | H12: =YEAR(I12) -> 2013 | I12: 41579 | J12: =AVERAGEIFS(D:D,A:A,G12,B:B,H12) -> 9.55
A13: =MONTH(C13) -> 1 | B13: =YEAR(C13) -> 2013 | C13: 41286 | D13: 7.25 | G13: =MONTH(I13) -> 12 | H13: =YEAR(I13) -> 2013 | I13: 41609 | J13: =AVERAGEIFS(D:D,A:A,G13,B:B,H13) -> 10
... A157: =MONTH(C157) -> 6 | B157: =YEAR(C157) -> 2013 | C157: 41430 | D157: 8 | G157: =MONTH(I157) -> 12 | H157: =YEAR(I157) -> 2025 | I157: 45992 | J157: =AVERAGEIFS(D:D,A:A,G157,B:B,H157) -> 15
A158: =MONTH(C158) -> 6 | B158: =YEAR(C158) -> 2013 | C158: 41431 | D158: 8
A159: =MONTH(C159) -> 6 | B159: =YEAR(C159) -> 2013 | C159: 41432 | D159: 8
A160: =MONTH(C160) -> 6 | B160: =YEAR(C160) -> 2013 | C160: 41433 | D160: 8
A161: =MONTH(C161) -> 6 | B161: =YEAR(C161) -> 2013 | C161: 41434 | D161: 8
A162: =MONTH(C162) -> 6 | B162: =YEAR(C162) -> 2013 | C162: 41435 | D162: 8
A163: =MONTH(C163) -> 6 | B163: =YEAR(C163) -> 2013 | C163: 41436 | D163: 8
A164: =MONTH(C164) -> 6 | B164: =YEAR(C164) -> 2013 | C164: 41437 | D164: 8
A165: =MONTH(C165) -> 6 | B165: =YEAR(C165) -> 2013 | C165: 41438 | D165: 8
A166: =MONTH(C166) -> 6 | B166: =YEAR(C166) -> 2013 | C166: 41439 | D166: 8
A167: =MONTH(C167) -> 6 | B167: =YEAR(C167) -> 2013 | C167: 41440 | D167: 8
A168: =MONTH(C168) -> 6 | B168: =YEAR(C168) -> 2013 | C168: 41441 | D168: 8
A169: =MONTH(C169) -> 6 | B169: =YEAR(C169) -> 2013 | C169: 41442 | D169: 8
... A5004: =MONTH(C5004) -> 9 | B5004: =YEAR(C5004) -> 2026 | C5004: 46277 | D5004: 14
A5005: =MONTH(C5005) -> #VALUE! | B5005: =YEAR(C5005) -> #VALUE! | C5005: Fonte | D5005: Copom

Sheet parametro_i
B1: selic | C1: expec_IPCA | D1: acum_12m_IPCA | G1: selic_ex_ante | H1: selic_ex_post | J1: 2013-2025 | K1: selic_ex_ante | L1: selic_ex_post
A2: 41275 | B2: =VLOOKUP(A2,BCB_selic!I:J,2,0) -> 7.25 | C2: =VLOOKUP(A2,BCB_expec_IPCA!I:J,2,0) -> 5.6436364 | D2: =VLOOKUP(A2,BCB_ipca_acum12m!A:B,2,0) -> 6.15 | F2: 41275 | G2: =B2-C2 -> 1.6063636 | H2: =B2-D2 -> 1.1 | J2: média | K2: =AVERAGE(G:G) -> 5.0318264 | L2: =AVERAGE(H:H) -> 4.0210809
A3: 41306 | B3: =VLOOKUP(A3,BCB_selic!I:J,2,0) -> 7.25 | C3: =VLOOKUP(A3,BCB_expec_IPCA!I:J,2,0) -> 5.4972222 | D3: =VLOOKUP(A3,BCB_ipca_acum12m!A:B,2,0) -> 6.31 | F3: 41306 | G3: =B3-C3 -> 1.7527778 | H3: =B3-D3 -> 0.94
A4: 41334 | B4: =VLOOKUP(A4,BCB_selic!I:J,2,0) -> 7.25 | C4: =VLOOKUP(A4,BCB_expec_IPCA!I:J,2,0) -> 5.449 | D4: =VLOOKUP(A4,BCB_ipca_acum12m!A:B,2,0) -> 6.59 | F4: 41334 | G4: =B4-C4 -> 1.801 | H4: =B4-D4 -> 0.66
A5: 41365 | B5: =VLOOKUP(A5,BCB_selic!I:J,2,0) -> 7.3583333 | C5: =VLOOKUP(A5,BCB_expec_IPCA!I:J,2,0) -> 5.4613636 | D5: =VLOOKUP(A5,BCB_ipca_acum12m!A:B,2,0) -> 6.49 | F5: 41365 | G5: =B5-C5 -> 1.8969697 | H5: =B5-D5 -> 0.86833333
A6: 41395 | B6: =VLOOKUP(A6,BCB_selic!I:J,2,0) -> 7.5322581 | C6: =VLOOKUP(A6,BCB_expec_IPCA!I:J,2,0) -> 5.5885714 | D6: =VLOOKUP(A6,BCB_ipca_acum12m!A:B,2,0) -> 6.5 | F6: 41395 | G6: =B6-C6 -> 1.9436866 | H6: =B6-D6 -> 1.0322581
A7: 41426 | B7: =VLOOKUP(A7,BCB_selic!I:J,2,0) -> 8 | C7: =VLOOKUP(A7,BCB_expec_IPCA!I:J,2,0) -> 5.6945 | D7: =VLOOKUP(A7,BCB_ipca_acum12m!A:B,2,0) -> 6.7 | F7: 41426 | G7: =B7-C7 -> 2.3055 | H7: =B7-D7 -> 1.3
A8: 41456 | B8: =VLOOKUP(A8,BCB_selic!I:J,2,0) -> 8.3387097 | C8: =VLOOKUP(A8,BCB_expec_IPCA!I:J,2,0) -> 5.6482609 | D8: =VLOOKUP(A8,BCB_ipca_acum12m!A:B,2,0) -> 6.27 | F8: 41456 | G8: =B8-C8 -> 2.6904488 | H8: =B8-D8 -> 2.0687097
A9: 41487 | B9: =VLOOKUP(A9,BCB_selic!I:J,2,0) -> 8.5483871 | C9: =VLOOKUP(A9,BCB_expec_IPCA!I:J,2,0) -> 5.9313636 | D9: =VLOOKUP(A9,BCB_ipca_acum12m!A:B,2,0) -> 6.09 | F9: 41487 | G9: =B9-C9 -> 2.6170235 | H9: =B9-D9 -> 2.4583871
A10: 41518 | B10: =VLOOKUP(A10,BCB_selic!I:J,2,0) -> 9 | C10: =VLOOKUP(A10,BCB_expec_IPCA!I:J,2,0) -> 6.18 | D10: =VLOOKUP(A10,BCB_ipca_acum12m!A:B,2,0) -> 5.86 | F10: 41518 | G10: =B10-C10 -> 2.82 | H10: =B10-D10 -> 3.14
A11: 41548 | B11: =VLOOKUP(A11,BCB_selic!I:J,2,0) -> 9.3548387 | C11: =VLOOKUP(A11,BCB_expec_IPCA!I:J,2,0) -> 6.2482609 | D11: =VLOOKUP(A11,BCB_ipca_acum12m!A:B,2,0) -> 5.84 | F11: 41548 | G11: =B11-C11 -> 3.1065778 | H11: =B11-D11 -> 3.5148387
A12: 41579 | B12: =VLOOKUP(A12,BCB_selic!I:J,2,0) -> 9.55 | C12: =VLOOKUP(A12,BCB_expec_IPCA!I:J,2,0) -> 6.1995 | D12: =VLOOKUP(A12,BCB_ipca_acum12m!A:B,2,0) -> 5.77 | F12: 41579 | G12: =B12-C12 -> 3.3505 | H12: =B12-D12 -> 3.78
A13: 41609 | B13: =VLOOKUP(A13,BCB_selic!I:J,2,0) -> 10 | C13: =VLOOKUP(A13,BCB_expec_IPCA!I:J,2,0) -> 6.1057143 | D13: =VLOOKUP(A13,BCB_ipca_acum12m!A:B,2,0) -> 5.91 | F13: 41609 | G13: =B13-C13 -> 3.8942857 | H13: =B13-D13 -> 4.09
A14: 41640 | B14: =VLOOKUP(A14,BCB_selic!I:J,2,0) -> 10.258065 | C14: =VLOOKUP(A14,BCB_expec_IPCA!I:J,2,0) -> 6.0440909 | D14: =VLOOKUP(A14,BCB_ipca_acum12m!A:B,2,0) -> 5.59 | F14: 41640 | G14: =B14-C14 -> 4.2139736 | H14: =B14-D14 -> 4.6680645
... A157: 45992 | B157: =VLOOKUP(A157,BCB_selic!I:J,2,0) -> 15 | C157: =VLOOKUP(A157,BCB_expec_IPCA!I:J,2,0) -> 3.9991909 | D157: =VLOOKUP(A157,BCB_ipca_acum12m!A:B,2,0) -> 4.26 | F157: 45992 | G157: =B157-C157 -> 11.000809 | H157: =B157-D157 -> 10.74

Sheet PAIM_B
A1: date | B1: SALDO | C1: AMORTIZACAO | E1: date | I1: média 2014-2025 | J1: =AVERAGE(G:G) -> 0.78927363
A2: 41275 | B2: 56448 | C2: 6795.4407 | E2: 41275
A3: 41306 | B3: 58497 | C3: 7295.2401 | E3: 41306 | F3: =rotativo_[[#This Row],[AMORTIZACAO]]/B2 -> 0.12923824 | G3: =(1-(1-F3)^12) -> 0.80998312
A4: 41334 | B4: 58023 | C4: 7086.6996 | E4: 41334 | F4: =rotativo_[[#This Row],[AMORTIZACAO]]/B3 -> 0.12114638 | G4: =(1-(1-F4)^12) -> 0.78767625
A5: 41365 | B5: 58696 | C5: 7124.4556 | E5: 41365 | F5: =rotativo_[[#This Row],[AMORTIZACAO]]/B4 -> 0.12278675 | G5: =(1-(1-F5)^12) -> 0.79238334
A6: 41395 | B6: 58448 | C6: 7052.7902 | E6: 41395 | F6: =rotativo_[[#This Row],[AMORTIZACAO]]/B5 -> 0.12015794 | G6: =(1-(1-F6)^12) -> 0.78479287
A7: 41426 | B7: 58312 | C7: 7158.9924 | E7: 41426 | F7: =rotativo_[[#This Row],[AMORTIZACAO]]/B6 -> 0.12248481 | G7: =(1-(1-F7)^12) -> 0.79152418
A8: 41456 | B8: 58335 | C8: 7023.3229 | E8: 41456 | F8: =rotativo_[[#This Row],[AMORTIZACAO]]/B7 -> 0.12044387 | G8: =(1-(1-F8)^12) -> 0.78563063
A9: 41487 | B9: 58901 | C9: 7125.9033 | E9: 41487 | F9: =rotativo_[[#This Row],[AMORTIZACAO]]/B8 -> 0.12215485 | G9: =(1-(1-F9)^12) -> 0.79058154
A10: 41518 | B10: 60605 | C10: 7389.7849 | E10: 41518 | F10: =rotativo_[[#This Row],[AMORTIZACAO]]/B9 -> 0.12546111 | G10: =(1-(1-F10)^12) -> 0.7998528
A11: 41548 | B11: 59980 | C11: 7181.5396 | E11: 41548 | F11: =rotativo_[[#This Row],[AMORTIZACAO]]/B10 -> 0.11849748 | G11: =(1-(1-F11)^12) -> 0.77986824
A12: 41579 | B12: 59710 | C12: 7296.1504 | E12: 41579 | F12: =rotativo_[[#This Row],[AMORTIZACAO]]/B11 -> 0.12164305 | G12: =(1-(1-F12)^12) -> 0.7891117
A13: 41609 | B13: 57843 | C13: 7045.7462 | E13: 41609 | F13: =rotativo_[[#This Row],[AMORTIZACAO]]/B12 -> 0.11799943 | G13: =(1-(1-F13)^12) -> 0.77837111
A14: 41640 | B14: 60204 | C14: 7304.8413 | E14: 41640 | F14: =rotativo_[[#This Row],[AMORTIZACAO]]/B13 -> 0.12628739 | G14: =(1-(1-F14)^12) -> 0.80211027
... A164: 46204 | B164: 226011 | C164: 25420.262 | E164: 46204 | F164: =rotativo_[[#This Row],[AMORTIZACAO]]/B163 -> 0.11230809 | G164: =(1-(1-F164)^12) -> 0.76058732

Sheet PAIM_Z
A1: date | B1: SALDO | C1: AMORTIZACAO | E1: date | I1: média 2014-2025 | J1: =AVERAGE(G:G) -> 0.043218079
A2: 41275 | B2: 263172 | C2: 1141.6838 | E2: 41275
A3: 41306 | B3: 268517 | C3: 1161.4156 | E3: 41306 | F3: =imobiliario[[#This Row],[AMORTIZACAO]]/B2 -> 0.0044131426 | G3: =(1-(1-F3)^12) -> 0.051691029
A4: 41334 | B4: 275996 | C4: 1188.8596 | E4: 41334 | F4: =imobiliario[[#This Row],[AMORTIZACAO]]/B3 -> 0.004427502 | G4: =(1-(1-F4)^12) -> 0.051855146
A5: 41365 | B5: 283580 | C5: 1212.0339 | E5: 41365 | F5: =imobiliario[[#This Row],[AMORTIZACAO]]/B4 -> 0.0043914909 | G5: =(1-(1-F5)^12) -> 0.051443518
A6: 41395 | B6: 292042 | C6: 1241.4545 | E6: 41395 | F6: =imobiliario[[#This Row],[AMORTIZACAO]]/B5 -> 0.0043777928 | G6: =(1-(1-F6)^12) -> 0.051286897
A7: 41426 | B7: 300962 | C7: 1267.1468 | E7: 41426 | F7: =imobiliario[[#This Row],[AMORTIZACAO]]/B6 -> 0.0043389198 | G7: =(1-(1-F7)^12) -> 0.050842304
A8: 41456 | B8: 309231 | C8: 1287.9121 | E8: 41456 | F8: =imobiliario[[#This Row],[AMORTIZACAO]]/B7 -> 0.004279318 | G8: =(1-(1-F8)^12) -> 0.050160262
A9: 41487 | B9: 317820 | C9: 1316.7721 | E9: 41487 | F9: =imobiliario[[#This Row],[AMORTIZACAO]]/B8 -> 0.0042582152 | G9: =(1-(1-F9)^12) -> 0.049918669
A10: 41518 | B10: 322542 | C10: 1325.9655 | E10: 41518 | F10: =imobiliario[[#This Row],[AMORTIZACAO]]/B9 -> 0.0041720644 | G10: =(1-(1-F10)^12) -> 0.048931797
A11: 41548 | B11: 325399 | C11: 1387.5084 | E11: 41548 | F11: =imobiliario[[#This Row],[AMORTIZACAO]]/B10 -> 0.0043017915 | G11: =(1-(1-F11)^12) -> 0.050417486
A12: 41579 | B12: 333018 | C12: 1409.9445 | E12: 41579 | F12: =imobiliario[[#This Row],[AMORTIZACAO]]/B11 -> 0.0043329712 | G12: =(1-(1-F12)^12) -> 0.050774252
A13: 41609 | B13: 340707 | C13: 1438.1521 | E13: 41609 | F13: =imobiliario[[#This Row],[AMORTIZACAO]]/B12 -> 0.0043185417 | G13: =(1-(1-F13)^12) -> 0.050609161
A14: 41640 | B14: 347394 | C14: 1464.7606 | E14: 41640 | F14: =imobiliario[[#This Row],[AMORTIZACAO]]/B13 -> 0.0042991796 | G14: =(1-(1-F14)^12) -> 0.050387594
... A164: 46204 | B164: 1414648 | C164: 4488.0777 | E164: 46204 | F164: =imobiliario[[#This Row],[AMORTIZACAO]]/B163 -> 0.0032164138 | G164: =(1-(1-F164)^12) -> 0.037921442

Sheet parametro_r
A1: date | B1: rotativo | C1: imobiliário | F1: Tipo de Crédito | G1: modalidades incluídas | H1: média
A2: 41275 | F2: B | G2: cheque especial, cartão de crédito rotativo, cartão de crédito parcelado | H2: =AVERAGE(B:B) -> 0.78927363
A3: 41306 | B3: =VLOOKUP(A3,PAIM_B!E:G,3,0) -> 0.80998312 | C3: =VLOOKUP(A3,PAIM_Z!E:G,3,0) -> 0.051691029 | F3: Z | G3: imobiliário com taxas reguladas e imobiliário com taxas de mercado | H3: =AVERAGE(C:C) -> 0.043218079
A4: 41334 | B4: =VLOOKUP(A4,PAIM_B!E:G,3,0) -> 0.78767625 | C4: =VLOOKUP(A4,PAIM_Z!E:G,3,0) -> 0.051855146
A5: 41365 | B5: =VLOOKUP(A5,PAIM_B!E:G,3,0) -> 0.79238334 | C5: =VLOOKUP(A5,PAIM_Z!E:G,3,0) -> 0.051443518
A6: 41395 | B6: =VLOOKUP(A6,PAIM_B!E:G,3,0) -> 0.78479287 | C6: =VLOOKUP(A6,PAIM_Z!E:G,3,0) -> 0.051286897
A7: 41426 | B7: =VLOOKUP(A7,PAIM_B!E:G,3,0) -> 0.79152418 | C7: =VLOOKUP(A7,PAIM_Z!E:G,3,0) -> 0.050842304
A8: 41456 | B8: =VLOOKUP(A8,PAIM_B!E:G,3,0) -> 0.78563063 | C8: =VLOOKUP(A8,PAIM_Z!E:G,3,0) -> 0.050160262
A9: 41487 | B9: =VLOOKUP(A9,PAIM_B!E:G,3,0) -> 0.79058154 | C9: =VLOOKUP(A9,PAIM_Z!E:G,3,0) -> 0.049918669
A10: 41518 | B10: =VLOOKUP(A10,PAIM_B!E:G,3,0) -> 0.7998528 | C10: =VLOOKUP(A10,PAIM_Z!E:G,3,0) -> 0.048931797
A11: 41548 | B11: =VLOOKUP(A11,PAIM_B!E:G,3,0) -> 0.77986824 | C11: =VLOOKUP(A11,PAIM_Z!E:G,3,0) -> 0.050417486
A12: 41579 | B12: =VLOOKUP(A12,PAIM_B!E:G,3,0) -> 0.7891117 | C12: =VLOOKUP(A12,PAIM_Z!E:G,3,0) -> 0.050774252
A13: 41609 | B13: =VLOOKUP(A13,PAIM_B!E:G,3,0) -> 0.77837111 | C13: =VLOOKUP(A13,PAIM_Z!E:G,3,0) -> 0.050609161
A14: 41640 | B14: =VLOOKUP(A14,PAIM_B!E:G,3,0) -> 0.80211027 | C14: =VLOOKUP(A14,PAIM_Z!E:G,3,0) -> 0.050387594
A15: 41671 | B15: =VLOOKUP(A15,PAIM_B!E:G,3,0) -> 0.82295763 | C15: =VLOOKUP(A15,PAIM_Z!E:G,3,0) -> 0.050328662
... A164: 46204 | B164: =VLOOKUP(A164,PAIM_B!E:G,3,0) -> 0.76058732 | C164: =VLOOKUP(A164,PAIM_Z!E:G,3,0) -> 0.037921442

Sheet BCB_TX_JUROS
A1: Data | B1: 20573 - Saldo da carteira de crédito com recursos livres - Pessoas físicas - Cheque especial - R$ (milhões) | C1: 20587 - Saldo da carteira de crédito com recursos livres - Pessoas físicas - Cartão de crédito rotativo - R$ (milhões) | D1: 20588 - Saldo da carteira de crédito com recursos livres - Pessoas físicas - Cartão de crédito parcelado - R$ (milhões) | E1: TOTAL MODALIDADES (B) | F1: %Cheque Especial | G1: %CC Rotativo | H1: %CC Parcelado | I1: 20741 - Taxa média de juros das operações de crédito com recursos livres - Pessoas físicas - Cheque especial - % a.a. | J1: 22022 - Taxa média de juros das operações de crédito com recursos livres - Pessoas físicas - Cartão de crédito rotativo - % a.a. | K1: 22023 - Taxa média de juros das operações de crédito com recursos livres - Pessoas físicas - Cartão de crédito parcelado - % a.a. | L1: TX_JUROS_PONDERADA | N1: Data | O1: 20610 - Saldo da carteira de crédito com recursos direcionados - Pessoas físicas - Financiamento imobiliário com taxas de mercado - R$ (milhões) | P1: 20611 - Saldo da carteira de crédito com recursos direcionados - Pessoas físicas - Financiamento imobiliário com taxas reguladas - R$ (milhões) | Q1: TOTAL MODALIDADES (Z) | R1: %Imobiliário taxas mercado | S1: %Imobiliário taxas reguladas | T1: 20772 - Taxa média de juros das operações de crédito com recursos direcionados - Pessoas físicas - Financiamento imobiliário com taxas de mercado - % a.a. | U1: 20773 - Taxa média de juros das operações de crédito com recursos direcionados - Pessoas físicas - Financiamento imobiliário com taxas reguladas - % a.a. | V1: TX_JUROS_PONDERADA
A2: 41275 | B2: 21957 | C2: 24591 | D2: 9900 | E2: =SUM(B2:D2) -> 56448 | F2: =B2/$E2 -> 0.38897747 | G2: =C2/$E2 -> 0.43563988 | H2: =D2/$E2 -> 0.17538265 | I2: 122.4 | J2: 250.18 | K2: 107.18 | L2: =F2*I2+G2*J2+H2*K2 -> 175.39674 | N2: 41275 | O2: 38185 | P2: 224987 | Q2: =SUM(O2:P2) -> 263172 | R2: =O2/$Q2 -> 0.14509522 | S2: =P2/$Q2 -> 0.85490478 | T2: 12.88 | U2: 7.1 | V2: =R2*T2+S2*U2 -> 7.9386504
A3: 41306 | B3: 22635 | C3: 25963 | D3: 9899 | E3: =SUM(B3:D3) -> 58497 | F3: =B3/$E3 -> 0.38694292 | G3: =C3/$E3 -> 0.44383473 | H3: =D3/$E3 -> 0.16922235 | I3: 122.58 | J3: 254.45 | K3: 106.42 | L3: =F3*I3+G3*J3+H3*K3 -> 178.37385 | N3: 41306 | O3: 39142 | P3: 229375 | Q3: =SUM(O3:P3) -> 268517 | R3: =O3/$Q3 -> 0.14577103 | S3: =P3/$Q3 -> 0.85422897 | T3: 12.67 | U3: 6.84 | V3: =R3*T3+S3*U3 -> 7.6898451
A4: 41334 | B4: 22058 | C4: 26057 | D4: 9908 | E4: =SUM(B4:D4) -> 58023 | F4: =B4/$E4 -> 0.38015959 | G4: =C4/$E4 -> 0.44908054 | H4: =D4/$E4 -> 0.17075987 | I4: 122.09 | J4: 252.63 | K4: 105.17 | L4: =F4*I4+G4*J4+H4*K4 -> 177.82372 | N4: 41334 | O4: 40573 | P4: 235423 | Q4: =SUM(O4:P4) -> 275996 | R4: =O4/$Q4 -> 0.14700575 | S4: =P4/$Q4 -> 0.85299425 | T4: 12.28 | U4: 6.91 | V4: =R4*T4+S4*U4 -> 7.6994209
A5: 41365 | B5: 22953 | C5: 25725 | D5: 10018 | E5: =SUM(B5:D5) -> 58696 | F5: =B5/$E5 -> 0.39104879 | G5: =C5/$E5 -> 0.43827518 | H5: =D5/$E5 -> 0.17067603 | I5: 121.62 | J5: 254.85 | K5: 100.13 | L5: =F5*I5+G5*J5+H5*K5 -> 176.34357 | N5: 41365 | O5: 42167 | P5: 241413 | Q5: =SUM(O5:P5) -> 283580 | R5: =O5/$Q5 -> 0.14869525 | S5: =P5/$Q5 -> 0.85130475 | T5: 12.24 | U5: 7.08 | V5: =R5*T5+S5*U5 -> 7.8472675
A6: 41395 | B6: 22784 | C6: 25742 | D6: 9922 | E6: =SUM(B6:D6) -> 58448 | F6: =B6/$E6 -> 0.38981659 | G6: =C6/$E6 -> 0.44042568 | H6: =D6/$E6 -> 0.16975773 | I6: 121.13 | J6: 254.53 | K6: 105.36 | L6: =F6*I6+G6*J6+H6*K6 -> 177.20571 | N6: 41395 | O6: 43951 | P6: 248091 | Q6: =SUM(O6:P6) -> 292042 | R6: =O6/$Q6 -> 0.15049548 | S6: =P6/$Q6 -> 0.84950452 | T6: 11.99 | U6: 7.05 | V6: =R6*T6+S6*U6 -> 7.7934477
A7: 41426 | B7: 22054 | C7: 26401 | D7: 9857 | E7: =SUM(B7:D7) -> 58312 | F7: =B7/$E7 -> 0.37820689 | G7: =C7/$E7 -> 0.45275415 | H7: =D7/$E7 -> 0.16903896 | I7: 121.77 | J7: 255.35 | K7: 105.94 | L7: =F7*I7+G7*J7+H7*K7 -> 179.57301 | N7: 41426 | O7: 45827 | P7: 255135 | Q7: =SUM(O7:P7) -> 300962 | R7: =O7/$Q7 -> 0.15226839 | S7: =P7/$Q7 -> 0.84773161 | T7: 11.93 | U7: 7.07 | V7: =R7*T7+S7*U7 -> 7.8100244
A8: 41456 | B8: 22440 | C8: 25973 | D8: 9922 | E8: =SUM(B8:D8) -> 58335 | F8: =B8/$E8 -> 0.38467472 | G8: =C8/$E8 -> 0.44523871 | H8: =D8/$E8 -> 0.17008657 | I8: 121.96 | J8: 260.52 | K8: 103.44 | L8: =F8*I8+G8*J8+H8*K8 -> 180.50227 | N8: 41456 | O8: 47539 | P8: 261692 | Q8: =SUM(O8:P8) -> 309231 | R8: =O8/$Q8 -> 0.15373297 | S8: =P8/$Q8 -> 0.84626703 | T8: 12.34 | U8: 7.17 | V8: =R8*T8+S8*U8 -> 7.9647995
A9: 41487 | B9: 22555 | C9: 25871 | D9: 10475 | E9: =SUM(B9:D9) -> 58901 | F9: =B9/$E9 -> 0.38293068 | G9: =C9/$E9 -> 0.43922854 | H9: =D9/$E9 -> 0.17784078 | I9: 122.64 | J9: 260.74 | K9: 106.07 | L9: =F9*I9+G9*J9+H9*K9 -> 180.35064 | N9: 41487 | O9: 49456 | P9: 268364 | Q9: =SUM(O9:P9) -> 317820 | R9: =O9/$Q9 -> 0.15561009 | S9: =P9/$Q9 -> 0.84438991 | T9: 12.34 | U9: 7.29 | V9: =R9*T9+S9*U9 -> 8.075831
A10: 41518 | B10: 23460 | C10: 26471 | D10: 10674 | E10: =SUM(B10:D10) -> 60605 | F10: =B10/$E10 -> 0.38709677 | G10: =C10/$E10 -> 0.43677914 | H10: =D10/$E10 -> 0.17612408 | I10: 125.51 | J10: 263.23 | K10: 101.49 | L10: =F10*I10+G10*J10+H10*K10 -> 181.43272 | N10: 41518 | O10: 50960 | P10: 271582 | Q10: =SUM(O10:P10) -> 322542 | R10: =O10/$Q10 -> 0.15799493 | S10: =P10/$Q10 -> 0.84200507 | T10: 12.57 | U10: 7.55 | V10: =R10*T10+S10*U10 -> 8.3431345
A11: 41548 | B11: 23420 | C11: 25876 | D11: 10684 | E11: =SUM(B11:D11) -> 59980 | F11: =B11/$E11 -> 0.39046349 | G11: =C11/$E11 -> 0.43141047 | H11: =D11/$E11 -> 0.17812604 | I11: 126.35 | J11: 267.23 | K11: 102.46 | L11: =F11*I11+G11*J11+H11*K11 -> 182.87168 | N11: 41548 | O11: 50422 | P11: 274977 | Q11: =SUM(O11:P11) -> 325399 | R11: =O11/$Q11 -> 0.15495438 | S11: =P11/$Q11 -> 0.84504562 | T11: 12.84 | U11: 7.91 | V11: =R11*T11+S11*U11 -> 8.6739251
A12: 41579 | B12: 22600 | C12: 26538 | D12: 10572 | E12: =SUM(B12:D12) -> 59710 | F12: =B12/$E12 -> 0.37849606 | G12: =C12/$E12 -> 0.44444817 | H12: =D12/$E12 -> 0.17705577 | I12: 127.46 | J12: 272.64 | K12: 105.6 | L12: =F12*I12+G12*J12+H12*K12 -> 188.11455 | N12: 41579 | O12: 51707 | P12: 281311 | Q12: =SUM(O12:P12) -> 333018 | R12: =O12/$Q12 -> 0.15526788 | S12: =P12/$Q12 -> 0.84473212 | T12: 14 | U12: 7.84 | V12: =R12*T12+S12*U12 -> 8.7964502
A13: 41609 | B13: 21623 | C13: 25563 | D13: 10657 | E13: =SUM(B13:D13) -> 57843 | F13: =B13/$E13 -> 0.37382224 | G13: =C13/$E13 -> 0.44193766 | H13: =D13/$E13 -> 0.1842401 | I13: 129.18 | J13: 285.95 | K13: 103.96 | L13: =F13*I13+G13*J13+H13*K13 -> 193.81603 | N13: 41609 | O13: 52752 | P13: 287955 | Q13: =SUM(O13:P13) -> 340707 | R13: =O13/$Q13 -> 0.15483098 | S13: =P13/$Q13 -> 0.84516902 | T13: 13.91 | U13: 7.89 | V13: =R13*T13+S13*U13 -> 8.8220825
... A164: 46204 | B164: 44929 | C164: 92761 | D164: 88321 | E164: =SUM(B164:D164) -> 226011 | F164: =B164/$E164 -> 0.19879121 | G164: =C164/$E164 -> 0.41042693 | H164: =D164/$E164 -> 0.39078186 | I164: 137.3 | J164: 436.15 | K164: 189.28 | L164: =F164*I164+G164*J164+H164*K164 -> 280.26893 | N164: 46204 | O164: 167767 | P164: 1246881 | Q164: =SUM(O164:P164) -> 1414648 | R164: =O164/$Q164 -> 0.11859275 | S164: =P164/$Q164 -> 0.88140725 | T164: 14.28 | U164: 10.92 | V164: =R164*T164+S164*U164 -> 11.318472
A165: Fonte | B165: BCB-DSTAT | C165: BCB-DSTAT | D165: BCB-DSTAT | E165: =SUM(B165:D165) -> 0 | F165: =B165/$E165 -> #VALUE! | G165: =C165/$E165 -> #VALUE! | H165: =D165/$E165 -> #VALUE! | I165: BCB-DSTAT | J165: BCB-DSTAT | K165: BCB-DSTAT | L165: =F165*I165+G165*J165+H165*K165 -> #VALUE! | N165: Fonte | O165: BCB-DSTAT | P165: BCB-DSTAT | Q165: =SUM(O165:P165) -> 0 | R165: =O165/$Q165 -> #VALUE! | S165: =P165/$Q165 -> #VALUE! | T165: BCB-DSTAT | U165: BCB-DSTAT | V165: =R165*T165+S165*U165 -> #VALUE!

Sheet parametro_lambda
A1: date | B1: i_ponderado_B | C1: i_ponderado_Z | E1: SELIC | G1: razao_i_ponderado_B_SELIC | H1: media2013-2019 | K1: razao_i_ponderado_Z_SELIC
A2: 41275 | B2: =VLOOKUP(A2,BCB_TX_JUROS!A:L,12,0) -> 175.39674 | C2: =VLOOKUP(A2,BCB_TX_JUROS!N:V,9,0) -> 7.9386504 | E2: =VLOOKUP(A2,BCB_selic!I:J,2,0) -> 7.25 | G2: =B2/E2 -> 24.192654 | K2: =C2/E2 -> 1.0949863 | N2: media2013-2019 | O2: =AVERAGE(G2:G85) -> 28.718945 | P2: =AVERAGE(K2:K85) -> 0.97056392
A3: 41306 | B3: =VLOOKUP(A3,BCB_TX_JUROS!A:L,12,0) -> 178.37385 | C3: =VLOOKUP(A3,BCB_TX_JUROS!N:V,9,0) -> 7.6898451 | E3: =VLOOKUP(A3,BCB_selic!I:J,2,0) -> 7.25 | G3: =B3/E3 -> 24.60329 | K3: =C3/E3 -> 1.0606683 | N3: media2020-2022 | O3: =AVERAGE(G86:G109) -> 71.423705 | P3: =AVERAGE(K86:K109) -> 2.3482742
A4: 41334 | B4: =VLOOKUP(A4,BCB_TX_JUROS!A:L,12,0) -> 177.82372 | C4: =VLOOKUP(A4,BCB_TX_JUROS!N:V,9,0) -> 7.6994209 | E4: =VLOOKUP(A4,BCB_selic!I:J,2,0) -> 7.25 | G4: =B4/E4 -> 24.527409 | K4: =C4/E4 -> 1.0619891 | N4: media2023-2025 | O4: =AVERAGE(G110:G157) -> 21.494555 | P4: =AVERAGE(K110:K157) -> 0.79535567
A5: 41365 | B5: =VLOOKUP(A5,BCB_TX_JUROS!A:L,12,0) -> 176.34357 | C5: =VLOOKUP(A5,BCB_TX_JUROS!N:V,9,0) -> 7.8472675 | E5: =VLOOKUP(A5,BCB_selic!I:J,2,0) -> 7.3583333 | G5: =B5/E5 -> 23.965152 | K5: =C5/E5 -> 1.0664463
A6: 41395 | B6: =VLOOKUP(A6,BCB_TX_JUROS!A:L,12,0) -> 177.20571 | C6: =VLOOKUP(A6,BCB_TX_JUROS!N:V,9,0) -> 7.7934477 | E6: =VLOOKUP(A6,BCB_selic!I:J,2,0) -> 7.5322581 | G6: =B6/E6 -> 23.526239 | K6: =C6/E6 -> 1.0346761
A7: 41426 | B7: =VLOOKUP(A7,BCB_TX_JUROS!A:L,12,0) -> 179.57301 | C7: =VLOOKUP(A7,BCB_TX_JUROS!N:V,9,0) -> 7.8100244 | E7: =VLOOKUP(A7,BCB_selic!I:J,2,0) -> 8 | G7: =B7/E7 -> 22.446627 | K7: =C7/E7 -> 0.97625305
A8: 41456 | B8: =VLOOKUP(A8,BCB_TX_JUROS!A:L,12,0) -> 180.50227 | C8: =VLOOKUP(A8,BCB_TX_JUROS!N:V,9,0) -> 7.9647995 | E8: =VLOOKUP(A8,BCB_selic!I:J,2,0) -> 8.3387097 | G8: =B8/E8 -> 21.646307 | K8: =C8/E8 -> 0.9551597
A9: 41487 | B9: =VLOOKUP(A9,BCB_TX_JUROS!A:L,12,0) -> 180.35064 | C9: =VLOOKUP(A9,BCB_TX_JUROS!N:V,9,0) -> 8.075831 | E9: =VLOOKUP(A9,BCB_selic!I:J,2,0) -> 8.5483871 | G9: =B9/E9 -> 21.097622 | K9: =C9/E9 -> 0.94471985
A10: 41518 | B10: =VLOOKUP(A10,BCB_TX_JUROS!A:L,12,0) -> 181.43272 | C10: =VLOOKUP(A10,BCB_TX_JUROS!N:V,9,0) -> 8.3431345 | E10: =VLOOKUP(A10,BCB_selic!I:J,2,0) -> 9 | G10: =B10/E10 -> 20.159191 | K10: =C10/E10 -> 0.92701495
A11: 41548 | B11: =VLOOKUP(A11,BCB_TX_JUROS!A:L,12,0) -> 182.87168 | C11: =VLOOKUP(A11,BCB_TX_JUROS!N:V,9,0) -> 8.6739251 | E11: =VLOOKUP(A11,BCB_selic!I:J,2,0) -> 9.3548387 | G11: =B11/E11 -> 19.548352 | K11: =C11/E11 -> 0.92721268
A12: 41579 | B12: =VLOOKUP(A12,BCB_TX_JUROS!A:L,12,0) -> 188.11455 | C12: =VLOOKUP(A12,BCB_TX_JUROS!N:V,9,0) -> 8.7964502 | E12: =VLOOKUP(A12,BCB_selic!I:J,2,0) -> 9.55 | G12: =B12/E12 -> 19.697858 | K12: =C12/E12 -> 0.92109426
A13: 41609 | B13: =VLOOKUP(A13,BCB_TX_JUROS!A:L,12,0) -> 193.81603 | C13: =VLOOKUP(A13,BCB_TX_JUROS!N:V,9,0) -> 8.8220825 | E13: =VLOOKUP(A13,BCB_selic!I:J,2,0) -> 10 | G13: =B13/E13 -> 19.381603 | K13: =C13/E13 -> 0.88220825
A14: 41640 | B14: =VLOOKUP(A14,BCB_TX_JUROS!A:L,12,0) -> 193.91782 | C14: =VLOOKUP(A14,BCB_TX_JUROS!N:V,9,0) -> 9.5187798 | E14: =VLOOKUP(A14,BCB_selic!I:J,2,0) -> 10.258065 | G14: =B14/E14 -> 18.903939 | K14: =C14/E14 -> 0.92793137
A15: 41671 | B15: =VLOOKUP(A15,BCB_TX_JUROS!A:L,12,0) -> 199.52372 | C15: =VLOOKUP(A15,BCB_TX_JUROS!N:V,9,0) -> 8.7467805 | E15: =VLOOKUP(A15,BCB_selic!I:J,2,0) -> 10.517857 | G15: =B15/E15 -> 18.969997 | K15: =C15/E15 -> 0.83161241
A16: 41699 | B16: =VLOOKUP(A16,BCB_TX_JUROS!A:L,12,0) -> 197.60588 | C16: =VLOOKUP(A16,BCB_TX_JUROS!N:V,9,0) -> 9.787762 | E16: =VLOOKUP(A16,BCB_selic!I:J,2,0) -> 10.75 | G16: =B16/E16 -> 18.381943 | K16: =C16/E16 -> 0.91048949
... A157: 45992 | B157: =VLOOKUP(A157,BCB_TX_JUROS!A:L,12,0) -> 279.54073 | C157: =VLOOKUP(A157,BCB_TX_JUROS!N:V,9,0) -> 10.805362 | E157: =VLOOKUP(A157,BCB_selic!I:J,2,0) -> 15 | G157: =B157/E157 -> 18.636049 | K157: =C157/E157 -> 0.72035745

Sheet parametro_lambda (2)
A1: date | B1: i_ponderado_B | C1: i_ponderado_Z | E1: ipca_acum_12m | F1: i_ponderado_B_real | G1: i_ponderado_Z_real | I1: razao_i_ponderado_B_SELIC | J1: razao_i_ponderado_Z_SELIC | K1: =AVERAGE(F:F) -> 253.91868 | L1: =AVERAGE(G:G) -> 3.2323683 | M1: SELIC | O1: razao_i_ponderado_B_SELIC | P1: media2013-2019 | S1: razao_i_ponderado_Z_SELIC
A2: 41275 | B2: =VLOOKUP(A2,BCB_TX_JUROS!A:L,12,0) -> 175.39674 | C2: =VLOOKUP(A2,BCB_TX_JUROS!N:V,9,0) -> 7.9386504 | E2: =VLOOKUP(A2,BCB_ipca_acum12m!A:B,2,0) -> 6.15 | F2: =B2-E2 -> 169.24674 | G2: =C2-E2 -> 1.7886504 | H2: =M2-E2 -> 1.1 | I2: =F2/H2 -> 153.86067 | J2: =G2/H2 -> 1.6260458 | M2: =VLOOKUP(A2,BCB_selic!I:J,2,0) -> 7.25 | O2: =B2/M2 -> 24.192654 | S2: =C2/M2 -> 1.0949863 | V2: media2013-2019 | W2: =AVERAGE(O2:O85) -> 28.718945 | X2: =AVERAGE(S2:S85) -> 0.97056392
A3: 41306 | B3: =VLOOKUP(A3,BCB_TX_JUROS!A:L,12,0) -> 178.37385 | C3: =VLOOKUP(A3,BCB_TX_JUROS!N:V,9,0) -> 7.6898451 | E3: =VLOOKUP(A3,BCB_ipca_acum12m!A:B,2,0) -> 6.31 | F3: =B3-E3 -> 172.06385 | G3: =C3-E3 -> 1.3798451 | H3: =M3-E3 -> 0.94 | I3: =F3/H3 -> 183.04665 | J3: =G3/H3 -> 1.4679203 | K3: =K1/5 -> 50.783736 | L3: =L1/5 -> 0.64647366 | M3: =VLOOKUP(A3,BCB_selic!I:J,2,0) -> 7.25 | O3: =B3/M3 -> 24.60329 | S3: =C3/M3 -> 1.0606683 | V3: media2020-2022 | W3: =AVERAGE(O86:O109) -> 71.423705 | X3: =AVERAGE(S86:S109) -> 2.3482742
A4: 41334 | B4: =VLOOKUP(A4,BCB_TX_JUROS!A:L,12,0) -> 177.82372 | C4: =VLOOKUP(A4,BCB_TX_JUROS!N:V,9,0) -> 7.6994209 | E4: =VLOOKUP(A4,BCB_ipca_acum12m!A:B,2,0) -> 6.59 | F4: =B4-E4 -> 171.23372 | G4: =C4-E4 -> 1.1094209 | H4: =M4-E4 -> 0.66 | I4: =F4/H4 -> 259.44502 | J4: =G4/H4 -> 1.6809408 | M4: =VLOOKUP(A4,BCB_selic!I:J,2,0) -> 7.25 | O4: =B4/M4 -> 24.527409 | S4: =C4/M4 -> 1.0619891 | V4: media2023-2025 | W4: =AVERAGE(O110:O157) -> 21.494555 | X4: =AVERAGE(S110:S157) -> 0.79535567
A5: 41365 | B5: =VLOOKUP(A5,BCB_TX_JUROS!A:L,12,0) -> 176.34357 | C5: =VLOOKUP(A5,BCB_TX_JUROS!N:V,9,0) -> 7.8472675 | E5: =VLOOKUP(A5,BCB_ipca_acum12m!A:B,2,0) -> 6.49 | F5: =B5-E5 -> 169.85357 | G5: =C5-E5 -> 1.3572675 | H5: =M5-E5 -> 0.86833333 | I5: =F5/H5 -> 195.60872 | J5: =G5/H5 -> 1.563072 | M5: =VLOOKUP(A5,BCB_selic!I:J,2,0) -> 7.3583333 | O5: =B5/M5 -> 23.965152 | S5: =C5/M5 -> 1.0664463
A6: 41395 | B6: =VLOOKUP(A6,BCB_TX_JUROS!A:L,12,0) -> 177.20571 | C6: =VLOOKUP(A6,BCB_TX_JUROS!N:V,9,0) -> 7.7934477 | E6: =VLOOKUP(A6,BCB_ipca_acum12m!A:B,2,0) -> 6.5 | F6: =B6-E6 -> 170.70571 | G6: =C6-E6 -> 1.2934477 | H6: =M6-E6 -> 1.0322581 | I6: =F6/H6 -> 165.37115 | J6: =G6/H6 -> 1.2530274 | M6: =VLOOKUP(A6,BCB_selic!I:J,2,0) -> 7.5322581 | O6: =B6/M6 -> 23.526239 | S6: =C6/M6 -> 1.0346761
A7: 41426 | B7: =VLOOKUP(A7,BCB_TX_JUROS!A:L,12,0) -> 179.57301 | C7: =VLOOKUP(A7,BCB_TX_JUROS!N:V,9,0) -> 7.8100244 | E7: =VLOOKUP(A7,BCB_ipca_acum12m!A:B,2,0) -> 6.7 | F7: =B7-E7 -> 172.87301 | G7: =C7-E7 -> 1.1100244 | H7: =M7-E7 -> 1.3 | I7: =F7/H7 -> 132.97924 | J7: =G7/H7 -> 0.85386491 | M7: =VLOOKUP(A7,BCB_selic!I:J,2,0) -> 8 | O7: =B7/M7 -> 22.446627 | S7: =C7/M7 -> 0.97625305
A8: 41456 | B8: =VLOOKUP(A8,BCB_TX_JUROS!A:L,12,0) -> 180.50227 | C8: =VLOOKUP(A8,BCB_TX_JUROS!N:V,9,0) -> 7.9647995 | E8: =VLOOKUP(A8,BCB_ipca_acum12m!A:B,2,0) -> 6.27 | F8: =B8-E8 -> 174.23227 | G8: =C8-E8 -> 1.6947995 | H8: =M8-E8 -> 2.0687097 | I8: =F8/H8 -> 84.222679 | J8: =G8/H8 -> 0.81925438 | M8: =VLOOKUP(A8,BCB_selic!I:J,2,0) -> 8.3387097 | O8: =B8/M8 -> 21.646307 | S8: =C8/M8 -> 0.9551597
A9: 41487 | B9: =VLOOKUP(A9,BCB_TX_JUROS!A:L,12,0) -> 180.35064 | C9: =VLOOKUP(A9,BCB_TX_JUROS!N:V,9,0) -> 8.075831 | E9: =VLOOKUP(A9,BCB_ipca_acum12m!A:B,2,0) -> 6.09 | F9: =B9-E9 -> 174.26064 | G9: =C9-E9 -> 1.985831 | H9: =M9-E9 -> 2.4583871 | I9: =F9/H9 -> 70.884133 | J9: =G9/H9 -> 0.80777798 | M9: =VLOOKUP(A9,BCB_selic!I:J,2,0) -> 8.5483871 | O9: =B9/M9 -> 21.097622 | S9: =C9/M9 -> 0.94471985
A10: 41518 | B10: =VLOOKUP(A10,BCB_TX_JUROS!A:L,12,0) -> 181.43272 | C10: =VLOOKUP(A10,BCB_TX_JUROS!N:V,9,0) -> 8.3431345 | E10: =VLOOKUP(A10,BCB_ipca_acum12m!A:B,2,0) -> 5.86 | F10: =B10-E10 -> 175.57272 | G10: =C10-E10 -> 2.4831345 | H10: =M10-E10 -> 3.14 | I10: =F10/H10 -> 55.91488 | J10: =G10/H10 -> 0.79080718 | M10: =VLOOKUP(A10,BCB_selic!I:J,2,0) -> 9 | O10: =B10/M10 -> 20.159191 | S10: =C10/M10 -> 0.92701495
A11: 41548 | B11: =VLOOKUP(A11,BCB_TX_JUROS!A:L,12,0) -> 182.87168 | C11: =VLOOKUP(A11,BCB_TX_JUROS!N:V,9,0) -> 8.6739251 | E11: =VLOOKUP(A11,BCB_ipca_acum12m!A:B,2,0) -> 5.84 | F11: =B11-E11 -> 177.03168 | G11: =C11-E11 -> 2.8339251 | H11: =M11-E11 -> 3.5148387 | I11: =F11/H11 -> 50.366942 | J11: =G11/H11 -> 0.80627458 | M11: =VLOOKUP(A11,BCB_selic!I:J,2,0) -> 9.3548387 | O11: =B11/M11 -> 19.548352 | S11: =C11/M11 -> 0.92721268
A12: 41579 | B12: =VLOOKUP(A12,BCB_TX_JUROS!A:L,12,0) -> 188.11455 | C12: =VLOOKUP(A12,BCB_TX_JUROS!N:V,9,0) -> 8.7964502 | E12: =VLOOKUP(A12,BCB_ipca_acum12m!A:B,2,0) -> 5.77 | F12: =B12-E12 -> 182.34455 | G12: =C12-E12 -> 3.0264502 | H12: =M12-E12 -> 3.78 | I12: =F12/H12 -> 48.239298 | J12: =G12/H12 -> 0.80064819 | M12: =VLOOKUP(A12,BCB_selic!I:J,2,0) -> 9.55 | O12: =B12/M12 -> 19.697858 | S12: =C12/M12 -> 0.92109426
A13: 41609 | B13: =VLOOKUP(A13,BCB_TX_JUROS!A:L,12,0) -> 193.81603 | C13: =VLOOKUP(A13,BCB_TX_JUROS!N:V,9,0) -> 8.8220825 | E13: =VLOOKUP(A13,BCB_ipca_acum12m!A:B,2,0) -> 5.91 | F13: =B13-E13 -> 187.90603 | G13: =C13-E13 -> 2.9120825 | H13: =M13-E13 -> 4.09 | I13: =F13/H13 -> 45.942795 | J13: =G13/H13 -> 0.71200062 | M13: =VLOOKUP(A13,BCB_selic!I:J,2,0) -> 10 | O13: =B13/M13 -> 19.381603 | S13: =C13/M13 -> 0.88220825
A14: 41640 | B14: =VLOOKUP(A14,BCB_TX_JUROS!A:L,12,0) -> 193.91782 | C14: =VLOOKUP(A14,BCB_TX_JUROS!N:V,9,0) -> 9.5187798 | E14: =VLOOKUP(A14,BCB_ipca_acum12m!A:B,2,0) -> 5.59 | F14: =B14-E14 -> 188.32782 | G14: =C14-E14 -> 3.9287798 | H14: =M14-E14 -> 4.6680645 | I14: =F14/H14 -> 40.343878 | J14: =G14/H14 -> 0.84162929 | M14: =VLOOKUP(A14,BCB_selic!I:J,2,0) -> 10.258065 | O14: =B14/M14 -> 18.903939 | S14: =C14/M14 -> 0.92793137
A15: 41671 | B15: =VLOOKUP(A15,BCB_TX_JUROS!A:L,12,0) -> 199.52372 | C15: =VLOOKUP(A15,BCB_TX_JUROS!N:V,9,0) -> 8.7467805 | E15: =VLOOKUP(A15,BCB_ipca_acum12m!A:B,2,0) -> 5.68 | F15: =B15-E15 -> 193.84372 | G15: =C15-E15 -> 3.0667805 | H15: =M15-E15 -> 4.8378571 | I15: =F15/H15 -> 40.068095 | J15: =G15/H15 -> 0.63391299 | M15: =VLOOKUP(A15,BCB_selic!I:J,2,0) -> 10.517857 | O15: =B15/M15 -> 18.969997 | S15: =C15/M15 -> 0.83161241
A16: 41699 | B16: =VLOOKUP(A16,BCB_TX_JUROS!A:L,12,0) -> 197.60588 | C16: =VLOOKUP(A16,BCB_TX_JUROS!N:V,9,0) -> 9.787762 | E16: =VLOOKUP(A16,BCB_ipca_acum12m!A:B,2,0) -> 6.15 | F16: =B16-E16 -> 191.45588 | G16: =C16-E16 -> 3.637762 | H16: =M16-E16 -> 4.6 | I16: =F16/H16 -> 41.620844 | J16: =G16/H16 -> 0.79081782 | M16: =VLOOKUP(A16,BCB_selic!I:J,2,0) -> 10.75 | O16: =B16/M16 -> 18.381943 | S16: =C16/M16 -> 0.91048949
... A157: 45992 | B157: =VLOOKUP(A157,BCB_TX_JUROS!A:L,12,0) -> 279.54073 | C157: =VLOOKUP(A157,BCB_TX_JUROS!N:V,9,0) -> 10.805362 | E157: =VLOOKUP(A157,BCB_ipca_acum12m!A:B,2,0) -> 4.26 | F157: =B157-E157 -> 275.28073 | G157: =C157-E157 -> 6.5453618 | H157: =M157-E157 -> 10.74 | I157: =F157/H157 -> 25.631353 | J157: =G157/H157 -> 0.60943778 | M157: =VLOOKUP(A157,BCB_selic!I:J,2,0) -> 15 | O157: =B157/M157 -> 18.636049 | S157: =C157/M157 -> 0.72035745

Sheet regressões
A1: RESUMO DOS RESULTADOS | U1: RESUMO DOS RESULTADOS
A3: Estatística de regressão | U3: Estatística de regressão
A4: R múltiplo | B4: 0.55884095 | U4: R múltiplo | V4: 0.70534241
A5: R-Quadrado | B5: 0.3123032 | U5: R-Quadrado | V5: 0.49750792
A6: R-quadrado ajustado | B6: 0.30783764 | U6: R-quadrado ajustado | V6: 0.49424499
A7: Erro padrão | B7: 39.907769 | U7: Erro padrão | V7: 1.7216205
A8: Observações | B8: 156 | U8: Observações | V8: 156
A10: ANOVA | U10: ANOVA
B11: gl | C11: SQ | D11: MQ | E11: F | F11: F de significação | V11: gl | W11: SQ | X11: MQ | Y11: F | Z11: F de significação
A12: Regressão | B12: 1 | C12: 111382.01 | D12: 111382.01 | E12: 69.935898 | F12: 3.4184184e-14 | U12: Regressão | V12: 1 | W12: 451.92499 | X12: 451.92499 | Y12: 152.47249 | Z12: 8.7751854e-25
A13: Resíduo | B13: 154 | C13: 245265.03 | D13: 1592.6301 | U13: Resíduo | V13: 154 | W13: 456.45248 | X13: 2.9639772
A14: Total | B14: 155 | C14: 356647.04 | U14: Total | V14: 155 | W14: 908.37747
B16: Coeficientes | C16: Erro padrão | D16: Stat t | E16: valor-P | F16: 95% inferiores | G16: 95% superiores | H16: Inferior 95,0% | I16: Superior 95,0% | V16: Coeficientes | W16: Erro padrão | X16: Stat t | Y16: valor-P | Z16: 95% inferiores | AA16: 95% superiores | AB16: Inferior 95,0% | AC16: Superior 95,0%
A17: Interseção | B17: 224.81593 | C17: 4.7243866 | D17: 47.586269 | E17: 5.3489517e-94 | F17: 215.48296 | G17: 234.1489 | H17: 215.48296 | I17: 234.1489 | U17: Interseção | V17: 1.3785821 | W17: 0.20380996 | X17: 6.7640565 | Y17: 2.6290358e-10 | Z17: 0.97595794 | AA17: 1.7812062 | AB17: 0.97595794 | AC17: 1.7812062
A18: Variável X 1 | B18: 7.2375437 | C18: 0.86544829 | D18: 8.3627686 | E18: 3.4184184e-14 | F18: 5.527861 | G18: 8.9472265 | H18: 5.527861 | I18: 8.9472265 | U18: Variável X 1 | V18: 0.4610169 | W18: 0.037335425 | X18: 12.347975 | Y18: 8.7751854e-25 | Z18: 0.38726121 | AA18: 0.53477259 | AB18: 0.38726121 | AC18: 0.53477259
A22: RESULTADOS DE RESÍDUOS | U22: RESULTADOS DE RESÍDUOS
A24: Observação | B24: Y previsto | C24: Resíduos | U24: Observação | V24: Y previsto | W24: Resíduos
A25: 1 | B25: 232.77723 | C25: -63.53049 | U25: 1 | V25: 1.8857007 | W25: -0.097050279
A26: 2 | B26: 231.61922 | C26: -59.55537 | U26: 2 | V26: 1.811938 | W26: -0.43209285
A27: 3 | B27: 229.59271 | C27: -58.358994 | U27: 3 | V27: 1.6828532 | W27: -0.57343233
A28: 4 | B28: 231.10053 | C28: -61.246958 | U28: 4 | V28: 1.7788984 | W28: -0.42163091
A29: 5 | B29: 232.28694 | C29: -61.581239 | U29: 5 | V29: 1.8544705 | W29: -0.56102284
A30: 6 | B30: 234.22474 | C30: -61.351726 | U30: 6 | V30: 1.977904 | W30: -0.86787966
A31: 7 | B31: 239.78831 | C31: -65.556036 | U31: 7 | V31: 2.3322922 | W31: -0.63749275
A32: 8 | B32: 242.60862 | C32: -68.347977 | U32: 8 | V32: 2.5119401 | W32: -0.5261091
A33: 9 | B33: 247.54182 | C33: -71.969096 | U33: 9 | V33: 2.8261751 | W33: -0.34304061
A34: 10 | B34: 250.25473 | C34: -73.223055 | U34: 10 | V34: 2.9989821 | W34: -0.16505703
A35: 11 | B35: 252.17385 | C35: -69.829301 | U35: 11 | V35: 3.121226 | W35: -0.094775798
A36: 12 | B36: 254.41749 | C36: -66.511454 | U36: 12 | V36: 3.2641412 | W36: -0.35205868
... A180: 156 | B180: 302.54715 | C180: -27.266418 | U180: 156 | V180: 6.3299036 | W180: 0.21545821
