Workbook

Sheet CEI_COMPLETA
A1: Nome da Origem | B1: Códigos | C1: Transações e saldos | D1: USOS | E1: RECURSOS
A2: 2000 | B2: P.7 | C2: Importação de bens e serviços
A3: 2000 | B3: P.6 | C3: Exportação de bens e serviços
A4: 2000 | B4: P.1 | C4: Produção | E4: 388773
A5: 2000 | B5: P.2 | C5: Consumo intermediário | D5: 97391
A6: 2000 | B6: D.21-D.31 | C6: Impostos, líquidos de subsídios, sobre produtos
A7: 2000 | B7: B.1 | C7: Valor adicionado bruto/Produto interno bruto (1) | D7: 291382 | E7: 291382
A8: 2000 | B8: B.11 | C8: Saldo externo de bens e serviços
A9: 2000 | B9: D.1 | C9: Remuneração dos empregados | D9: 28608 | E9: 470094
A10: 2000 | B10: D.11 | C10: Ordenados e salários | D10: 24362 | E10: 380925
A11: 2000 | B11: D.12 | C11: Contribuições sociais dos empregadores | D11: 4246 | E11: 89169
A12: 2000 | B12: D.121 | C12: Contribuições sociais efetivas | D12: 4246 | E12: 67435
A13: 2000 | B13: D.122 | C13: Contribuições sociais imputadas | E13: 21734
A14: 2000 | B14: D.2-D.3 | C14: Impostos, líquidos de subsídios, sobre a produção e a importação | D14: -1189
A15: 2000 | B15: D.29-D.39 | C15: Outros impostos, líquidos de subsídios, sobre a produção | D15: -1189
A16: 2000 | B16: B.2 | C16: Excedente operacional bruto | D16: 115598 | E16: 115598
A17: 2000 | B17: B.3 | C17: Rendimento misto bruto (rendimento de autônomos) | D17: 148365 | E17: 148365
A18: 2000 | B18: D.4 | C18: Rendas de propriedade | D18: 17092 | E18: 148856
A19: 2000 | B19: D.41 | C19: Juros | D19: 17027 | E19: 67149
A20: 2000 | B20: D.42 | C20: Dividendos e retiradas | E20: 70376
A21: 2000 | B21: D.43-D.44 | C21: Desembolsos por rendas de investimentos / Lucros reinvestidos de investimento direto estrangeiro | E21: 11331
A22: 2000 | B22: D.45 | C22: Renda de recursos naturais | D22: 65
A23: 2000 | B23: B.5 | C23: Saldo das rendas primárias brutas/Renda nacional bruta (2) | D23: 865821 | E23: 865821
A24: 2000 | B24: D.5 | C24: Impostos correntes sobre a renda, patrimônio, etc. | D24: 38568
A25: 2000 | B25: D.61 | C25: Contribuições sociais | D25: 129632
A26: 2000 | B26: D.611 | C26: Contribuições sociais efetivas dos empregadores | D26: 67435
A27: 2000 | B27: D.612 | C27: Contribuições sociais imputadas dos empregadores | D27: 21734
A28: 2000 | B28: D.613 | C28: Contribuições sociais efetivas das famílias/empregados | D28: 40463
A29: 2000 | B29: D.62 | C29: Benefícios sociais, exceto transferências sociais em espécie | E29: 160298
A30: 2000 | B30: D.621 | C30: Benefícios de seguridade social em numerário | E30: 70874
A31: 2000 | B31: D.622 | C31: Outros benefícios de seguro social | E31: 86655
A32: 2000 | B32: D.623 | C32: Benefícios de assistência social em numerário | E32: 2769
A33: 2000 | B33: D.7 | C33: Outras transferências correntes | D33: 15190 | E33: 6592
A34: 2000 | B34: D.71 | C34: Prêmios líquidos de seguros não-vida | D34: 2584
A35: 2000 | B35: D.72 | C35: Indenizações de seguros não-vida | E35: 2815
A36: 2000 | B36: D.73 | C36: Transferências correntes entre administrações públicas
A37: 2000 | B37: D.74 | C37: Cooperação Internacional
A38: 2000 | B38: D.75 | C38: Transferências correntes diversas | D38: 12606 | E38: 3777
A39: 2000 | B39: B.6 | C39: Renda disponível bruta | D39: 849321 | E39: 849321
A40: 2000 | B40: D.63 | C40: Transferências sociais em espécie | E40: 107799
A41: 2000 | B41: B.7 | C41: Renda disponível bruta ajustada | D41: 957120 | E41: 957120
A42: 2000 | B42: P.4 | C42: Consumo final efetivo | D42: 862131
A43: 2000 | B43: P.3 | C43: Despesa de consumo final | D43: 754333
A44: 2000 | B44: D.8 | C44: Ajustamento pela variação das participações líquidas das famílias nos fundos de pensões, FGTS e PIS/PASEP | E44: 12561
A45: 2000 | B45: B.8 | C45: Poupança bruta | D45: 107549
A46: 2000 | B46: B.12 | C46: Saldo externo corrente
A47: 2000 | B47: B.8 | C47: Poupança bruta | E47: 107549
A48: 2000 | B48: P.51 | C48: Formação bruta de capital fixo | D48: 81409
A49: 2000 | B49: P.52 | C49: Variação de estoques
A50: 2000 | B50: NP | C50: Aquisições líquidas de cessões de ativos não-financeiros não-produzidos
A51: 2000 | B51: D.9 | C51: Transferências de capital a receber | E51: 5
A52: 2000 | B52: B.9 | C52: Capacidade (+) / Necessidade(-) líquida de financiamento | D52: 24812
A53: 2000 | B53: B.10.1 | C53: Variações do patrimônio líquido resultantes de poupança e da transferência de capital | E53: 106220
A54: 2001 | B54: P.7 | C54: Importação de bens e serviços
A55: 2001 | B55: P.6 | C55: Exportação de bens e serviços
A56: 2001 | B56: P.1 | C56: Produção | E56: 411050
A57: 2001 | B57: P.2 | C57: Consumo intermediário | D57: 110866
A58: 2001 | B58: D.21-D.31 | C58: Impostos, líquidos de subsídios, sobre produtos
A59: 2001 | B59: B.1 | C59: Valor adicionado bruto/Produto interno bruto (1) | D59: 300184 | E59: 300184
A60: 2001 | B60: B.11 | C60: Saldo externo de bens e serviços
A61: 2001 | B61: D.1 | C61: Remuneração dos empregados | D61: 30382 | E61: 520720
A62: 2001 | B62: D.11 | C62: Ordenados e salários | D62: 25594 | E62: 418314
A63: 2001 | B63: D.12 | C63: Contribuições sociais dos empregadores | D63: 4788 | E63: 102406
A64: 2001 | B64: D.121 | C64: Contribuições sociais efetivas | D64: 4788 | E64: 76664
A65: 2001 | B65: D.122 | C65: Contribuições sociais imputadas | E65: 25742
A66: 2001 | B66: D.2-D.3 | C66: Impostos, líquidos de subsídios, sobre a produção e a importação | D66: -1496
A67: 2001 | B67: D.29-D.39 | C67: Outros impostos, líquidos de subsídios, sobre a produção | D67: -1496
A68: 2001 | B68: B.2 | C68: Excedente operacional bruto | D68: 116877 | E68: 116877
A69: 2001 | B69: B.3 | C69: Rendimento misto bruto (rendimento de autônomos) | D69: 154420 | E69: 154420
A70: 2001 | B70: D.4 | C70: Rendas de propriedade | D70: 18342 | E70: 169908
A71: 2001 | B71: D.41 | C71: Juros | D71: 18273 | E71: 71317
A72: 2001 | B72: D.42 | C72: Dividendos e retiradas | E72: 83903
A73: 2001 | B73: D.43-D.44 | C73: Desembolsos por rendas de investimentos / Lucros reinvestidos de investimento direto estrangeiro | E73: 14687
A74: 2001 | B74: D.45 | C74: Renda de recursos naturais | D74: 69
A75: 2001 | B75: B.5 | C75: Saldo das rendas primárias brutas/Renda nacional bruta (2) | D75: 943583 | E75: 943583
A76: 2001 | B76: D.5 | C76: Impostos correntes sobre a renda, patrimônio, etc. | D76: 44219
A77: 2001 | B77: D.61 | C77: Contribuições sociais | D77: 151615
A78: 2001 | B78: D.611 | C78: Contribuições sociais efetivas dos empregadores | D78: 76664
A79: 2001 | B79: D.612 | C79: Contribuições sociais imputadas dos empregadores | D79: 25742
A80: 2001 | B80: D.613 | C80: Contribuições sociais efetivas das famílias/empregados | D80: 49209
A81: 2001 | B81: D.62 | C81: Benefícios sociais, exceto transferências sociais em espécie | E81: 183633
A82: 2001 | B82: D.621 | C82: Benefícios de seguridade social em numerário | E82: 81993
A83: 2001 | B83: D.622 | C83: Outros benefícios de seguro social | E83: 98537
A84: 2001 | B84: D.623 | C84: Benefícios de assistência social em numerário | E84: 3103
A85: 2001 | B85: D.7 | C85: Outras transferências correntes | D85: 18577 | E85: 9167
A86: 2001 | B86: D.71 | C86: Prêmios líquidos de seguros não-vida | D86: 5236
A87: 2001 | B87: D.72 | C87: Indenizações de seguros não-vida | E87: 5491
A88: 2001 | B88: D.73 | C88: Transferências correntes entre administrações públicas
A89: 2001 | B89: D.74 | C89: Cooperação Internacional
A90: 2001 | B90: D.75 | C90: Transferências correntes diversas | D90: 13341 | E90: 3676
A91: 2001 | B91: B.6 | C91: Renda disponível bruta | D91: 921972 | E91: 921972
A92: 2001 | B92: D.63 | C92: Transferências sociais em espécie | E92: 115533
A93: 2001 | B93: B.7 | C93: Renda disponível bruta ajustada | D93: 1037505 | E93: 1037505
A94: 2001 | B94: P.4 | C94: Consumo final efetivo | D94: 938189
A95: 2001 | B95: P.3 | C95: Despesa de consumo final | D95: 822656
A96: 2001 | B96: D.8 | C96: Ajustamento pela variação das participações líquidas das famílias nos fundos de pensões, FGTS e PIS/PASEP | E96: 17532
A97: 2001 | B97: B.8 | C97: Poupança bruta | D97: 116849
A98: 2001 | B98: B.12 | C98: Saldo externo corrente
A99: 2001 | B99: B.8 | C99: Poupança bruta | E99: 116849
A100: 2001 | B100: P.51 | C100: Formação bruta de capital fixo | D100: 81411
...

Sheet Ajustes
A1: ORIGINAL | B1: Renda nacional disponível bruta | C1: Despesa de consumo final | D1: Formação Bruta de Capital Fixo | E1: Investimento Residencial | F1: Juros pessoais | G1: Transferências | H1: Poupança bruta | I1: Renda nacional disponível bruta | J1: Despesa de consumo final | K1: Formação Bruta de Capital Fixo | L1: Investimento Residencial | M1: Juros pessoais | N1: Transferências | O1: Poupança bruta | P1: FONTE | Q1: LINHA | S1: RECURSO/USO | T1: 2000 | U1: 2001 | V1: 2002 | W1: 2003 | X1: 2004 | Y1: 2005 | Z1: 2006 | AA1: 2007 | AB1: 2008 | AC1: 2009 | AD1: 2010 | AE1: 2011 | AF1: 2012 | AG1: 2013 | AH1: 2014 | AI1: 2015 | AJ1: 2016 | AK1: 2017 | AL1: 2018 | AM1: 2019 | AN1: 2020 | AO1: 2021
A2: Renda nacional disponível bruta | P2: CEI | Q2: B.6 | R2: B.6 | S2: R | T2: =_xlfn.LET( _xlpm.intervaloSoma, IF($S2="R", 'CEI_COMPLETA'!$E:$E, 'CEI_COMPLETA'!$D:$D), SUMIFS(_xlpm.intervaloSoma, 'CEI_COMPLETA'!$A:$A, Ajustes!T$1, 'CEI_COMPLETA'!$B:$B, Ajustes!$Q2) ) -> 849321 | U2: =_xlfn.LET( _xlpm.intervaloSoma, IF($S2="R", 'CEI_COMPLETA'!$E:$E, 'CEI_COMPLETA'!$D:$D), SUMIFS(_xlpm.intervaloSoma, 'CEI_COMPLETA'!$A:$A, Ajustes!U$1, 'CEI_COMPLETA'!$B:$B, Ajustes!$Q2) ) -> 921972 | V2: =_xlfn.LET( _xlpm.intervaloSoma, IF($S2="R", 'CEI_COMPLETA'!$E:$E, 'CEI_COMPLETA'!$D:$D), SUMIFS(_xlpm.intervaloSoma, 'CEI_COMPLETA'!$A:$A, Ajustes!V$1, 'CEI_COMPLETA'!$B:$B, Ajustes!$Q2) ) -> 1011475 | W2: =_xlfn.LET( _xlpm.intervaloSoma, IF($S2="R", 'CEI_COMPLETA'!$E:$E, 'CEI_COMPLETA'!$D:$D), SUMIFS(_xlpm.intervaloSoma, 'CEI_COMPLETA'!$A:$A, Ajustes!W$1, 'CEI_COMPLETA'!$B:$B, Ajustes!$Q2) ) -> 1154362 | X2: =_xlfn.LET( _xlpm.intervaloSoma, IF($S2="R", 'CEI_COMPLETA'!$E:$E, 'CEI_COMPLETA'!$D:$D), SUMIFS(_xlpm.intervaloSoma, 'CEI_COMPLETA'!$A:$A, Ajustes!X$1, 'CEI_COMPLETA'!$B:$B, Ajustes!$Q2) ) -> 1276698 | Y2: =_xlfn.LET( _xlpm.intervaloSoma, IF($S2="R", 'CEI_COMPLETA'!$E:$E, 'CEI_COMPLETA'!$D:$D), SUMIFS(_xlpm.intervaloSoma, 'CEI_COMPLETA'!$A:$A, Ajustes!Y$1, 'CEI_COMPLETA'!$B:$B, Ajustes!$Q2) ) -> 1406510 | Z2: =_xlfn.LET( _xlpm.intervaloSoma, IF($S2="R", 'CEI_COMPLETA'!$E:$E, 'CEI_COMPLETA'!$D:$D), SUMIFS(_xlpm.intervaloSoma, 'CEI_COMPLETA'!$A:$A, Ajustes!Z$1, 'CEI_COMPLETA'!$B:$B, Ajustes!$Q2) ) -> 1546184 | AA2: =_xlfn.LET( _xlpm.intervaloSoma, IF($S2="R", 'CEI_COMPLETA'!$E:$E, 'CEI_COMPLETA'!$D:$D), SUMIFS(_xlpm.intervaloSoma, 'CEI_COMPLETA'!$A:$A, Ajustes!AA$1, 'CEI_COMPLETA'!$B:$B, Ajustes!$Q2) ) -> 1737958 | ... AC2: =_xlfn.LET( _xlpm.intervaloSoma, IF($S2="R", 'CEI_COMPLETA'!$E:$E, 'CEI_COMPLETA'!$D:$D), SUMIFS(_xlpm.intervaloSoma, 'CEI_COMPLETA'!$A:$A, Ajustes!AC$1, 'CEI_COMPLETA'!$B:$B, Ajustes!$Q2) ) -> 2202388 | AD2: =_xlfn.LET( _xlpm.intervaloSoma, IF($S2="R", 'CEI_COMPLETA'!$E:$E, 'CEI_COMPLETA'!$D:$D), SUMIFS(_xlpm.intervaloSoma, 'CEI_COMPLETA'!$A:$A, Ajustes!AD$1, 'CEI_COMPLETA'!$B:$B, Ajustes!$R2) ) -> 2492302 | AE2: =_xlfn.LET( _xlpm.intervaloSoma, IF($S2="R", 'CEI_COMPLETA'!$E:$E, 'CEI_COMPLETA'!$D:$D), SUMIFS(_xlpm.intervaloSoma, 'CEI_COMPLETA'!$A:$A, Ajustes!AE$1, 'CEI_COMPLETA'!$B:$B, Ajustes!$R2) ) -> 2828939 | AF2: =_xlfn.LET( _xlpm.intervaloSoma, IF($S2="R", 'CEI_COMPLETA'!$E:$E, 'CEI_COMPLETA'!$D:$D), SUMIFS(_xlpm.intervaloSoma, 'CEI_COMPLETA'!$A:$A, Ajustes!AF$1, 'CEI_COMPLETA'!$B:$B, Ajustes!$R2) ) -> 3161213 | AG2: =_xlfn.LET( _xlpm.intervaloSoma, IF($S2="R", 'CEI_COMPLETA'!$E:$E, 'CEI_COMPLETA'!$D:$D), SUMIFS(_xlpm.intervaloSoma, 'CEI_COMPLETA'!$A:$A, Ajustes!AG$1, 'CEI_COMPLETA'!$B:$B, Ajustes!$R2) ) -> 3550416 | AH2: =_xlfn.LET( _xlpm.intervaloSoma, IF($S2="R", 'CEI_COMPLETA'!$E:$E, 'CEI_COMPLETA'!$D:$D), SUMIFS(_xlpm.intervaloSoma, 'CEI_COMPLETA'!$A:$A, Ajustes!AH$1, 'CEI_COMPLETA'!$B:$B, Ajustes!$R2) ) -> 3898396 | AI2: =_xlfn.LET( _xlpm.intervaloSoma, IF($S2="R", 'CEI_COMPLETA'!$E:$E, 'CEI_COMPLETA'!$D:$D), SUMIFS(_xlpm.intervaloSoma, 'CEI_COMPLETA'!$A:$A, Ajustes!AI$1, 'CEI_COMPLETA'!$B:$B, Ajustes!$R2) ) -> 4148220 | AJ2: =_xlfn.LET( _xlpm.intervaloSoma, IF($S2="R", 'CEI_COMPLETA'!$E:$E, 'CEI_COMPLETA'!$D:$D), SUMIFS(_xlpm.intervaloSoma, 'CEI_COMPLETA'!$A:$A, Ajustes!AJ$1, 'CEI_COMPLETA'!$B:$B, Ajustes!$R2) ) -> 4404397 | AK2: =_xlfn.LET( _xlpm.intervaloSoma, IF($S2="R", 'CEI_COMPLETA'!$E:$E, 'CEI_COMPLETA'!$D:$D), SUMIFS(_xlpm.intervaloSoma, 'CEI_COMPLETA'!$A:$A, Ajustes!AK$1, 'CEI_COMPLETA'!$B:$B, Ajustes!$R2) ) -> 4704231 | ... AO2: =_xlfn.LET( _xlpm.intervaloSoma, IF($S2="R", 'CEI_COMPLETA'!$E:$E, 'CEI_COMPLETA'!$D:$D), SUMIFS(_xlpm.intervaloSoma, 'CEI_COMPLETA'!$A:$A, Ajustes!AO$1, 'CEI_COMPLETA'!$B:$B, Ajustes!$R2) ) -> 5937056
A3: Despesa de consumo final | P3: CEI | Q3: P.3 | R3: P.3 | S3: U | T3: =_xlfn.LET( _xlpm.intervaloSoma, IF($S3="R", 'CEI_COMPLETA'!$E:$E, 'CEI_COMPLETA'!$D:$D), SUMIFS(_xlpm.intervaloSoma, 'CEI_COMPLETA'!$A:$A, Ajustes!T$1, 'CEI_COMPLETA'!$B:$B, Ajustes!$Q3) ) -> 754333 | U3: =_xlfn.LET( _xlpm.intervaloSoma, IF($S3="R", 'CEI_COMPLETA'!$E:$E, 'CEI_COMPLETA'!$D:$D), SUMIFS(_xlpm.intervaloSoma, 'CEI_COMPLETA'!$A:$A, Ajustes!U$1, 'CEI_COMPLETA'!$B:$B, Ajustes!$Q3) ) -> 822656 | V3: =_xlfn.LET( _xlpm.intervaloSoma, IF($S3="R", 'CEI_COMPLETA'!$E:$E, 'CEI_COMPLETA'!$D:$D), SUMIFS(_xlpm.intervaloSoma, 'CEI_COMPLETA'!$A:$A, Ajustes!V$1, 'CEI_COMPLETA'!$B:$B, Ajustes!$Q3) ) -> 895614 | W3: =_xlfn.LET( _xlpm.intervaloSoma, IF($S3="R", 'CEI_COMPLETA'!$E:$E, 'CEI_COMPLETA'!$D:$D), SUMIFS(_xlpm.intervaloSoma, 'CEI_COMPLETA'!$A:$A, Ajustes!W$1, 'CEI_COMPLETA'!$B:$B, Ajustes!$Q3) ) -> 1035030 | X3: =_xlfn.LET( _xlpm.intervaloSoma, IF($S3="R", 'CEI_COMPLETA'!$E:$E, 'CEI_COMPLETA'!$D:$D), SUMIFS(_xlpm.intervaloSoma, 'CEI_COMPLETA'!$A:$A, Ajustes!X$1, 'CEI_COMPLETA'!$B:$B, Ajustes!$Q3) ) -> 1147362 | Y3: =_xlfn.LET( _xlpm.intervaloSoma, IF($S3="R", 'CEI_COMPLETA'!$E:$E, 'CEI_COMPLETA'!$D:$D), SUMIFS(_xlpm.intervaloSoma, 'CEI_COMPLETA'!$A:$A, Ajustes!Y$1, 'CEI_COMPLETA'!$B:$B, Ajustes!$Q3) ) -> 1277027 | Z3: =_xlfn.LET( _xlpm.intervaloSoma, IF($S3="R", 'CEI_COMPLETA'!$E:$E, 'CEI_COMPLETA'!$D:$D), SUMIFS(_xlpm.intervaloSoma, 'CEI_COMPLETA'!$A:$A, Ajustes!Z$1, 'CEI_COMPLETA'!$B:$B, Ajustes!$Q3) ) -> 1411686 | AA3: =_xlfn.LET( _xlpm.intervaloSoma, IF($S3="R", 'CEI_COMPLETA'!$E:$E, 'CEI_COMPLETA'!$D:$D), SUMIFS(_xlpm.intervaloSoma, 'CEI_COMPLETA'!$A:$A, Ajustes!AA$1, 'CEI_COMPLETA'!$B:$B, Ajustes!$Q3) ) -> 1585632 | ... AC3: =_xlfn.LET( _xlpm.intervaloSoma, IF($S3="R", 'CEI_COMPLETA'!$E:$E, 'CEI_COMPLETA'!$D:$D), SUMIFS(_xlpm.intervaloSoma, 'CEI_COMPLETA'!$A:$A, Ajustes!AC$1, 'CEI_COMPLETA'!$B:$B, Ajustes!$Q3) ) -> 2011763 | AD3: =_xlfn.LET( _xlpm.intervaloSoma, IF($S3="R", 'CEI_COMPLETA'!$E:$E, 'CEI_COMPLETA'!$D:$D), SUMIFS(_xlpm.intervaloSoma, 'CEI_COMPLETA'!$A:$A, Ajustes!AD$1, 'CEI_COMPLETA'!$B:$B, Ajustes!$R3) ) -> 2278735 | AE3: =_xlfn.LET( _xlpm.intervaloSoma, IF($S3="R", 'CEI_COMPLETA'!$E:$E, 'CEI_COMPLETA'!$D:$D), SUMIFS(_xlpm.intervaloSoma, 'CEI_COMPLETA'!$A:$A, Ajustes!AE$1, 'CEI_COMPLETA'!$B:$B, Ajustes!$R3) ) -> 2573419 | AF3: =_xlfn.LET( _xlpm.intervaloSoma, IF($S3="R", 'CEI_COMPLETA'!$E:$E, 'CEI_COMPLETA'!$D:$D), SUMIFS(_xlpm.intervaloSoma, 'CEI_COMPLETA'!$A:$A, Ajustes!AF$1, 'CEI_COMPLETA'!$B:$B, Ajustes!$R3) ) -> 2883929 | AG3: =_xlfn.LET( _xlpm.intervaloSoma, IF($S3="R", 'CEI_COMPLETA'!$E:$E, 'CEI_COMPLETA'!$D:$D), SUMIFS(_xlpm.intervaloSoma, 'CEI_COMPLETA'!$A:$A, Ajustes!AG$1, 'CEI_COMPLETA'!$B:$B, Ajustes!$R3) ) -> 3213817 | AH3: =_xlfn.LET( _xlpm.intervaloSoma, IF($S3="R", 'CEI_COMPLETA'!$E:$E, 'CEI_COMPLETA'!$D:$D), SUMIFS(_xlpm.intervaloSoma, 'CEI_COMPLETA'!$A:$A, Ajustes!AH$1, 'CEI_COMPLETA'!$B:$B, Ajustes!$R3) ) -> 3555352 | AI3: =_xlfn.LET( _xlpm.intervaloSoma, IF($S3="R", 'CEI_COMPLETA'!$E:$E, 'CEI_COMPLETA'!$D:$D), SUMIFS(_xlpm.intervaloSoma, 'CEI_COMPLETA'!$A:$A, Ajustes!AI$1, 'CEI_COMPLETA'!$B:$B, Ajustes!$R3) ) -> 3747870 | AJ3: =_xlfn.LET( _xlpm.intervaloSoma, IF($S3="R", 'CEI_COMPLETA'!$E:$E, 'CEI_COMPLETA'!$D:$D), SUMIFS(_xlpm.intervaloSoma, 'CEI_COMPLETA'!$A:$A, Ajustes!AJ$1, 'CEI_COMPLETA'!$B:$B, Ajustes!$R3) ) -> 3939208 | AK3: =_xlfn.LET( _xlpm.intervaloSoma, IF($S3="R", 'CEI_COMPLETA'!$E:$E, 'CEI_COMPLETA'!$D:$D), SUMIFS(_xlpm.intervaloSoma, 'CEI_COMPLETA'!$A:$A, Ajustes!AK$1, 'CEI_COMPLETA'!$B:$B, Ajustes!$R3) ) -> 4156152 | ... AO3: =_xlfn.LET( _xlpm.intervaloSoma, IF($S3="R", 'CEI_COMPLETA'!$E:$E, 'CEI_COMPLETA'!$D:$D), SUMIFS(_xlpm.intervaloSoma, 'CEI_COMPLETA'!$A:$A, Ajustes!AO$1, 'CEI_COMPLETA'!$B:$B, Ajustes!$R3) ) -> 5415523
A4: Formação Bruta de Capital Fixo | P4: CEI | Q4: P.51 | R4: P.51 | S4: U | T4: =_xlfn.LET( _xlpm.intervaloSoma, IF($S4="R", 'CEI_COMPLETA'!$E:$E, 'CEI_COMPLETA'!$D:$D), SUMIFS(_xlpm.intervaloSoma, 'CEI_COMPLETA'!$A:$A, Ajustes!T$1, 'CEI_COMPLETA'!$B:$B, Ajustes!$Q4) ) -> 81409 | U4: =_xlfn.LET( _xlpm.intervaloSoma, IF($S4="R", 'CEI_COMPLETA'!$E:$E, 'CEI_COMPLETA'!$D:$D), SUMIFS(_xlpm.intervaloSoma, 'CEI_COMPLETA'!$A:$A, Ajustes!U$1, 'CEI_COMPLETA'!$B:$B, Ajustes!$Q4) ) -> 81411 | V4: =_xlfn.LET( _xlpm.intervaloSoma, IF($S4="R", 'CEI_COMPLETA'!$E:$E, 'CEI_COMPLETA'!$D:$D), SUMIFS(_xlpm.intervaloSoma, 'CEI_COMPLETA'!$A:$A, Ajustes!V$1, 'CEI_COMPLETA'!$B:$B, Ajustes!$Q4) ) -> 94472 | W4: =_xlfn.LET( _xlpm.intervaloSoma, IF($S4="R", 'CEI_COMPLETA'!$E:$E, 'CEI_COMPLETA'!$D:$D), SUMIFS(_xlpm.intervaloSoma, 'CEI_COMPLETA'!$A:$A, Ajustes!W$1, 'CEI_COMPLETA'!$B:$B, Ajustes!$Q4) ) -> 102164 | X4: =_xlfn.LET( _xlpm.intervaloSoma, IF($S4="R", 'CEI_COMPLETA'!$E:$E, 'CEI_COMPLETA'!$D:$D), SUMIFS(_xlpm.intervaloSoma, 'CEI_COMPLETA'!$A:$A, Ajustes!X$1, 'CEI_COMPLETA'!$B:$B, Ajustes!$Q4) ) -> 113120 | Y4: =_xlfn.LET( _xlpm.intervaloSoma, IF($S4="R", 'CEI_COMPLETA'!$E:$E, 'CEI_COMPLETA'!$D:$D), SUMIFS(_xlpm.intervaloSoma, 'CEI_COMPLETA'!$A:$A, Ajustes!Y$1, 'CEI_COMPLETA'!$B:$B, Ajustes!$Q4) ) -> 116178 | Z4: =_xlfn.LET( _xlpm.intervaloSoma, IF($S4="R", 'CEI_COMPLETA'!$E:$E, 'CEI_COMPLETA'!$D:$D), SUMIFS(_xlpm.intervaloSoma, 'CEI_COMPLETA'!$A:$A, Ajustes!Z$1, 'CEI_COMPLETA'!$B:$B, Ajustes!$Q4) ) -> 125113 | AA4: =_xlfn.LET( _xlpm.intervaloSoma, IF($S4="R", 'CEI_COMPLETA'!$E:$E, 'CEI_COMPLETA'!$D:$D), SUMIFS(_xlpm.intervaloSoma, 'CEI_COMPLETA'!$A:$A, Ajustes!AA$1, 'CEI_COMPLETA'!$B:$B, Ajustes!$Q4) ) -> 140587 | ... AC4: =_xlfn.LET( _xlpm.intervaloSoma, IF($S4="R", 'CEI_COMPLETA'!$E:$E, 'CEI_COMPLETA'!$D:$D), SUMIFS(_xlpm.intervaloSoma, 'CEI_COMPLETA'!$A:$A, Ajustes!AC$1, 'CEI_COMPLETA'!$B:$B, Ajustes!$Q4) ) -> 188950 | AD4: =_xlfn.LET( _xlpm.intervaloSoma, IF($S4="R", 'CEI_COMPLETA'!$E:$E, 'CEI_COMPLETA'!$D:$D), SUMIFS(_xlpm.intervaloSoma, 'CEI_COMPLETA'!$A:$A, Ajustes!AD$1, 'CEI_COMPLETA'!$B:$B, Ajustes!$R4) ) -> 232612 | AE4: =_xlfn.LET( _xlpm.intervaloSoma, IF($S4="R", 'CEI_COMPLETA'!$E:$E, 'CEI_COMPLETA'!$D:$D), SUMIFS(_xlpm.intervaloSoma, 'CEI_COMPLETA'!$A:$A, Ajustes!AE$1, 'CEI_COMPLETA'!$B:$B, Ajustes!$R4) ) -> 266481 | AF4: =_xlfn.LET( _xlpm.intervaloSoma, IF($S4="R", 'CEI_COMPLETA'!$E:$E, 'CEI_COMPLETA'!$D:$D), SUMIFS(_xlpm.intervaloSoma, 'CEI_COMPLETA'!$A:$A, Ajustes!AF$1, 'CEI_COMPLETA'!$B:$B, Ajustes!$R4) ) -> 316948 | AG4: =_xlfn.LET( _xlpm.intervaloSoma, IF($S4="R", 'CEI_COMPLETA'!$E:$E, 'CEI_COMPLETA'!$D:$D), SUMIFS(_xlpm.intervaloSoma, 'CEI_COMPLETA'!$A:$A, Ajustes!AG$1, 'CEI_COMPLETA'!$B:$B, Ajustes!$R4) ) -> 358359 | AH4: =_xlfn.LET( _xlpm.intervaloSoma, IF($S4="R", 'CEI_COMPLETA'!$E:$E, 'CEI_COMPLETA'!$D:$D), SUMIFS(_xlpm.intervaloSoma, 'CEI_COMPLETA'!$A:$A, Ajustes!AH$1, 'CEI_COMPLETA'!$B:$B, Ajustes!$R4) ) -> 371432 | AI4: =_xlfn.LET( _xlpm.intervaloSoma, IF($S4="R", 'CEI_COMPLETA'!$E:$E, 'CEI_COMPLETA'!$D:$D), SUMIFS(_xlpm.intervaloSoma, 'CEI_COMPLETA'!$A:$A, Ajustes!AI$1, 'CEI_COMPLETA'!$B:$B, Ajustes!$R4) ) -> 372116 | AJ4: =_xlfn.LET( _xlpm.intervaloSoma, IF($S4="R", 'CEI_COMPLETA'!$E:$E, 'CEI_COMPLETA'!$D:$D), SUMIFS(_xlpm.intervaloSoma, 'CEI_COMPLETA'!$A:$A, Ajustes!AJ$1, 'CEI_COMPLETA'!$B:$B, Ajustes!$R4) ) -> 361645 | AK4: =_xlfn.LET( _xlpm.intervaloSoma, IF($S4="R", 'CEI_COMPLETA'!$E:$E, 'CEI_COMPLETA'!$D:$D), SUMIFS(_xlpm.intervaloSoma, 'CEI_COMPLETA'!$A:$A, Ajustes!AK$1, 'CEI_COMPLETA'!$B:$B, Ajustes!$R4) ) -> 355517 | ... AO4: =_xlfn.LET( _xlpm.intervaloSoma, IF($S4="R", 'CEI_COMPLETA'!$E:$E, 'CEI_COMPLETA'!$D:$D), SUMIFS(_xlpm.intervaloSoma, 'CEI_COMPLETA'!$A:$A, Ajustes!AO$1, 'CEI_COMPLETA'!$B:$B, Ajustes!$R4) ) -> 499699
A5: Investimento Residencial | P5: NÃO HÁ
A6: Juros pessoais | P6: NÃO HÁ
A7: Transferências
A8: Poupança bruta | P8: CEI | Q8: B.8 | R8: B.8 | S8: R | T8: =_xlfn.LET( _xlpm.intervaloSoma, IF($S8="R", 'CEI_COMPLETA'!$E:$E, 'CEI_COMPLETA'!$D:$D), SUMIFS(_xlpm.intervaloSoma, 'CEI_COMPLETA'!$A:$A, Ajustes!T$1, 'CEI_COMPLETA'!$B:$B, Ajustes!$Q8) ) -> 107549 | U8: =_xlfn.LET( _xlpm.intervaloSoma, IF($S8="R", 'CEI_COMPLETA'!$E:$E, 'CEI_COMPLETA'!$D:$D), SUMIFS(_xlpm.intervaloSoma, 'CEI_COMPLETA'!$A:$A, Ajustes!U$1, 'CEI_COMPLETA'!$B:$B, Ajustes!$Q8) ) -> 116849 | V8: =_xlfn.LET( _xlpm.intervaloSoma, IF($S8="R", 'CEI_COMPLETA'!$E:$E, 'CEI_COMPLETA'!$D:$D), SUMIFS(_xlpm.intervaloSoma, 'CEI_COMPLETA'!$A:$A, Ajustes!V$1, 'CEI_COMPLETA'!$B:$B, Ajustes!$Q8) ) -> 136253 | W8: =_xlfn.LET( _xlpm.intervaloSoma, IF($S8="R", 'CEI_COMPLETA'!$E:$E, 'CEI_COMPLETA'!$D:$D), SUMIFS(_xlpm.intervaloSoma, 'CEI_COMPLETA'!$A:$A, Ajustes!W$1, 'CEI_COMPLETA'!$B:$B, Ajustes!$Q8) ) -> 148397 | X8: =_xlfn.LET( _xlpm.intervaloSoma, IF($S8="R", 'CEI_COMPLETA'!$E:$E, 'CEI_COMPLETA'!$D:$D), SUMIFS(_xlpm.intervaloSoma, 'CEI_COMPLETA'!$A:$A, Ajustes!X$1, 'CEI_COMPLETA'!$B:$B, Ajustes!$Q8) ) -> 161027 | Y8: =_xlfn.LET( _xlpm.intervaloSoma, IF($S8="R", 'CEI_COMPLETA'!$E:$E, 'CEI_COMPLETA'!$D:$D), SUMIFS(_xlpm.intervaloSoma, 'CEI_COMPLETA'!$A:$A, Ajustes!Y$1, 'CEI_COMPLETA'!$B:$B, Ajustes!$Q8) ) -> 163972 | Z8: =_xlfn.LET( _xlpm.intervaloSoma, IF($S8="R", 'CEI_COMPLETA'!$E:$E, 'CEI_COMPLETA'!$D:$D), SUMIFS(_xlpm.intervaloSoma, 'CEI_COMPLETA'!$A:$A, Ajustes!Z$1, 'CEI_COMPLETA'!$B:$B, Ajustes!$Q8) ) -> 175214 | AA8: =_xlfn.LET( _xlpm.intervaloSoma, IF($S8="R", 'CEI_COMPLETA'!$E:$E, 'CEI_COMPLETA'!$D:$D), SUMIFS(_xlpm.intervaloSoma, 'CEI_COMPLETA'!$A:$A, Ajustes!AA$1, 'CEI_COMPLETA'!$B:$B, Ajustes!$Q8) ) -> 189576 | ... AC8: =_xlfn.LET( _xlpm.intervaloSoma, IF($S8="R", 'CEI_COMPLETA'!$E:$E, 'CEI_COMPLETA'!$D:$D), SUMIFS(_xlpm.intervaloSoma, 'CEI_COMPLETA'!$A:$A, Ajustes!AC$1, 'CEI_COMPLETA'!$B:$B, Ajustes!$Q8) ) -> 231219 | AD8: =_xlfn.LET( _xlpm.intervaloSoma, IF($S8="R", 'CEI_COMPLETA'!$E:$E, 'CEI_COMPLETA'!$D:$D), SUMIFS(_xlpm.intervaloSoma, 'CEI_COMPLETA'!$A:$A, Ajustes!AD$1, 'CEI_COMPLETA'!$B:$B, Ajustes!$R8) ) -> 267784 | AE8: =_xlfn.LET( _xlpm.intervaloSoma, IF($S8="R", 'CEI_COMPLETA'!$E:$E, 'CEI_COMPLETA'!$D:$D), SUMIFS(_xlpm.intervaloSoma, 'CEI_COMPLETA'!$A:$A, Ajustes!AE$1, 'CEI_COMPLETA'!$B:$B, Ajustes!$R8) ) -> 296791 | AF8: =_xlfn.LET( _xlpm.intervaloSoma, IF($S8="R", 'CEI_COMPLETA'!$E:$E, 'CEI_COMPLETA'!$D:$D), SUMIFS(_xlpm.intervaloSoma, 'CEI_COMPLETA'!$A:$A, Ajustes!AF$1, 'CEI_COMPLETA'!$B:$B, Ajustes!$R8) ) -> 343646 | AG8: =_xlfn.LET( _xlpm.intervaloSoma, IF($S8="R", 'CEI_COMPLETA'!$E:$E, 'CEI_COMPLETA'!$D:$D), SUMIFS(_xlpm.intervaloSoma, 'CEI_COMPLETA'!$A:$A, Ajustes!AG$1, 'CEI_COMPLETA'!$B:$B, Ajustes!$R8) ) -> 385540 | AH8: =_xlfn.LET( _xlpm.intervaloSoma, IF($S8="R", 'CEI_COMPLETA'!$E:$E, 'CEI_COMPLETA'!$D:$D), SUMIFS(_xlpm.intervaloSoma, 'CEI_COMPLETA'!$A:$A, Ajustes!AH$1, 'CEI_COMPLETA'!$B:$B, Ajustes!$R8) ) -> 394290 | AI8: =_xlfn.LET( _xlpm.intervaloSoma, IF($S8="R", 'CEI_COMPLETA'!$E:$E, 'CEI_COMPLETA'!$D:$D), SUMIFS(_xlpm.intervaloSoma, 'CEI_COMPLETA'!$A:$A, Ajustes!AI$1, 'CEI_COMPLETA'!$B:$B, Ajustes!$R8) ) -> 493510 | AJ8: =_xlfn.LET( _xlpm.intervaloSoma, IF($S8="R", 'CEI_COMPLETA'!$E:$E, 'CEI_COMPLETA'!$D:$D), SUMIFS(_xlpm.intervaloSoma, 'CEI_COMPLETA'!$A:$A, Ajustes!AJ$1, 'CEI_COMPLETA'!$B:$B, Ajustes!$R8) ) -> 531088 | AK8: =_xlfn.LET( _xlpm.intervaloSoma, IF($S8="R", 'CEI_COMPLETA'!$E:$E, 'CEI_COMPLETA'!$D:$D), SUMIFS(_xlpm.intervaloSoma, 'CEI_COMPLETA'!$A:$A, Ajustes!AK$1, 'CEI_COMPLETA'!$B:$B, Ajustes!$R8) ) -> 563059 | ... AO8: =_xlfn.LET( _xlpm.intervaloSoma, IF($S8="R", 'CEI_COMPLETA'!$E:$E, 'CEI_COMPLETA'!$D:$D), SUMIFS(_xlpm.intervaloSoma, 'CEI_COMPLETA'!$A:$A, Ajustes!AO$1, 'CEI_COMPLETA'!$B:$B, Ajustes!$R8) ) -> 591302
A10: AJUSTES | T10: 2000 | U10: 2001 | V10: 2002 | W10: 2003 | X10: 2004 | Y10: 2005 | Z10: 2006 | AA10: 2007 | AB10: 2008 | AC10: 2009 | AD10: 2010 | AE10: 2011 | AF10: 2012 | AG10: 2013 | AH10: 2014 | AI10: 2015 | AJ10: 2016 | AK10: 2017 | AL10: 2018 | AM10: 2019 | AN10: 2020 | AO10: 2021
A11: Produção não-mercantil | I11: {=_xlfn.SWITCH(B11,0,0,"-",-1,"+",1)} -> 0 | J11: {=_xlfn.SWITCH(C11,0,0,"-",-1,"+",1)} -> 0 | K11: {=_xlfn.SWITCH(D11,0,0,"-",-1,"+",1)} -> 0 | L11: {=_xlfn.SWITCH(E11,0,0,"-",-1,"+",1)} -> 0 | M11: {=_xlfn.SWITCH(F11,0,0,"-",-1,"+",1)} -> 0 | N11: {=_xlfn.SWITCH(G11,0,0,"-",-1,"+",1)} -> 0 | O11: {=_xlfn.SWITCH(H11,0,0,"-",-1,"+",1)} -> 0 | T11: =SUM(T12:T14) -> 127301.62 | U11: =SUM(U12:U14) -> 131756.94 | V11: =SUM(V12:V14) -> 144068.99 | W11: =SUM(W12:W14) -> 156483.25 | X11: =SUM(X12:X14) -> 166144.09 | Y11: =SUM(Y12:Y14) -> 178614.98 | Z11: =SUM(Z12:Z14) -> 187466.72 | AA11: =SUM(AA12:AA14) -> 204036.25 | ... AO11: =SUM(AO12:AO14) -> 670410.08
A12: Aluguel Imputado | B12: - | C12: - | I12: {=_xlfn.SWITCH(B12,0,0,"-",-1,"+",1)} -> -1 | J12: {=_xlfn.SWITCH(C12,0,0,"-",-1,"+",1)} -> -1 | K12: {=_xlfn.SWITCH(D12,0,0,"-",-1,"+",1)} -> 0 | L12: {=_xlfn.SWITCH(E12,0,0,"-",-1,"+",1)} -> 0 | M12: {=_xlfn.SWITCH(F12,0,0,"-",-1,"+",1)} -> 0 | N12: {=_xlfn.SWITCH(G12,0,0,"-",-1,"+",1)} -> 0 | O12: {=_xlfn.SWITCH(H12,0,0,"-",-1,"+",1)} -> 0 | P12: TRU -Tabela 2 - Usos de bens e serviços - Descrição do Produto: Aluguel Imputado - aba demanda - coluna Consumo das Famílias | T12: 107290 | U12: 111313 | V12: 120331 | W12: 130517 | X12: 137783 | Y12: 149147 | Z12: 155582 | AA12: 168313 | AB12: 180243 | AC12: 199961 | AD12: 216622 | AE12: 249695 | AF12: 287350 | AG12: 335975 | AH12: 367290 | AI12: 400237 | AJ12: 423533 | AK12: 441426 | AL12: 460205 | AM12: 482425 | AN12: 516019 | AO12: 547406
A13: Autoconsumo (Agropecuária) | B13: - | C13: - | I13: {=_xlfn.SWITCH(B13,0,0,"-",-1,"+",1)} -> -1 | J13: {=_xlfn.SWITCH(C13,0,0,"-",-1,"+",1)} -> -1 | K13: {=_xlfn.SWITCH(D13,0,0,"-",-1,"+",1)} -> 0 | L13: {=_xlfn.SWITCH(E13,0,0,"-",-1,"+",1)} -> 0 | M13: {=_xlfn.SWITCH(F13,0,0,"-",-1,"+",1)} -> 0 | N13: {=_xlfn.SWITCH(G13,0,0,"-",-1,"+",1)} -> 0 | O13: {=_xlfn.SWITCH(H13,0,0,"-",-1,"+",1)} -> 0 | P13: POF + TRU | T13: 4490.548 | U13: 4922.3507 | V13: 5726.3239 | W13: 6488.0395 | X13: 6794.0781 | Y13: 7317.8925 | Z13: 8031.0548 | AA13: 8919.4675 | AB13: 10892.737 | AC13: 11473.96 | AD13: 12676.56 | AE13: 15237.845 | AF13: 16841.694 | AG13: 19470.841 | AH13: 20889.906 | AI13: 22640.026 | AJ13: 25501.369 | AK13: 25887.689 | AL13: 26236.004 | AM13: 28451.372 | AN13: 32732.573 | AO13: 39050.084
A14: Construção | B14: - | C14: - | I14: {=_xlfn.SWITCH(B14,0,0,"-",-1,"+",1)} -> -1 | J14: {=_xlfn.SWITCH(C14,0,0,"-",-1,"+",1)} -> -1 | K14: {=_xlfn.SWITCH(D14,0,0,"-",-1,"+",1)} -> 0 | L14: {=_xlfn.SWITCH(E14,0,0,"-",-1,"+",1)} -> 0 | M14: {=_xlfn.SWITCH(F14,0,0,"-",-1,"+",1)} -> 0 | N14: {=_xlfn.SWITCH(G14,0,0,"-",-1,"+",1)} -> 0 | O14: {=_xlfn.SWITCH(H14,0,0,"-",-1,"+",1)} -> 0 | P14: tab08, tab17, CEI | T14: 15521.071 | U14: 15521.589 | V14: 18011.669 | W14: 19478.213 | X14: 21567.01 | Y14: 22150.085 | Z14: 23853.668 | AA14: 26803.781 | AB14: 29797.2 | AC14: 36024.633 | AD14: 44349 | AE14: 48841 | AF14: 54094 | AG14: 58385 | AH14: 61187 | AI14: 63066 | AJ14: 63990 | AK14: 63806 | AL14: 68076 | AM14: 72340 | AN14: 76292 | AO14: 83954
A15: Investimento Residencial | I15: {=_xlfn.SWITCH(B15,0,0,"-",-1,"+",1)} -> 0 | J15: {=_xlfn.SWITCH(C15,0,0,"-",-1,"+",1)} -> 0 | K15: {=_xlfn.SWITCH(D15,0,0,"-",-1,"+",1)} -> 0 | L15: {=_xlfn.SWITCH(E15,0,0,"-",-1,"+",1)} -> 0 | M15: {=_xlfn.SWITCH(F15,0,0,"-",-1,"+",1)} -> 0 | N15: {=_xlfn.SWITCH(G15,0,0,"-",-1,"+",1)} -> 0 | O15: {=_xlfn.SWITCH(H15,0,0,"-",-1,"+",1)} -> 0 | T15: =T16 -> 66827.775 | U15: =U16 -> 66830.007 | V15: =V16 -> 77551.337 | W15: =W16 -> 83865.712 | X15: =X16 -> 92859.273 | Y15: =Y16 -> 95369.768 | Z15: =Z16 -> 102704.74 | AA15: =AA16 -> 115406.8 | ... AO15: =AO16 -> 376554.67
A16: Construção Residencial (total) | D16: - | E16: + | H16: - | I16: {=_xlfn.SWITCH(B16,0,0,"-",-1,"+",1)} -> 0 | J16: {=_xlfn.SWITCH(C16,0,0,"-",-1,"+",1)} -> 0 | K16: {=_xlfn.SWITCH(D16,0,0,"-",-1,"+",1)} -> -1 | L16: {=_xlfn.SWITCH(E16,0,0,"-",-1,"+",1)} -> 1 | M16: {=_xlfn.SWITCH(F16,0,0,"-",-1,"+",1)} -> 0 | N16: {=_xlfn.SWITCH(G16,0,0,"-",-1,"+",1)} -> 0 | O16: {=_xlfn.SWITCH(H16,0,0,"-",-1,"+",1)} -> -1 | P16: tab08, tab17, CEI | T16: 66827.775 | U16: 66830.007 | V16: 77551.337 | W16: 83865.712 | X16: 92859.273 | Y16: 95369.768 | Z16: 102704.74 | AA16: 115406.8 | AB16: 128295.31 | AC16: 155108.25 | AD16: 190949.78 | AE16: 220753.09 | AF16: 264764.19 | AG16: 300261.66 | AH16: 316290.69 | AI16: 324841.77 | AJ16: 316289.19 | AK16: 289667.52 | AL16: 293380.55 | AM16: 305428.36 | AN16: 318252.09 | AO16: 376554.67
A17: Construção Residencial (não-mercantil) | E17: - | I17: {=_xlfn.SWITCH(B17,0,0,"-",-1,"+",1)} -> 0 | J17: {=_xlfn.SWITCH(C17,0,0,"-",-1,"+",1)} -> 0 | K17: {=_xlfn.SWITCH(D17,0,0,"-",-1,"+",1)} -> 0 | L17: {=_xlfn.SWITCH(E17,0,0,"-",-1,"+",1)} -> -1 | M17: {=_xlfn.SWITCH(F17,0,0,"-",-1,"+",1)} -> 0 | N17: {=_xlfn.SWITCH(G17,0,0,"-",-1,"+",1)} -> 0 | O17: {=_xlfn.SWITCH(H17,0,0,"-",-1,"+",1)} -> 0 | P17: tab08, tab17, CEI | T17: 7482.7873 | U17: 7483.0372 | V17: 8683.5176 | W17: 9390.5459 | X17: 10397.566 | Y17: 10678.669 | Z17: 11499.975 | AA17: 12922.24 | AB17: 14365.382 | AC17: 17367.659 | AD17: 21380.879 | AE17: 23808.771 | AF17: 27712.932 | AG17: 31029.682 | AH17: 32588.778 | AI17: 36419.228 | AJ17: 39015.831 | AK17: 39156.484 | AL17: 42045.266 | AM17: 43819.625 | AN17: 43621.445 | AO17: 47315.41
A18: Renda de Propriedade sem acesso direto das famílias | B18: - | H18: - | I18: {=_xlfn.SWITCH(B18,0,0,"-",-1,"+",1)} -> -1 | J18: {=_xlfn.SWITCH(C18,0,0,"-",-1,"+",1)} -> 0 | K18: {=_xlfn.SWITCH(D18,0,0,"-",-1,"+",1)} -> 0 | L18: {=_xlfn.SWITCH(E18,0,0,"-",-1,"+",1)} -> 0 | M18: {=_xlfn.SWITCH(F18,0,0,"-",-1,"+",1)} -> 0 | N18: {=_xlfn.SWITCH(G18,0,0,"-",-1,"+",1)} -> 0 | O18: {=_xlfn.SWITCH(H18,0,0,"-",-1,"+",1)} -> -1 | P18: CEI | Q18: D.43-D.44 | R18: D.44 | S18: R | T18: =_xlfn.LET( _xlpm.intervaloSoma, IF($S18="R", 'CEI_COMPLETA'!$E:$E, 'CEI_COMPLETA'!$D:$D), SUMIFS(_xlpm.intervaloSoma, 'CEI_COMPLETA'!$A:$A, Ajustes!T$1, 'CEI_COMPLETA'!$B:$B, Ajustes!$Q18) ) -> 11331 | U18: =_xlfn.LET( _xlpm.intervaloSoma, IF($S18="R", 'CEI_COMPLETA'!$E:$E, 'CEI_COMPLETA'!$D:$D), SUMIFS(_xlpm.intervaloSoma, 'CEI_COMPLETA'!$A:$A, Ajustes!U$1, 'CEI_COMPLETA'!$B:$B, Ajustes!$Q18) ) -> 14687 | V18: =_xlfn.LET( _xlpm.intervaloSoma, IF($S18="R", 'CEI_COMPLETA'!$E:$E, 'CEI_COMPLETA'!$D:$D), SUMIFS(_xlpm.intervaloSoma, 'CEI_COMPLETA'!$A:$A, Ajustes!V$1, 'CEI_COMPLETA'!$B:$B, Ajustes!$Q18) ) -> 15190 | W18: =_xlfn.LET( _xlpm.intervaloSoma, IF($S18="R", 'CEI_COMPLETA'!$E:$E, 'CEI_COMPLETA'!$D:$D), SUMIFS(_xlpm.intervaloSoma, 'CEI_COMPLETA'!$A:$A, Ajustes!W$1, 'CEI_COMPLETA'!$B:$B, Ajustes!$Q18) ) -> 27074 | X18: =_xlfn.LET( _xlpm.intervaloSoma, IF($S18="R", 'CEI_COMPLETA'!$E:$E, 'CEI_COMPLETA'!$D:$D), SUMIFS(_xlpm.intervaloSoma, 'CEI_COMPLETA'!$A:$A, Ajustes!X$1, 'CEI_COMPLETA'!$B:$B, Ajustes!$Q18) ) -> 24602 | Y18: =_xlfn.LET( _xlpm.intervaloSoma, IF($S18="R", 'CEI_COMPLETA'!$E:$E, 'CEI_COMPLETA'!$D:$D), SUMIFS(_xlpm.intervaloSoma, 'CEI_COMPLETA'!$A:$A, Ajustes!Y$1, 'CEI_COMPLETA'!$B:$B, Ajustes!$Q18) ) -> 24607 | Z18: =_xlfn.LET( _xlpm.intervaloSoma, IF($S18="R", 'CEI_COMPLETA'!$E:$E, 'CEI_COMPLETA'!$D:$D), SUMIFS(_xlpm.intervaloSoma, 'CEI_COMPLETA'!$A:$A, Ajustes!Z$1, 'CEI_COMPLETA'!$B:$B, Ajustes!$Q18) ) -> 28239 | AA18: =_xlfn.LET( _xlpm.intervaloSoma, IF($S18="R", 'CEI_COMPLETA'!$E:$E, 'CEI_COMPLETA'!$D:$D), SUMIFS(_xlpm.intervaloSoma, 'CEI_COMPLETA'!$A:$A, Ajustes!AA$1, 'CEI_COMPLETA'!$B:$B, Ajustes!$Q18) ) -> 30586 | ... AC18: =_xlfn.LET( _xlpm.intervaloSoma, IF($S18="R", 'CEI_COMPLETA'!$E:$E, 'CEI_COMPLETA'!$D:$D), SUMIFS(_xlpm.intervaloSoma, 'CEI_COMPLETA'!$A:$A, Ajustes!AC$1, 'CEI_COMPLETA'!$B:$B, Ajustes!$Q18) ) -> 42827 | AD18: =_xlfn.LET( _xlpm.intervaloSoma, IF($S18="R", 'CEI_COMPLETA'!$E:$E, 'CEI_COMPLETA'!$D:$D), SUMIFS(_xlpm.intervaloSoma, 'CEI_COMPLETA'!$A:$A, Ajustes!AD$1, 'CEI_COMPLETA'!$B:$B, Ajustes!$R18) ) -> 60549 | AE18: =_xlfn.LET( _xlpm.intervaloSoma, IF($S18="R", 'CEI_COMPLETA'!$E:$E, 'CEI_COMPLETA'!$D:$D), SUMIFS(_xlpm.intervaloSoma, 'CEI_COMPLETA'!$A:$A, Ajustes!AE$1, 'CEI_COMPLETA'!$B:$B, Ajustes!$R18) ) -> 52629 | AF18: =_xlfn.LET( _xlpm.intervaloSoma, IF($S18="R", 'CEI_COMPLETA'!$E:$E, 'CEI_COMPLETA'!$D:$D), SUMIFS(_xlpm.intervaloSoma, 'CEI_COMPLETA'!$A:$A, Ajustes!AF$1, 'CEI_COMPLETA'!$B:$B, Ajustes!$R18) ) -> 80269 | AG18: =_xlfn.LET( _xlpm.intervaloSoma, IF($S18="R", 'CEI_COMPLETA'!$E:$E, 'CEI_COMPLETA'!$D:$D), SUMIFS(_xlpm.intervaloSoma, 'CEI_COMPLETA'!$A:$A, Ajustes!AG$1, 'CEI_COMPLETA'!$B:$B, Ajustes!$R18) ) -> 54208 | AH18: =_xlfn.LET( _xlpm.intervaloSoma, IF($S18="R", 'CEI_COMPLETA'!$E:$E, 'CEI_COMPLETA'!$D:$D), SUMIFS(_xlpm.intervaloSoma, 'CEI_COMPLETA'!$A:$A, Ajustes!AH$1, 'CEI_COMPLETA'!$B:$B, Ajustes!$R18) ) -> 58846 | AI18: =_xlfn.LET( _xlpm.intervaloSoma, IF($S18="R", 'CEI_COMPLETA'!$E:$E, 'CEI_COMPLETA'!$D:$D), SUMIFS(_xlpm.intervaloSoma, 'CEI_COMPLETA'!$A:$A, Ajustes!AI$1, 'CEI_COMPLETA'!$B:$B, Ajustes!$R18) ) -> 99434 | AJ18: =_xlfn.LET( _xlpm.intervaloSoma, IF($S18="R", 'CEI_COMPLETA'!$E:$E, 'CEI_COMPLETA'!$D:$D), SUMIFS(_xlpm.intervaloSoma, 'CEI_COMPLETA'!$A:$A, Ajustes!AJ$1, 'CEI_COMPLETA'!$B:$B, Ajustes!$R18) ) -> 87702 | AK18: =_xlfn.LET( _xlpm.intervaloSoma, IF($S18="R", 'CEI_COMPLETA'!$E:$E, 'CEI_COMPLETA'!$D:$D), SUMIFS(_xlpm.intervaloSoma, 'CEI_COMPLETA'!$A:$A, Ajustes!AK$1, 'CEI_COMPLETA'!$B:$B, Ajustes!$R18) ) -> 74085 | ... AO18: =_xlfn.LET( _xlpm.intervaloSoma, IF($S18="R", 'CEI_COMPLETA'!$E:$E, 'CEI_COMPLETA'!$D:$D), SUMIFS(_xlpm.intervaloSoma, 'CEI_COMPLETA'!$A:$A, Ajustes!AO$1, 'CEI_COMPLETA'!$B:$B, Ajustes!$R18) ) -> 81699
A19: Rendimento de investimentos atribuído a acionistas de fundos de investimento | I19: {=_xlfn.SWITCH(B19,0,0,"-",-1,"+",1)} -> 0 | J19: {=_xlfn.SWITCH(C19,0,0,"-",-1,"+",1)} -> 0 | K19: {=_xlfn.SWITCH(D19,0,0,"-",-1,"+",1)} -> 0 | L19: {=_xlfn.SWITCH(E19,0,0,"-",-1,"+",1)} -> 0 | M19: {=_xlfn.SWITCH(F19,0,0,"-",-1,"+",1)} -> 0 | N19: {=_xlfn.SWITCH(G19,0,0,"-",-1,"+",1)} -> 0 | O19: {=_xlfn.SWITCH(H19,0,0,"-",-1,"+",1)} -> 0 | P19: CEI | R19: D.443 | S19: R | T19: =_xlfn.LET( _xlpm.intervaloSoma, IF($S19="R", 'CEI_COMPLETA'!$E:$E, 'CEI_COMPLETA'!$D:$D), SUMIFS(_xlpm.intervaloSoma, 'CEI_COMPLETA'!$A:$A, Ajustes!T$1, 'CEI_COMPLETA'!$B:$B, Ajustes!$Q19) ) -> 0 | U19: =_xlfn.LET( _xlpm.intervaloSoma, IF($S19="R", 'CEI_COMPLETA'!$E:$E, 'CEI_COMPLETA'!$D:$D), SUMIFS(_xlpm.intervaloSoma, 'CEI_COMPLETA'!$A:$A, Ajustes!U$1, 'CEI_COMPLETA'!$B:$B, Ajustes!$Q19) ) -> 0 | V19: =_xlfn.LET( _xlpm.intervaloSoma, IF($S19="R", 'CEI_COMPLETA'!$E:$E, 'CEI_COMPLETA'!$D:$D), SUMIFS(_xlpm.intervaloSoma, 'CEI_COMPLETA'!$A:$A, Ajustes!V$1, 'CEI_COMPLETA'!$B:$B, Ajustes!$Q19) ) -> 0 | W19: =_xlfn.LET( _xlpm.intervaloSoma, IF($S19="R", 'CEI_COMPLETA'!$E:$E, 'CEI_COMPLETA'!$D:$D), SUMIFS(_xlpm.intervaloSoma, 'CEI_COMPLETA'!$A:$A, Ajustes!W$1, 'CEI_COMPLETA'!$B:$B, Ajustes!$Q19) ) -> 0 | X19: =_xlfn.LET( _xlpm.intervaloSoma, IF($S19="R", 'CEI_COMPLETA'!$E:$E, 'CEI_COMPLETA'!$D:$D), SUMIFS(_xlpm.intervaloSoma, 'CEI_COMPLETA'!$A:$A, Ajustes!X$1, 'CEI_COMPLETA'!$B:$B, Ajustes!$Q19) ) -> 0 | Y19: =_xlfn.LET( _xlpm.intervaloSoma, IF($S19="R", 'CEI_COMPLETA'!$E:$E, 'CEI_COMPLETA'!$D:$D), SUMIFS(_xlpm.intervaloSoma, 'CEI_COMPLETA'!$A:$A, Ajustes!Y$1, 'CEI_COMPLETA'!$B:$B, Ajustes!$Q19) ) -> 0 | Z19: =_xlfn.LET( _xlpm.intervaloSoma, IF($S19="R", 'CEI_COMPLETA'!$E:$E, 'CEI_COMPLETA'!$D:$D), SUMIFS(_xlpm.intervaloSoma, 'CEI_COMPLETA'!$A:$A, Ajustes!Z$1, 'CEI_COMPLETA'!$B:$B, Ajustes!$Q19) ) -> 0 | AA19: =_xlfn.LET( _xlpm.intervaloSoma, IF($S19="R", 'CEI_COMPLETA'!$E:$E, 'CEI_COMPLETA'!$D:$D), SUMIFS(_xlpm.intervaloSoma, 'CEI_COMPLETA'!$A:$A, Ajustes!AA$1, 'CEI_COMPLETA'!$B:$B, Ajustes!$Q19) ) -> 0 | ... AC19: =_xlfn.LET( _xlpm.intervaloSoma, IF($S19="R", 'CEI_COMPLETA'!$E:$E, 'CEI_COMPLETA'!$D:$D), SUMIFS(_xlpm.intervaloSoma, 'CEI_COMPLETA'!$A:$A, Ajustes!AC$1, 'CEI_COMPLETA'!$B:$B, Ajustes!$Q19) ) -> 0 | AD19: =_xlfn.LET( _xlpm.intervaloSoma, IF($S19="R", 'CEI_COMPLETA'!$E:$E, 'CEI_COMPLETA'!$D:$D), SUMIFS(_xlpm.intervaloSoma, 'CEI_COMPLETA'!$A:$A, Ajustes!AD$1, 'CEI_COMPLETA'!$B:$B, Ajustes!$R19) ) -> 7010 | AE19: =_xlfn.LET( _xlpm.intervaloSoma, IF($S19="R", 'CEI_COMPLETA'!$E:$E, 'CEI_COMPLETA'!$D:$D), SUMIFS(_xlpm.intervaloSoma, 'CEI_COMPLETA'!$A:$A, Ajustes!AE$1, 'CEI_COMPLETA'!$B:$B, Ajustes!$R19) ) -> 7694 | AF19: =_xlfn.LET( _xlpm.intervaloSoma, IF($S19="R", 'CEI_COMPLETA'!$E:$E, 'CEI_COMPLETA'!$D:$D), SUMIFS(_xlpm.intervaloSoma, 'CEI_COMPLETA'!$A:$A, Ajustes!AF$1, 'CEI_COMPLETA'!$B:$B, Ajustes!$R19) ) -> 12594 | AG19: =_xlfn.LET( _xlpm.intervaloSoma, IF($S19="R", 'CEI_COMPLETA'!$E:$E, 'CEI_COMPLETA'!$D:$D), SUMIFS(_xlpm.intervaloSoma, 'CEI_COMPLETA'!$A:$A, Ajustes!AG$1, 'CEI_COMPLETA'!$B:$B, Ajustes!$R19) ) -> 14142 | AH19: =_xlfn.LET( _xlpm.intervaloSoma, IF($S19="R", 'CEI_COMPLETA'!$E:$E, 'CEI_COMPLETA'!$D:$D), SUMIFS(_xlpm.intervaloSoma, 'CEI_COMPLETA'!$A:$A, Ajustes!AH$1, 'CEI_COMPLETA'!$B:$B, Ajustes!$R19) ) -> 12853 | AI19: =_xlfn.LET( _xlpm.intervaloSoma, IF($S19="R", 'CEI_COMPLETA'!$E:$E, 'CEI_COMPLETA'!$D:$D), SUMIFS(_xlpm.intervaloSoma, 'CEI_COMPLETA'!$A:$A, Ajustes!AI$1, 'CEI_COMPLETA'!$B:$B, Ajustes!$R19) ) -> 14074 | AJ19: =_xlfn.LET( _xlpm.intervaloSoma, IF($S19="R", 'CEI_COMPLETA'!$E:$E, 'CEI_COMPLETA'!$D:$D), SUMIFS(_xlpm.intervaloSoma, 'CEI_COMPLETA'!$A:$A, Ajustes!AJ$1, 'CEI_COMPLETA'!$B:$B, Ajustes!$R19) ) -> 16607 | AK19: =_xlfn.LET( _xlpm.intervaloSoma, IF($S19="R", 'CEI_COMPLETA'!$E:$E, 'CEI_COMPLETA'!$D:$D), SUMIFS(_xlpm.intervaloSoma, 'CEI_COMPLETA'!$A:$A, Ajustes!AK$1, 'CEI_COMPLETA'!$B:$B, Ajustes!$R19) ) -> 20365 | ... AO19: =_xlfn.LET( _xlpm.intervaloSoma, IF($S19="R", 'CEI_COMPLETA'!$E:$E, 'CEI_COMPLETA'!$D:$D), SUMIFS(_xlpm.intervaloSoma, 'CEI_COMPLETA'!$A:$A, Ajustes!AO$1, 'CEI_COMPLETA'!$B:$B, Ajustes!$R19) ) -> 7379
A20: Rendimento de investimentos atribuído a detentores de apólices de seguros | I20: {=_xlfn.SWITCH(B20,0,0,"-",-1,"+",1)} -> 0 | J20: {=_xlfn.SWITCH(C20,0,0,"-",-1,"+",1)} -> 0 | K20: {=_xlfn.SWITCH(D20,0,0,"-",-1,"+",1)} -> 0 | L20: {=_xlfn.SWITCH(E20,0,0,"-",-1,"+",1)} -> 0 | M20: {=_xlfn.SWITCH(F20,0,0,"-",-1,"+",1)} -> 0 | N20: {=_xlfn.SWITCH(G20,0,0,"-",-1,"+",1)} -> 0 | O20: {=_xlfn.SWITCH(H20,0,0,"-",-1,"+",1)} -> 0 | P20: CEI | R20: D.441 | S20: R | T20: =_xlfn.LET( _xlpm.intervaloSoma, IF($S20="R", 'CEI_COMPLETA'!$E:$E, 'CEI_COMPLETA'!$D:$D), SUMIFS(_xlpm.intervaloSoma, 'CEI_COMPLETA'!$A:$A, Ajustes!T$1, 'CEI_COMPLETA'!$B:$B, Ajustes!$Q20) ) -> 0 | U20: =_xlfn.LET( _xlpm.intervaloSoma, IF($S20="R", 'CEI_COMPLETA'!$E:$E, 'CEI_COMPLETA'!$D:$D), SUMIFS(_xlpm.intervaloSoma, 'CEI_COMPLETA'!$A:$A, Ajustes!U$1, 'CEI_COMPLETA'!$B:$B, Ajustes!$Q20) ) -> 0 | V20: =_xlfn.LET( _xlpm.intervaloSoma, IF($S20="R", 'CEI_COMPLETA'!$E:$E, 'CEI_COMPLETA'!$D:$D), SUMIFS(_xlpm.intervaloSoma, 'CEI_COMPLETA'!$A:$A, Ajustes!V$1, 'CEI_COMPLETA'!$B:$B, Ajustes!$Q20) ) -> 0 | W20: =_xlfn.LET( _xlpm.intervaloSoma, IF($S20="R", 'CEI_COMPLETA'!$E:$E, 'CEI_COMPLETA'!$D:$D), SUMIFS(_xlpm.intervaloSoma, 'CEI_COMPLETA'!$A:$A, Ajustes!W$1, 'CEI_COMPLETA'!$B:$B, Ajustes!$Q20) ) -> 0 | X20: =_xlfn.LET( _xlpm.intervaloSoma, IF($S20="R", 'CEI_COMPLETA'!$E:$E, 'CEI_COMPLETA'!$D:$D), SUMIFS(_xlpm.intervaloSoma, 'CEI_COMPLETA'!$A:$A, Ajustes!X$1, 'CEI_COMPLETA'!$B:$B, Ajustes!$Q20) ) -> 0 | Y20: =_xlfn.LET( _xlpm.intervaloSoma, IF($S20="R", 'CEI_COMPLETA'!$E:$E, 'CEI_COMPLETA'!$D:$D), SUMIFS(_xlpm.intervaloSoma, 'CEI_COMPLETA'!$A:$A, Ajustes!Y$1, 'CEI_COMPLETA'!$B:$B, Ajustes!$Q20) ) -> 0 | Z20: =_xlfn.LET( _xlpm.intervaloSoma, IF($S20="R", 'CEI_COMPLETA'!$E:$E, 'CEI_COMPLETA'!$D:$D), SUMIFS(_xlpm.intervaloSoma, 'CEI_COMPLETA'!$A:$A, Ajustes!Z$1, 'CEI_COMPLETA'!$B:$B, Ajustes!$Q20) ) -> 0 | AA20: =_xlfn.LET( _xlpm.intervaloSoma, IF($S20="R", 'CEI_COMPLETA'!$E:$E, 'CEI_COMPLETA'!$D:$D), SUMIFS(_xlpm.intervaloSoma, 'CEI_COMPLETA'!$A:$A, Ajustes!AA$1, 'CEI_COMPLETA'!$B:$B, Ajustes!$Q20) ) -> 0 | ... AC20: =_xlfn.LET( _xlpm.intervaloSoma, IF($S20="R", 'CEI_COMPLETA'!$E:$E, 'CEI_COMPLETA'!$D:$D), SUMIFS(_xlpm.intervaloSoma, 'CEI_COMPLETA'!$A:$A, Ajustes!AC$1, 'CEI_COMPLETA'!$B:$B, Ajustes!$Q20) ) -> 0 | AD20: =_xlfn.LET( _xlpm.intervaloSoma, IF($S20="R", 'CEI_COMPLETA'!$E:$E, 'CEI_COMPLETA'!$D:$D), SUMIFS(_xlpm.intervaloSoma, 'CEI_COMPLETA'!$A:$A, Ajustes!AD$1, 'CEI_COMPLETA'!$B:$B, Ajustes!$R20) ) -> 3863 | AE20: =_xlfn.LET( _xlpm.intervaloSoma, IF($S20="R", 'CEI_COMPLETA'!$E:$E, 'CEI_COMPLETA'!$D:$D), SUMIFS(_xlpm.intervaloSoma, 'CEI_COMPLETA'!$A:$A, Ajustes!AE$1, 'CEI_COMPLETA'!$B:$B, Ajustes!$R20) ) -> 4056 | AF20: =_xlfn.LET( _xlpm.intervaloSoma, IF($S20="R", 'CEI_COMPLETA'!$E:$E, 'CEI_COMPLETA'!$D:$D), SUMIFS(_xlpm.intervaloSoma, 'CEI_COMPLETA'!$A:$A, Ajustes!AF$1, 'CEI_COMPLETA'!$B:$B, Ajustes!$R20) ) -> 5027 | AG20: =_xlfn.LET( _xlpm.intervaloSoma, IF($S20="R", 'CEI_COMPLETA'!$E:$E, 'CEI_COMPLETA'!$D:$D), SUMIFS(_xlpm.intervaloSoma, 'CEI_COMPLETA'!$A:$A, Ajustes!AG$1, 'CEI_COMPLETA'!$B:$B, Ajustes!$R20) ) -> 3371 | AH20: =_xlfn.LET( _xlpm.intervaloSoma, IF($S20="R", 'CEI_COMPLETA'!$E:$E, 'CEI_COMPLETA'!$D:$D), SUMIFS(_xlpm.intervaloSoma, 'CEI_COMPLETA'!$A:$A, Ajustes!AH$1, 'CEI_COMPLETA'!$B:$B, Ajustes!$R20) ) -> 5386 | AI20: =_xlfn.LET( _xlpm.intervaloSoma, IF($S20="R", 'CEI_COMPLETA'!$E:$E, 'CEI_COMPLETA'!$D:$D), SUMIFS(_xlpm.intervaloSoma, 'CEI_COMPLETA'!$A:$A, Ajustes!AI$1, 'CEI_COMPLETA'!$B:$B, Ajustes!$R20) ) -> 5933 | AJ20: =_xlfn.LET( _xlpm.intervaloSoma, IF($S20="R", 'CEI_COMPLETA'!$E:$E, 'CEI_COMPLETA'!$D:$D), SUMIFS(_xlpm.intervaloSoma, 'CEI_COMPLETA'!$A:$A, Ajustes!AJ$1, 'CEI_COMPLETA'!$B:$B, Ajustes!$R20) ) -> 5988 | AK20: =_xlfn.LET( _xlpm.intervaloSoma, IF($S20="R", 'CEI_COMPLETA'!$E:$E, 'CEI_COMPLETA'!$D:$D), SUMIFS(_xlpm.intervaloSoma, 'CEI_COMPLETA'!$A:$A, Ajustes!AK$1, 'CEI_COMPLETA'!$B:$B, Ajustes!$R20) ) -> 5335 | ... AO20: =_xlfn.LET( _xlpm.intervaloSoma, IF($S20="R", 'CEI_COMPLETA'!$E:$E, 'CEI_COMPLETA'!$D:$D), SUMIFS(_xlpm.intervaloSoma, 'CEI_COMPLETA'!$A:$A, Ajustes!AO$1, 'CEI_COMPLETA'!$B:$B, Ajustes!$R20) ) -> 3891
A21: Rendimento de investimentos a pagar sobre direitos de pensão | I21: {=_xlfn.SWITCH(B21,0,0,"-",-1,"+",1)} -> 0 | J21: {=_xlfn.SWITCH(C21,0,0,"-",-1,"+",1)} -> 0 | K21: {=_xlfn.SWITCH(D21,0,0,"-",-1,"+",1)} -> 0 | L21: {=_xlfn.SWITCH(E21,0,0,"-",-1,"+",1)} -> 0 | M21: {=_xlfn.SWITCH(F21,0,0,"-",-1,"+",1)} -> 0 | N21: {=_xlfn.SWITCH(G21,0,0,"-",-1,"+",1)} -> 0 | O21: {=_xlfn.SWITCH(H21,0,0,"-",-1,"+",1)} -> 0 | P21: CEI | R21: D.442 | S21: R | T21: =_xlfn.LET( _xlpm.intervaloSoma, IF($S21="R", 'CEI_COMPLETA'!$E:$E, 'CEI_COMPLETA'!$D:$D), SUMIFS(_xlpm.intervaloSoma, 'CEI_COMPLETA'!$A:$A, Ajustes!T$1, 'CEI_COMPLETA'!$B:$B, Ajustes!$Q21) ) -> 0 | U21: =_xlfn.LET( _xlpm.intervaloSoma, IF($S21="R", 'CEI_COMPLETA'!$E:$E, 'CEI_COMPLETA'!$D:$D), SUMIFS(_xlpm.intervaloSoma, 'CEI_COMPLETA'!$A:$A, Ajustes!U$1, 'CEI_COMPLETA'!$B:$B, Ajustes!$Q21) ) -> 0 | V21: =_xlfn.LET( _xlpm.intervaloSoma, IF($S21="R", 'CEI_COMPLETA'!$E:$E, 'CEI_COMPLETA'!$D:$D), SUMIFS(_xlpm.intervaloSoma, 'CEI_COMPLETA'!$A:$A, Ajustes!V$1, 'CEI_COMPLETA'!$B:$B, Ajustes!$Q21) ) -> 0 | W21: =_xlfn.LET( _xlpm.intervaloSoma, IF($S21="R", 'CEI_COMPLETA'!$E:$E, 'CEI_COMPLETA'!$D:$D), SUMIFS(_xlpm.intervaloSoma, 'CEI_COMPLETA'!$A:$A, Ajustes!W$1, 'CEI_COMPLETA'!$B:$B, Ajustes!$Q21) ) -> 0 | X21: =_xlfn.LET( _xlpm.intervaloSoma, IF($S21="R", 'CEI_COMPLETA'!$E:$E, 'CEI_COMPLETA'!$D:$D), SUMIFS(_xlpm.intervaloSoma, 'CEI_COMPLETA'!$A:$A, Ajustes!X$1, 'CEI_COMPLETA'!$B:$B, Ajustes!$Q21) ) -> 0 | Y21: =_xlfn.LET( _xlpm.intervaloSoma, IF($S21="R", 'CEI_COMPLETA'!$E:$E, 'CEI_COMPLETA'!$D:$D), SUMIFS(_xlpm.intervaloSoma, 'CEI_COMPLETA'!$A:$A, Ajustes!Y$1, 'CEI_COMPLETA'!$B:$B, Ajustes!$Q21) ) -> 0 | Z21: =_xlfn.LET( _xlpm.intervaloSoma, IF($S21="R", 'CEI_COMPLETA'!$E:$E, 'CEI_COMPLETA'!$D:$D), SUMIFS(_xlpm.intervaloSoma, 'CEI_COMPLETA'!$A:$A, Ajustes!Z$1, 'CEI_COMPLETA'!$B:$B, Ajustes!$Q21) ) -> 0 | AA21: =_xlfn.LET( _xlpm.intervaloSoma, IF($S21="R", 'CEI_COMPLETA'!$E:$E, 'CEI_COMPLETA'!$D:$D), SUMIFS(_xlpm.intervaloSoma, 'CEI_COMPLETA'!$A:$A, Ajustes!AA$1, 'CEI_COMPLETA'!$B:$B, Ajustes!$Q21) ) -> 0 | ... AC21: =_xlfn.LET( _xlpm.intervaloSoma, IF($S21="R", 'CEI_COMPLETA'!$E:$E, 'CEI_COMPLETA'!$D:$D), SUMIFS(_xlpm.intervaloSoma, 'CEI_COMPLETA'!$A:$A, Ajustes!AC$1, 'CEI_COMPLETA'!$B:$B, Ajustes!$Q21) ) -> 0 | AD21: =_xlfn.LET( _xlpm.intervaloSoma, IF($S21="R", 'CEI_COMPLETA'!$E:$E, 'CEI_COMPLETA'!$D:$D), SUMIFS(_xlpm.intervaloSoma, 'CEI_COMPLETA'!$A:$A, Ajustes!AD$1, 'CEI_COMPLETA'!$B:$B, Ajustes!$R21) ) -> 49676 | AE21: =_xlfn.LET( _xlpm.intervaloSoma, IF($S21="R", 'CEI_COMPLETA'!$E:$E, 'CEI_COMPLETA'!$D:$D), SUMIFS(_xlpm.intervaloSoma, 'CEI_COMPLETA'!$A:$A, Ajustes!AE$1, 'CEI_COMPLETA'!$B:$B, Ajustes!$R21) ) -> 40879 | AF21: =_xlfn.LET( _xlpm.intervaloSoma, IF($S21="R", 'CEI_COMPLETA'!$E:$E, 'CEI_COMPLETA'!$D:$D), SUMIFS(_xlpm.intervaloSoma, 'CEI_COMPLETA'!$A:$A, Ajustes!AF$1, 'CEI_COMPLETA'!$B:$B, Ajustes!$R21) ) -> 62648 | AG21: =_xlfn.LET( _xlpm.intervaloSoma, IF($S21="R", 'CEI_COMPLETA'!$E:$E, 'CEI_COMPLETA'!$D:$D), SUMIFS(_xlpm.intervaloSoma, 'CEI_COMPLETA'!$A:$A, Ajustes!AG$1, 'CEI_COMPLETA'!$B:$B, Ajustes!$R21) ) -> 36695 | AH21: =_xlfn.LET( _xlpm.intervaloSoma, IF($S21="R", 'CEI_COMPLETA'!$E:$E, 'CEI_COMPLETA'!$D:$D), SUMIFS(_xlpm.intervaloSoma, 'CEI_COMPLETA'!$A:$A, Ajustes!AH$1, 'CEI_COMPLETA'!$B:$B, Ajustes!$R21) ) -> 40607 | AI21: =_xlfn.LET( _xlpm.intervaloSoma, IF($S21="R", 'CEI_COMPLETA'!$E:$E, 'CEI_COMPLETA'!$D:$D), SUMIFS(_xlpm.intervaloSoma, 'CEI_COMPLETA'!$A:$A, Ajustes!AI$1, 'CEI_COMPLETA'!$B:$B, Ajustes!$R21) ) -> 79427 | AJ21: =_xlfn.LET( _xlpm.intervaloSoma, IF($S21="R", 'CEI_COMPLETA'!$E:$E, 'CEI_COMPLETA'!$D:$D), SUMIFS(_xlpm.intervaloSoma, 'CEI_COMPLETA'!$A:$A, Ajustes!AJ$1, 'CEI_COMPLETA'!$B:$B, Ajustes!$R21) ) -> 65107 | AK21: =_xlfn.LET( _xlpm.intervaloSoma, IF($S21="R", 'CEI_COMPLETA'!$E:$E, 'CEI_COMPLETA'!$D:$D), SUMIFS(_xlpm.intervaloSoma, 'CEI_COMPLETA'!$A:$A, Ajustes!AK$1, 'CEI_COMPLETA'!$B:$B, Ajustes!$R21) ) -> 48385 | ... AO21: =_xlfn.LET( _xlpm.intervaloSoma, IF($S21="R", 'CEI_COMPLETA'!$E:$E, 'CEI_COMPLETA'!$D:$D), SUMIFS(_xlpm.intervaloSoma, 'CEI_COMPLETA'!$A:$A, Ajustes!AO$1, 'CEI_COMPLETA'!$B:$B, Ajustes!$R21) ) -> 70429
A22: Contribuições sociais dos empregadores (RECURSOS) | I22: {=_xlfn.SWITCH(B22,0,0,"-",-1,"+",1)} -> 0 | J22: {=_xlfn.SWITCH(C22,0,0,"-",-1,"+",1)} -> 0 | K22: {=_xlfn.SWITCH(D22,0,0,"-",-1,"+",1)} -> 0 | L22: {=_xlfn.SWITCH(E22,0,0,"-",-1,"+",1)} -> 0 | M22: {=_xlfn.SWITCH(F22,0,0,"-",-1,"+",1)} -> 0 | N22: {=_xlfn.SWITCH(G22,0,0,"-",-1,"+",1)} -> 0 | O22: {=_xlfn.SWITCH(H22,0,0,"-",-1,"+",1)} -> 0 | P22: CEI | Q22: D.12 | R22: D.12 | S22: R | T22: =_xlfn.LET( _xlpm.intervaloSoma, IF($S22="R", 'CEI_COMPLETA'!$E:$E, 'CEI_COMPLETA'!$D:$D), SUMIFS(_xlpm.intervaloSoma, 'CEI_COMPLETA'!$A:$A, Ajustes!T$1, 'CEI_COMPLETA'!$B:$B, Ajustes!$Q22) ) -> 89169 | U22: =_xlfn.LET( _xlpm.intervaloSoma, IF($S22="R", 'CEI_COMPLETA'!$E:$E, 'CEI_COMPLETA'!$D:$D), SUMIFS(_xlpm.intervaloSoma, 'CEI_COMPLETA'!$A:$A, Ajustes!U$1, 'CEI_COMPLETA'!$B:$B, Ajustes!$Q22) ) -> 102406 | V22: =_xlfn.LET( _xlpm.intervaloSoma, IF($S22="R", 'CEI_COMPLETA'!$E:$E, 'CEI_COMPLETA'!$D:$D), SUMIFS(_xlpm.intervaloSoma, 'CEI_COMPLETA'!$A:$A, Ajustes!V$1, 'CEI_COMPLETA'!$B:$B, Ajustes!$Q22) ) -> 112071 | W22: =_xlfn.LET( _xlpm.intervaloSoma, IF($S22="R", 'CEI_COMPLETA'!$E:$E, 'CEI_COMPLETA'!$D:$D), SUMIFS(_xlpm.intervaloSoma, 'CEI_COMPLETA'!$A:$A, Ajustes!W$1, 'CEI_COMPLETA'!$B:$B, Ajustes!$Q22) ) -> 130544 | X22: =_xlfn.LET( _xlpm.intervaloSoma, IF($S22="R", 'CEI_COMPLETA'!$E:$E, 'CEI_COMPLETA'!$D:$D), SUMIFS(_xlpm.intervaloSoma, 'CEI_COMPLETA'!$A:$A, Ajustes!X$1, 'CEI_COMPLETA'!$B:$B, Ajustes!$Q22) ) -> 150377 | Y22: =_xlfn.LET( _xlpm.intervaloSoma, IF($S22="R", 'CEI_COMPLETA'!$E:$E, 'CEI_COMPLETA'!$D:$D), SUMIFS(_xlpm.intervaloSoma, 'CEI_COMPLETA'!$A:$A, Ajustes!Y$1, 'CEI_COMPLETA'!$B:$B, Ajustes!$Q22) ) -> 167910 | Z22: =_xlfn.LET( _xlpm.intervaloSoma, IF($S22="R", 'CEI_COMPLETA'!$E:$E, 'CEI_COMPLETA'!$D:$D), SUMIFS(_xlpm.intervaloSoma, 'CEI_COMPLETA'!$A:$A, Ajustes!Z$1, 'CEI_COMPLETA'!$B:$B, Ajustes!$Q22) ) -> 186735 | AA22: =_xlfn.LET( _xlpm.intervaloSoma, IF($S22="R", 'CEI_COMPLETA'!$E:$E, 'CEI_COMPLETA'!$D:$D), SUMIFS(_xlpm.intervaloSoma, 'CEI_COMPLETA'!$A:$A, Ajustes!AA$1, 'CEI_COMPLETA'!$B:$B, Ajustes!$Q22) ) -> 217336 | ... AC22: =_xlfn.LET( _xlpm.intervaloSoma, IF($S22="R", 'CEI_COMPLETA'!$E:$E, 'CEI_COMPLETA'!$D:$D), SUMIFS(_xlpm.intervaloSoma, 'CEI_COMPLETA'!$A:$A, Ajustes!AC$1, 'CEI_COMPLETA'!$B:$B, Ajustes!$Q22) ) -> 286667 | AD22: =_xlfn.LET( _xlpm.intervaloSoma, IF($S22="R", 'CEI_COMPLETA'!$E:$E, 'CEI_COMPLETA'!$D:$D), SUMIFS(_xlpm.intervaloSoma, 'CEI_COMPLETA'!$A:$A, Ajustes!AD$1, 'CEI_COMPLETA'!$B:$B, Ajustes!$R22) ) -> 340905 | AE22: =_xlfn.LET( _xlpm.intervaloSoma, IF($S22="R", 'CEI_COMPLETA'!$E:$E, 'CEI_COMPLETA'!$D:$D), SUMIFS(_xlpm.intervaloSoma, 'CEI_COMPLETA'!$A:$A, Ajustes!AE$1, 'CEI_COMPLETA'!$B:$B, Ajustes!$R22) ) -> 393126 | AF22: =_xlfn.LET( _xlpm.intervaloSoma, IF($S22="R", 'CEI_COMPLETA'!$E:$E, 'CEI_COMPLETA'!$D:$D), SUMIFS(_xlpm.intervaloSoma, 'CEI_COMPLETA'!$A:$A, Ajustes!AF$1, 'CEI_COMPLETA'!$B:$B, Ajustes!$R22) ) -> 431871 | AG22: =_xlfn.LET( _xlpm.intervaloSoma, IF($S22="R", 'CEI_COMPLETA'!$E:$E, 'CEI_COMPLETA'!$D:$D), SUMIFS(_xlpm.intervaloSoma, 'CEI_COMPLETA'!$A:$A, Ajustes!AG$1, 'CEI_COMPLETA'!$B:$B, Ajustes!$R22) ) -> 483503 | AH22: =_xlfn.LET( _xlpm.intervaloSoma, IF($S22="R", 'CEI_COMPLETA'!$E:$E, 'CEI_COMPLETA'!$D:$D), SUMIFS(_xlpm.intervaloSoma, 'CEI_COMPLETA'!$A:$A, Ajustes!AH$1, 'CEI_COMPLETA'!$B:$B, Ajustes!$R22) ) -> 514960 | AI22: =_xlfn.LET( _xlpm.intervaloSoma, IF($S22="R", 'CEI_COMPLETA'!$E:$E, 'CEI_COMPLETA'!$D:$D), SUMIFS(_xlpm.intervaloSoma, 'CEI_COMPLETA'!$A:$A, Ajustes!AI$1, 'CEI_COMPLETA'!$B:$B, Ajustes!$R22) ) -> 545172 | AJ22: =_xlfn.LET( _xlpm.intervaloSoma, IF($S22="R", 'CEI_COMPLETA'!$E:$E, 'CEI_COMPLETA'!$D:$D), SUMIFS(_xlpm.intervaloSoma, 'CEI_COMPLETA'!$A:$A, Ajustes!AJ$1, 'CEI_COMPLETA'!$B:$B, Ajustes!$R22) ) -> 573144 | AK22: =_xlfn.LET( _xlpm.intervaloSoma, IF($S22="R", 'CEI_COMPLETA'!$E:$E, 'CEI_COMPLETA'!$D:$D), SUMIFS(_xlpm.intervaloSoma, 'CEI_COMPLETA'!$A:$A, Ajustes!AK$1, 'CEI_COMPLETA'!$B:$B, Ajustes!$R22) ) -> 608182 | ... AO22: =_xlfn.LET( _xlpm.intervaloSoma, IF($S22="R", 'CEI_COMPLETA'!$E:$E, 'CEI_COMPLETA'!$D:$D), SUMIFS(_xlpm.intervaloSoma, 'CEI_COMPLETA'!$A:$A, Ajustes!AO$1, 'CEI_COMPLETA'!$B:$B, Ajustes!$R22) ) -> 739634
A23: Contribuições sociais efetivas dos empregadores | I23: {=_xlfn.SWITCH(B23,0,0,"-",-1,"+",1)} -> 0 | J23: {=_xlfn.SWITCH(C23,0,0,"-",-1,"+",1)} -> 0 | K23: {=_xlfn.SWITCH(D23,0,0,"-",-1,"+",1)} -> 0 | L23: {=_xlfn.SWITCH(E23,0,0,"-",-1,"+",1)} -> 0 | M23: {=_xlfn.SWITCH(F23,0,0,"-",-1,"+",1)} -> 0 | N23: {=_xlfn.SWITCH(G23,0,0,"-",-1,"+",1)} -> 0 | O23: {=_xlfn.SWITCH(H23,0,0,"-",-1,"+",1)} -> 0 | P23: CEI | Q23: D.121 | R23: D.121 | S23: R | T23: =_xlfn.LET( _xlpm.intervaloSoma, IF($S23="R", 'CEI_COMPLETA'!$E:$E, 'CEI_COMPLETA'!$D:$D), SUMIFS(_xlpm.intervaloSoma, 'CEI_COMPLETA'!$A:$A, Ajustes!T$1, 'CEI_COMPLETA'!$B:$B, Ajustes!$Q23) ) -> 67435 | U23: =_xlfn.LET( _xlpm.intervaloSoma, IF($S23="R", 'CEI_COMPLETA'!$E:$E, 'CEI_COMPLETA'!$D:$D), SUMIFS(_xlpm.intervaloSoma, 'CEI_COMPLETA'!$A:$A, Ajustes!U$1, 'CEI_COMPLETA'!$B:$B, Ajustes!$Q23) ) -> 76664 | V23: =_xlfn.LET( _xlpm.intervaloSoma, IF($S23="R", 'CEI_COMPLETA'!$E:$E, 'CEI_COMPLETA'!$D:$D), SUMIFS(_xlpm.intervaloSoma, 'CEI_COMPLETA'!$A:$A, Ajustes!V$1, 'CEI_COMPLETA'!$B:$B, Ajustes!$Q23) ) -> 84063 | W23: =_xlfn.LET( _xlpm.intervaloSoma, IF($S23="R", 'CEI_COMPLETA'!$E:$E, 'CEI_COMPLETA'!$D:$D), SUMIFS(_xlpm.intervaloSoma, 'CEI_COMPLETA'!$A:$A, Ajustes!W$1, 'CEI_COMPLETA'!$B:$B, Ajustes!$Q23) ) -> 99492 | X23: =_xlfn.LET( _xlpm.intervaloSoma, IF($S23="R", 'CEI_COMPLETA'!$E:$E, 'CEI_COMPLETA'!$D:$D), SUMIFS(_xlpm.intervaloSoma, 'CEI_COMPLETA'!$A:$A, Ajustes!X$1, 'CEI_COMPLETA'!$B:$B, Ajustes!$Q23) ) -> 118417 | Y23: =_xlfn.LET( _xlpm.intervaloSoma, IF($S23="R", 'CEI_COMPLETA'!$E:$E, 'CEI_COMPLETA'!$D:$D), SUMIFS(_xlpm.intervaloSoma, 'CEI_COMPLETA'!$A:$A, Ajustes!Y$1, 'CEI_COMPLETA'!$B:$B, Ajustes!$Q23) ) -> 129466 | Z23: =_xlfn.LET( _xlpm.intervaloSoma, IF($S23="R", 'CEI_COMPLETA'!$E:$E, 'CEI_COMPLETA'!$D:$D), SUMIFS(_xlpm.intervaloSoma, 'CEI_COMPLETA'!$A:$A, Ajustes!Z$1, 'CEI_COMPLETA'!$B:$B, Ajustes!$Q23) ) -> 151749 | AA23: =_xlfn.LET( _xlpm.intervaloSoma, IF($S23="R", 'CEI_COMPLETA'!$E:$E, 'CEI_COMPLETA'!$D:$D), SUMIFS(_xlpm.intervaloSoma, 'CEI_COMPLETA'!$A:$A, Ajustes!AA$1, 'CEI_COMPLETA'!$B:$B, Ajustes!$Q23) ) -> 179752 | ... AC23: =_xlfn.LET( _xlpm.intervaloSoma, IF($S23="R", 'CEI_COMPLETA'!$E:$E, 'CEI_COMPLETA'!$D:$D), SUMIFS(_xlpm.intervaloSoma, 'CEI_COMPLETA'!$A:$A, Ajustes!AC$1, 'CEI_COMPLETA'!$B:$B, Ajustes!$Q23) ) -> 239770 | AD23: =_xlfn.LET( _xlpm.intervaloSoma, IF($S23="R", 'CEI_COMPLETA'!$E:$E, 'CEI_COMPLETA'!$D:$D), SUMIFS(_xlpm.intervaloSoma, 'CEI_COMPLETA'!$A:$A, Ajustes!AD$1, 'CEI_COMPLETA'!$B:$B, Ajustes!$R23) ) -> 290193 | AE23: =_xlfn.LET( _xlpm.intervaloSoma, IF($S23="R", 'CEI_COMPLETA'!$E:$E, 'CEI_COMPLETA'!$D:$D), SUMIFS(_xlpm.intervaloSoma, 'CEI_COMPLETA'!$A:$A, Ajustes!AE$1, 'CEI_COMPLETA'!$B:$B, Ajustes!$R23) ) -> 338487 | AF23: =_xlfn.LET( _xlpm.intervaloSoma, IF($S23="R", 'CEI_COMPLETA'!$E:$E, 'CEI_COMPLETA'!$D:$D), SUMIFS(_xlpm.intervaloSoma, 'CEI_COMPLETA'!$A:$A, Ajustes!AF$1, 'CEI_COMPLETA'!$B:$B, Ajustes!$R23) ) -> 374647 | AG23: =_xlfn.LET( _xlpm.intervaloSoma, IF($S23="R", 'CEI_COMPLETA'!$E:$E, 'CEI_COMPLETA'!$D:$D), SUMIFS(_xlpm.intervaloSoma, 'CEI_COMPLETA'!$A:$A, Ajustes!AG$1, 'CEI_COMPLETA'!$B:$B, Ajustes!$R23) ) -> 421108 | AH23: =_xlfn.LET( _xlpm.intervaloSoma, IF($S23="R", 'CEI_COMPLETA'!$E:$E, 'CEI_COMPLETA'!$D:$D), SUMIFS(_xlpm.intervaloSoma, 'CEI_COMPLETA'!$A:$A, Ajustes!AH$1, 'CEI_COMPLETA'!$B:$B, Ajustes!$R23) ) -> 445250 | AI23: =_xlfn.LET( _xlpm.intervaloSoma, IF($S23="R", 'CEI_COMPLETA'!$E:$E, 'CEI_COMPLETA'!$D:$D), SUMIFS(_xlpm.intervaloSoma, 'CEI_COMPLETA'!$A:$A, Ajustes!AI$1, 'CEI_COMPLETA'!$B:$B, Ajustes!$R23) ) -> 473185 | AJ23: =_xlfn.LET( _xlpm.intervaloSoma, IF($S23="R", 'CEI_COMPLETA'!$E:$E, 'CEI_COMPLETA'!$D:$D), SUMIFS(_xlpm.intervaloSoma, 'CEI_COMPLETA'!$A:$A, Ajustes!AJ$1, 'CEI_COMPLETA'!$B:$B, Ajustes!$R23) ) -> 494799 | AK23: =_xlfn.LET( _xlpm.intervaloSoma, IF($S23="R", 'CEI_COMPLETA'!$E:$E, 'CEI_COMPLETA'!$D:$D), SUMIFS(_xlpm.intervaloSoma, 'CEI_COMPLETA'!$A:$A, Ajustes!AK$1, 'CEI_COMPLETA'!$B:$B, Ajustes!$R23) ) -> 518850 | ... AO23: =_xlfn.LET( _xlpm.intervaloSoma, IF($S23="R", 'CEI_COMPLETA'!$E:$E, 'CEI_COMPLETA'!$D:$D), SUMIFS(_xlpm.intervaloSoma, 'CEI_COMPLETA'!$A:$A, Ajustes!AO$1, 'CEI_COMPLETA'!$B:$B, Ajustes!$R23) ) -> 639009
A24: Contribuições sociais imputadas dos empregadores | I24: {=_xlfn.SWITCH(B24,0,0,"-",-1,"+",1)} -> 0 | J24: {=_xlfn.SWITCH(C24,0,0,"-",-1,"+",1)} -> 0 | K24: {=_xlfn.SWITCH(D24,0,0,"-",-1,"+",1)} -> 0 | L24: {=_xlfn.SWITCH(E24,0,0,"-",-1,"+",1)} -> 0 | M24: {=_xlfn.SWITCH(F24,0,0,"-",-1,"+",1)} -> 0 | N24: {=_xlfn.SWITCH(G24,0,0,"-",-1,"+",1)} -> 0 | O24: {=_xlfn.SWITCH(H24,0,0,"-",-1,"+",1)} -> 0 | P24: CEI | Q24: D.122 | R24: D.122 | S24: R | T24: =_xlfn.LET( _xlpm.intervaloSoma, IF($S24="R", 'CEI_COMPLETA'!$E:$E, 'CEI_COMPLETA'!$D:$D), SUMIFS(_xlpm.intervaloSoma, 'CEI_COMPLETA'!$A:$A, Ajustes!T$1, 'CEI_COMPLETA'!$B:$B, Ajustes!$Q24) ) -> 21734 | U24: =_xlfn.LET( _xlpm.intervaloSoma, IF($S24="R", 'CEI_COMPLETA'!$E:$E, 'CEI_COMPLETA'!$D:$D), SUMIFS(_xlpm.intervaloSoma, 'CEI_COMPLETA'!$A:$A, Ajustes!U$1, 'CEI_COMPLETA'!$B:$B, Ajustes!$Q24) ) -> 25742 | V24: =_xlfn.LET( _xlpm.intervaloSoma, IF($S24="R", 'CEI_COMPLETA'!$E:$E, 'CEI_COMPLETA'!$D:$D), SUMIFS(_xlpm.intervaloSoma, 'CEI_COMPLETA'!$A:$A, Ajustes!V$1, 'CEI_COMPLETA'!$B:$B, Ajustes!$Q24) ) -> 28008 | W24: =_xlfn.LET( _xlpm.intervaloSoma, IF($S24="R", 'CEI_COMPLETA'!$E:$E, 'CEI_COMPLETA'!$D:$D), SUMIFS(_xlpm.intervaloSoma, 'CEI_COMPLETA'!$A:$A, Ajustes!W$1, 'CEI_COMPLETA'!$B:$B, Ajustes!$Q24) ) -> 31052 | X24: =_xlfn.LET( _xlpm.intervaloSoma, IF($S24="R", 'CEI_COMPLETA'!$E:$E, 'CEI_COMPLETA'!$D:$D), SUMIFS(_xlpm.intervaloSoma, 'CEI_COMPLETA'!$A:$A, Ajustes!X$1, 'CEI_COMPLETA'!$B:$B, Ajustes!$Q24) ) -> 31960 | Y24: =_xlfn.LET( _xlpm.intervaloSoma, IF($S24="R", 'CEI_COMPLETA'!$E:$E, 'CEI_COMPLETA'!$D:$D), SUMIFS(_xlpm.intervaloSoma, 'CEI_COMPLETA'!$A:$A, Ajustes!Y$1, 'CEI_COMPLETA'!$B:$B, Ajustes!$Q24) ) -> 38444 | Z24: =_xlfn.LET( _xlpm.intervaloSoma, IF($S24="R", 'CEI_COMPLETA'!$E:$E, 'CEI_COMPLETA'!$D:$D), SUMIFS(_xlpm.intervaloSoma, 'CEI_COMPLETA'!$A:$A, Ajustes!Z$1, 'CEI_COMPLETA'!$B:$B, Ajustes!$Q24) ) -> 34986 | AA24: =_xlfn.LET( _xlpm.intervaloSoma, IF($S24="R", 'CEI_COMPLETA'!$E:$E, 'CEI_COMPLETA'!$D:$D), SUMIFS(_xlpm.intervaloSoma, 'CEI_COMPLETA'!$A:$A, Ajustes!AA$1, 'CEI_COMPLETA'!$B:$B, Ajustes!$Q24) ) -> 37584 | ... AC24: =_xlfn.LET( _xlpm.intervaloSoma, IF($S24="R", 'CEI_COMPLETA'!$E:$E, 'CEI_COMPLETA'!$D:$D), SUMIFS(_xlpm.intervaloSoma, 'CEI_COMPLETA'!$A:$A, Ajustes!AC$1, 'CEI_COMPLETA'!$B:$B, Ajustes!$Q24) ) -> 46897 | AD24: =_xlfn.LET( _xlpm.intervaloSoma, IF($S24="R", 'CEI_COMPLETA'!$E:$E, 'CEI_COMPLETA'!$D:$D), SUMIFS(_xlpm.intervaloSoma, 'CEI_COMPLETA'!$A:$A, Ajustes!AD$1, 'CEI_COMPLETA'!$B:$B, Ajustes!$R24) ) -> 50712 | AE24: =_xlfn.LET( _xlpm.intervaloSoma, IF($S24="R", 'CEI_COMPLETA'!$E:$E, 'CEI_COMPLETA'!$D:$D), SUMIFS(_xlpm.intervaloSoma, 'CEI_COMPLETA'!$A:$A, Ajustes!AE$1, 'CEI_COMPLETA'!$B:$B, Ajustes!$R24) ) -> 54639 | AF24: =_xlfn.LET( _xlpm.intervaloSoma, IF($S24="R", 'CEI_COMPLETA'!$E:$E, 'CEI_COMPLETA'!$D:$D), SUMIFS(_xlpm.intervaloSoma, 'CEI_COMPLETA'!$A:$A, Ajustes!AF$1, 'CEI_COMPLETA'!$B:$B, Ajustes!$R24) ) -> 57224 | AG24: =_xlfn.LET( _xlpm.intervaloSoma, IF($S24="R", 'CEI_COMPLETA'!$E:$E, 'CEI_COMPLETA'!$D:$D), SUMIFS(_xlpm.intervaloSoma, 'CEI_COMPLETA'!$A:$A, Ajustes!AG$1, 'CEI_COMPLETA'!$B:$B, Ajustes!$R24) ) -> 62395 | AH24: =_xlfn.LET( _xlpm.intervaloSoma, IF($S24="R", 'CEI_COMPLETA'!$E:$E, 'CEI_COMPLETA'!$D:$D), SUMIFS(_xlpm.intervaloSoma, 'CEI_COMPLETA'!$A:$A, Ajustes!AH$1, 'CEI_COMPLETA'!$B:$B, Ajustes!$R24) ) -> 69710 | AI24: =_xlfn.LET( _xlpm.intervaloSoma, IF($S24="R", 'CEI_COMPLETA'!$E:$E, 'CEI_COMPLETA'!$D:$D), SUMIFS(_xlpm.intervaloSoma, 'CEI_COMPLETA'!$A:$A, Ajustes!AI$1, 'CEI_COMPLETA'!$B:$B, Ajustes!$R24) ) -> 71987 | AJ24: =_xlfn.LET( _xlpm.intervaloSoma, IF($S24="R", 'CEI_COMPLETA'!$E:$E, 'CEI_COMPLETA'!$D:$D), SUMIFS(_xlpm.intervaloSoma, 'CEI_COMPLETA'!$A:$A, Ajustes!AJ$1, 'CEI_COMPLETA'!$B:$B, Ajustes!$R24) ) -> 78345 | AK24: =_xlfn.LET( _xlpm.intervaloSoma, IF($S24="R", 'CEI_COMPLETA'!$E:$E, 'CEI_COMPLETA'!$D:$D), SUMIFS(_xlpm.intervaloSoma, 'CEI_COMPLETA'!$A:$A, Ajustes!AK$1, 'CEI_COMPLETA'!$B:$B, Ajustes!$R24) ) -> 89332 | ... AO24: =_xlfn.LET( _xlpm.intervaloSoma, IF($S24="R", 'CEI_COMPLETA'!$E:$E, 'CEI_COMPLETA'!$D:$D), SUMIFS(_xlpm.intervaloSoma, 'CEI_COMPLETA'!$A:$A, Ajustes!AO$1, 'CEI_COMPLETA'!$B:$B, Ajustes!$R24) ) -> 100625
A25: Contribuições sociais (USOS) | I25: {=_xlfn.SWITCH(B25,0,0,"-",-1,"+",1)} -> 0 | J25: {=_xlfn.SWITCH(C25,0,0,"-",-1,"+",1)} -> 0 | K25: {=_xlfn.SWITCH(D25,0,0,"-",-1,"+",1)} -> 0 | L25: {=_xlfn.SWITCH(E25,0,0,"-",-1,"+",1)} -> 0 | M25: {=_xlfn.SWITCH(F25,0,0,"-",-1,"+",1)} -> 0 | N25: {=_xlfn.SWITCH(G25,0,0,"-",-1,"+",1)} -> 0 | O25: {=_xlfn.SWITCH(H25,0,0,"-",-1,"+",1)} -> 0 | P25: CEI | Q25: D.61 | R25: D.61 | S25: U | T25: =_xlfn.LET( _xlpm.intervaloSoma, IF($S25="R", 'CEI_COMPLETA'!$E:$E, 'CEI_COMPLETA'!$D:$D), SUMIFS(_xlpm.intervaloSoma, 'CEI_COMPLETA'!$A:$A, Ajustes!T$1, 'CEI_COMPLETA'!$B:$B, Ajustes!$Q25) ) -> 129632 | U25: =_xlfn.LET( _xlpm.intervaloSoma, IF($S25="R", 'CEI_COMPLETA'!$E:$E, 'CEI_COMPLETA'!$D:$D), SUMIFS(_xlpm.intervaloSoma, 'CEI_COMPLETA'!$A:$A, Ajustes!U$1, 'CEI_COMPLETA'!$B:$B, Ajustes!$Q25) ) -> 151615 | V25: =_xlfn.LET( _xlpm.intervaloSoma, IF($S25="R", 'CEI_COMPLETA'!$E:$E, 'CEI_COMPLETA'!$D:$D), SUMIFS(_xlpm.intervaloSoma, 'CEI_COMPLETA'!$A:$A, Ajustes!V$1, 'CEI_COMPLETA'!$B:$B, Ajustes!$Q25) ) -> 170707 | W25: =_xlfn.LET( _xlpm.intervaloSoma, IF($S25="R", 'CEI_COMPLETA'!$E:$E, 'CEI_COMPLETA'!$D:$D), SUMIFS(_xlpm.intervaloSoma, 'CEI_COMPLETA'!$A:$A, Ajustes!W$1, 'CEI_COMPLETA'!$B:$B, Ajustes!$Q25) ) -> 194502 | X25: =_xlfn.LET( _xlpm.intervaloSoma, IF($S25="R", 'CEI_COMPLETA'!$E:$E, 'CEI_COMPLETA'!$D:$D), SUMIFS(_xlpm.intervaloSoma, 'CEI_COMPLETA'!$A:$A, Ajustes!X$1, 'CEI_COMPLETA'!$B:$B, Ajustes!$Q25) ) -> 215107 | Y25: =_xlfn.LET( _xlpm.intervaloSoma, IF($S25="R", 'CEI_COMPLETA'!$E:$E, 'CEI_COMPLETA'!$D:$D), SUMIFS(_xlpm.intervaloSoma, 'CEI_COMPLETA'!$A:$A, Ajustes!Y$1, 'CEI_COMPLETA'!$B:$B, Ajustes!$Q25) ) -> 247112 | Z25: =_xlfn.LET( _xlpm.intervaloSoma, IF($S25="R", 'CEI_COMPLETA'!$E:$E, 'CEI_COMPLETA'!$D:$D), SUMIFS(_xlpm.intervaloSoma, 'CEI_COMPLETA'!$A:$A, Ajustes!Z$1, 'CEI_COMPLETA'!$B:$B, Ajustes!$Q25) ) -> 282410 | AA25: =_xlfn.LET( _xlpm.intervaloSoma, IF($S25="R", 'CEI_COMPLETA'!$E:$E, 'CEI_COMPLETA'!$D:$D), SUMIFS(_xlpm.intervaloSoma, 'CEI_COMPLETA'!$A:$A, Ajustes!AA$1, 'CEI_COMPLETA'!$B:$B, Ajustes!$Q25) ) -> 315996 | ... AC25: =_xlfn.LET( _xlpm.intervaloSoma, IF($S25="R", 'CEI_COMPLETA'!$E:$E, 'CEI_COMPLETA'!$D:$D), SUMIFS(_xlpm.intervaloSoma, 'CEI_COMPLETA'!$A:$A, Ajustes!AC$1, 'CEI_COMPLETA'!$B:$B, Ajustes!$Q25) ) -> 393773 | AD25: =_xlfn.LET( _xlpm.intervaloSoma, IF($S25="R", 'CEI_COMPLETA'!$E:$E, 'CEI_COMPLETA'!$D:$D), SUMIFS(_xlpm.intervaloSoma, 'CEI_COMPLETA'!$A:$A, Ajustes!AD$1, 'CEI_COMPLETA'!$B:$B, Ajustes!$R25) ) -> 474322 | AE25: =_xlfn.LET( _xlpm.intervaloSoma, IF($S25="R", 'CEI_COMPLETA'!$E:$E, 'CEI_COMPLETA'!$D:$D), SUMIFS(_xlpm.intervaloSoma, 'CEI_COMPLETA'!$A:$A, Ajustes!AE$1, 'CEI_COMPLETA'!$B:$B, Ajustes!$R25) ) -> 529663 | AF25: =_xlfn.LET( _xlpm.intervaloSoma, IF($S25="R", 'CEI_COMPLETA'!$E:$E, 'CEI_COMPLETA'!$D:$D), SUMIFS(_xlpm.intervaloSoma, 'CEI_COMPLETA'!$A:$A, Ajustes!AF$1, 'CEI_COMPLETA'!$B:$B, Ajustes!$R25) ) -> 599944 | AG25: =_xlfn.LET( _xlpm.intervaloSoma, IF($S25="R", 'CEI_COMPLETA'!$E:$E, 'CEI_COMPLETA'!$D:$D), SUMIFS(_xlpm.intervaloSoma, 'CEI_COMPLETA'!$A:$A, Ajustes!AG$1, 'CEI_COMPLETA'!$B:$B, Ajustes!$R25) ) -> 641336 | AH25: =_xlfn.LET( _xlpm.intervaloSoma, IF($S25="R", 'CEI_COMPLETA'!$E:$E, 'CEI_COMPLETA'!$D:$D), SUMIFS(_xlpm.intervaloSoma, 'CEI_COMPLETA'!$A:$A, Ajustes!AH$1, 'CEI_COMPLETA'!$B:$B, Ajustes!$R25) ) -> 690113 | AI25: =_xlfn.LET( _xlpm.intervaloSoma, IF($S25="R", 'CEI_COMPLETA'!$E:$E, 'CEI_COMPLETA'!$D:$D), SUMIFS(_xlpm.intervaloSoma, 'CEI_COMPLETA'!$A:$A, Ajustes!AI$1, 'CEI_COMPLETA'!$B:$B, Ajustes!$R25) ) -> 768026 | AJ25: =_xlfn.LET( _xlpm.intervaloSoma, IF($S25="R", 'CEI_COMPLETA'!$E:$E, 'CEI_COMPLETA'!$D:$D), SUMIFS(_xlpm.intervaloSoma, 'CEI_COMPLETA'!$A:$A, Ajustes!AJ$1, 'CEI_COMPLETA'!$B:$B, Ajustes!$R25) ) -> 787092 | AK25: =_xlfn.LET( _xlpm.intervaloSoma, IF($S25="R", 'CEI_COMPLETA'!$E:$E, 'CEI_COMPLETA'!$D:$D), SUMIFS(_xlpm.intervaloSoma, 'CEI_COMPLETA'!$A:$A, Ajustes!AK$1, 'CEI_COMPLETA'!$B:$B, Ajustes!$R25) ) -> 807880 | ... AO25: =_xlfn.LET( _xlpm.intervaloSoma, IF($S25="R", 'CEI_COMPLETA'!$E:$E, 'CEI_COMPLETA'!$D:$D), SUMIFS(_xlpm.intervaloSoma, 'CEI_COMPLETA'!$A:$A, Ajustes!AO$1, 'CEI_COMPLETA'!$B:$B, Ajustes!$R25) ) -> 1013186
A26: Contribuições sociais dos empregadores | I26: {=_xlfn.SWITCH(B26,0,0,"-",-1,"+",1)} -> 0 | J26: {=_xlfn.SWITCH(C26,0,0,"-",-1,"+",1)} -> 0 | K26: {=_xlfn.SWITCH(D26,0,0,"-",-1,"+",1)} -> 0 | L26: {=_xlfn.SWITCH(E26,0,0,"-",-1,"+",1)} -> 0 | M26: {=_xlfn.SWITCH(F26,0,0,"-",-1,"+",1)} -> 0 | N26: {=_xlfn.SWITCH(G26,0,0,"-",-1,"+",1)} -> 0 | O26: {=_xlfn.SWITCH(H26,0,0,"-",-1,"+",1)} -> 0 | P26: CEI | S26: U | T26: =_xlfn.LET( _xlpm.intervaloSoma, IF($S26="R", 'CEI_COMPLETA'!$E:$E, 'CEI_COMPLETA'!$D:$D), SUMIFS(_xlpm.intervaloSoma, 'CEI_COMPLETA'!$A:$A, Ajustes!T$1, 'CEI_COMPLETA'!$B:$B, Ajustes!$Q26) ) -> 0 | U26: =_xlfn.LET( _xlpm.intervaloSoma, IF($S26="R", 'CEI_COMPLETA'!$E:$E, 'CEI_COMPLETA'!$D:$D), SUMIFS(_xlpm.intervaloSoma, 'CEI_COMPLETA'!$A:$A, Ajustes!U$1, 'CEI_COMPLETA'!$B:$B, Ajustes!$Q26) ) -> 0 | V26: =_xlfn.LET( _xlpm.intervaloSoma, IF($S26="R", 'CEI_COMPLETA'!$E:$E, 'CEI_COMPLETA'!$D:$D), SUMIFS(_xlpm.intervaloSoma, 'CEI_COMPLETA'!$A:$A, Ajustes!V$1, 'CEI_COMPLETA'!$B:$B, Ajustes!$Q26) ) -> 0 | W26: =_xlfn.LET( _xlpm.intervaloSoma, IF($S26="R", 'CEI_COMPLETA'!$E:$E, 'CEI_COMPLETA'!$D:$D), SUMIFS(_xlpm.intervaloSoma, 'CEI_COMPLETA'!$A:$A, Ajustes!W$1, 'CEI_COMPLETA'!$B:$B, Ajustes!$Q26) ) -> 0 | X26: =_xlfn.LET( _xlpm.intervaloSoma, IF($S26="R", 'CEI_COMPLETA'!$E:$E, 'CEI_COMPLETA'!$D:$D), SUMIFS(_xlpm.intervaloSoma, 'CEI_COMPLETA'!$A:$A, Ajustes!X$1, 'CEI_COMPLETA'!$B:$B, Ajustes!$Q26) ) -> 0 | Y26: =_xlfn.LET( _xlpm.intervaloSoma, IF($S26="R", 'CEI_COMPLETA'!$E:$E, 'CEI_COMPLETA'!$D:$D), SUMIFS(_xlpm.intervaloSoma, 'CEI_COMPLETA'!$A:$A, Ajustes!Y$1, 'CEI_COMPLETA'!$B:$B, Ajustes!$Q26) ) -> 0 | Z26: =_xlfn.LET( _xlpm.intervaloSoma, IF($S26="R", 'CEI_COMPLETA'!$E:$E, 'CEI_COMPLETA'!$D:$D), SUMIFS(_xlpm.intervaloSoma, 'CEI_COMPLETA'!$A:$A, Ajustes!Z$1, 'CEI_COMPLETA'!$B:$B, Ajustes!$Q26) ) -> 0 | AA26: =_xlfn.LET( _xlpm.intervaloSoma, IF($S26="R", 'CEI_COMPLETA'!$E:$E, 'CEI_COMPLETA'!$D:$D), SUMIFS(_xlpm.intervaloSoma, 'CEI_COMPLETA'!$A:$A, Ajustes!AA$1, 'CEI_COMPLETA'!$B:$B, Ajustes!$Q26) ) -> 0 | ... AC26: =_xlfn.LET( _xlpm.intervaloSoma, IF($S26="R", 'CEI_COMPLETA'!$E:$E, 'CEI_COMPLETA'!$D:$D), SUMIFS(_xlpm.intervaloSoma, 'CEI_COMPLETA'!$A:$A, Ajustes!AC$1, 'CEI_COMPLETA'!$B:$B, Ajustes!$Q26) ) -> 0 | AD26: =_xlfn.LET( _xlpm.intervaloSoma, IF($S26="R", 'CEI_COMPLETA'!$E:$E, 'CEI_COMPLETA'!$D:$D), SUMIFS(_xlpm.intervaloSoma, 'CEI_COMPLETA'!$A:$A, Ajustes!AD$1, 'CEI_COMPLETA'!$B:$B, Ajustes!$R26) ) -> 0 | AE26: =_xlfn.LET( _xlpm.intervaloSoma, IF($S26="R", 'CEI_COMPLETA'!$E:$E, 'CEI_COMPLETA'!$D:$D), SUMIFS(_xlpm.intervaloSoma, 'CEI_COMPLETA'!$A:$A, Ajustes!AE$1, 'CEI_COMPLETA'!$B:$B, Ajustes!$R26) ) -> 0 | AF26: =_xlfn.LET( _xlpm.intervaloSoma, IF($S26="R", 'CEI_COMPLETA'!$E:$E, 'CEI_COMPLETA'!$D:$D), SUMIFS(_xlpm.intervaloSoma, 'CEI_COMPLETA'!$A:$A, Ajustes!AF$1, 'CEI_COMPLETA'!$B:$B, Ajustes!$R26) ) -> 0 | AG26: =_xlfn.LET( _xlpm.intervaloSoma, IF($S26="R", 'CEI_COMPLETA'!$E:$E, 'CEI_COMPLETA'!$D:$D), SUMIFS(_xlpm.intervaloSoma, 'CEI_COMPLETA'!$A:$A, Ajustes!AG$1, 'CEI_COMPLETA'!$B:$B, Ajustes!$R26) ) -> 0 | AH26: =_xlfn.LET( _xlpm.intervaloSoma, IF($S26="R", 'CEI_COMPLETA'!$E:$E, 'CEI_COMPLETA'!$D:$D), SUMIFS(_xlpm.intervaloSoma, 'CEI_COMPLETA'!$A:$A, Ajustes!AH$1, 'CEI_COMPLETA'!$B:$B, Ajustes!$R26) ) -> 0 | AI26: =_xlfn.LET( _xlpm.intervaloSoma, IF($S26="R", 'CEI_COMPLETA'!$E:$E, 'CEI_COMPLETA'!$D:$D), SUMIFS(_xlpm.intervaloSoma, 'CEI_COMPLETA'!$A:$A, Ajustes!AI$1, 'CEI_COMPLETA'!$B:$B, Ajustes!$R26) ) -> 0 | AJ26: =_xlfn.LET( _xlpm.intervaloSoma, IF($S26="R", 'CEI_COMPLETA'!$E:$E, 'CEI_COMPLETA'!$D:$D), SUMIFS(_xlpm.intervaloSoma, 'CEI_COMPLETA'!$A:$A, Ajustes!AJ$1, 'CEI_COMPLETA'!$B:$B, Ajustes!$R26) ) -> 0 | AK26: =_xlfn.LET( _xlpm.intervaloSoma, IF($S26="R", 'CEI_COMPLETA'!$E:$E, 'CEI_COMPLETA'!$D:$D), SUMIFS(_xlpm.intervaloSoma, 'CEI_COMPLETA'!$A:$A, Ajustes!AK$1, 'CEI_COMPLETA'!$B:$B, Ajustes!$R26) ) -> 0 | ... AO26: =_xlfn.LET( _xlpm.intervaloSoma, IF($S26="R", 'CEI_COMPLETA'!$E:$E, 'CEI_COMPLETA'!$D:$D), SUMIFS(_xlpm.intervaloSoma, 'CEI_COMPLETA'!$A:$A, Ajustes!AO$1, 'CEI_COMPLETA'!$B:$B, Ajustes!$R26) ) -> 0
A27: Contribuições sociais efetivas dos empregadores | I27: {=_xlfn.SWITCH(B27,0,0,"-",-1,"+",1)} -> 0 | J27: {=_xlfn.SWITCH(C27,0,0,"-",-1,"+",1)} -> 0 | K27: {=_xlfn.SWITCH(D27,0,0,"-",-1,"+",1)} -> 0 | L27: {=_xlfn.SWITCH(E27,0,0,"-",-1,"+",1)} -> 0 | M27: {=_xlfn.SWITCH(F27,0,0,"-",-1,"+",1)} -> 0 | N27: {=_xlfn.SWITCH(G27,0,0,"-",-1,"+",1)} -> 0 | O27: {=_xlfn.SWITCH(H27,0,0,"-",-1,"+",1)} -> 0 | P27: CEI | Q27: D.611 | R27: D.611 | S27: U | T27: =_xlfn.LET( _xlpm.intervaloSoma, IF($S27="R", 'CEI_COMPLETA'!$E:$E, 'CEI_COMPLETA'!$D:$D), SUMIFS(_xlpm.intervaloSoma, 'CEI_COMPLETA'!$A:$A, Ajustes!T$1, 'CEI_COMPLETA'!$B:$B, Ajustes!$Q27) ) -> 67435 | U27: =_xlfn.LET( _xlpm.intervaloSoma, IF($S27="R", 'CEI_COMPLETA'!$E:$E, 'CEI_COMPLETA'!$D:$D), SUMIFS(_xlpm.intervaloSoma, 'CEI_COMPLETA'!$A:$A, Ajustes!U$1, 'CEI_COMPLETA'!$B:$B, Ajustes!$Q27) ) -> 76664 | V27: =_xlfn.LET( _xlpm.intervaloSoma, IF($S27="R", 'CEI_COMPLETA'!$E:$E, 'CEI_COMPLETA'!$D:$D), SUMIFS(_xlpm.intervaloSoma, 'CEI_COMPLETA'!$A:$A, Ajustes!V$1, 'CEI_COMPLETA'!$B:$B, Ajustes!$Q27) ) -> 84063 | W27: =_xlfn.LET( _xlpm.intervaloSoma, IF($S27="R", 'CEI_COMPLETA'!$E:$E, 'CEI_COMPLETA'!$D:$D), SUMIFS(_xlpm.intervaloSoma, 'CEI_COMPLETA'!$A:$A, Ajustes!W$1, 'CEI_COMPLETA'!$B:$B, Ajustes!$Q27) ) -> 99492 | X27: =_xlfn.LET( _xlpm.intervaloSoma, IF($S27="R", 'CEI_COMPLETA'!$E:$E, 'CEI_COMPLETA'!$D:$D), SUMIFS(_xlpm.intervaloSoma, 'CEI_COMPLETA'!$A:$A, Ajustes!X$1, 'CEI_COMPLETA'!$B:$B, Ajustes!$Q27) ) -> 118417 | Y27: =_xlfn.LET( _xlpm.intervaloSoma, IF($S27="R", 'CEI_COMPLETA'!$E:$E, 'CEI_COMPLETA'!$D:$D), SUMIFS(_xlpm.intervaloSoma, 'CEI_COMPLETA'!$A:$A, Ajustes!Y$1, 'CEI_COMPLETA'!$B:$B, Ajustes!$Q27) ) -> 129466 | Z27: =_xlfn.LET( _xlpm.intervaloSoma, IF($S27="R", 'CEI_COMPLETA'!$E:$E, 'CEI_COMPLETA'!$D:$D), SUMIFS(_xlpm.intervaloSoma, 'CEI_COMPLETA'!$A:$A, Ajustes!Z$1, 'CEI_COMPLETA'!$B:$B, Ajustes!$Q27) ) -> 151749 | AA27: =_xlfn.LET( _xlpm.intervaloSoma, IF($S27="R", 'CEI_COMPLETA'!$E:$E, 'CEI_COMPLETA'!$D:$D), SUMIFS(_xlpm.intervaloSoma, 'CEI_COMPLETA'!$A:$A, Ajustes!AA$1, 'CEI_COMPLETA'!$B:$B, Ajustes!$Q27) ) -> 179752 | ... AC27: =_xlfn.LET( _xlpm.intervaloSoma, IF($S27="R", 'CEI_COMPLETA'!$E:$E, 'CEI_COMPLETA'!$D:$D), SUMIFS(_xlpm.intervaloSoma, 'CEI_COMPLETA'!$A:$A, Ajustes!AC$1, 'CEI_COMPLETA'!$B:$B, Ajustes!$Q27) ) -> 239770 | AD27: =_xlfn.LET( _xlpm.intervaloSoma, IF($S27="R", 'CEI_COMPLETA'!$E:$E, 'CEI_COMPLETA'!$D:$D), SUMIFS(_xlpm.intervaloSoma, 'CEI_COMPLETA'!$A:$A, Ajustes!AD$1, 'CEI_COMPLETA'!$B:$B, Ajustes!$R27) ) -> 290193 | AE27: =_xlfn.LET( _xlpm.intervaloSoma, IF($S27="R", 'CEI_COMPLETA'!$E:$E, 'CEI_COMPLETA'!$D:$D), SUMIFS(_xlpm.intervaloSoma, 'CEI_COMPLETA'!$A:$A, Ajustes!AE$1, 'CEI_COMPLETA'!$B:$B, Ajustes!$R27) ) -> 338487 | AF27: =_xlfn.LET( _xlpm.intervaloSoma, IF($S27="R", 'CEI_COMPLETA'!$E:$E, 'CEI_COMPLETA'!$D:$D), SUMIFS(_xlpm.intervaloSoma, 'CEI_COMPLETA'!$A:$A, Ajustes!AF$1, 'CEI_COMPLETA'!$B:$B, Ajustes!$R27) ) -> 374647 | AG27: =_xlfn.LET( _xlpm.intervaloSoma, IF($S27="R", 'CEI_COMPLETA'!$E:$E, 'CEI_COMPLETA'!$D:$D), SUMIFS(_xlpm.intervaloSoma, 'CEI_COMPLETA'!$A:$A, Ajustes!AG$1, 'CEI_COMPLETA'!$B:$B, Ajustes!$R27) ) -> 421108 | AH27: =_xlfn.LET( _xlpm.intervaloSoma, IF($S27="R", 'CEI_COMPLETA'!$E:$E, 'CEI_COMPLETA'!$D:$D), SUMIFS(_xlpm.intervaloSoma, 'CEI_COMPLETA'!$A:$A, Ajustes!AH$1, 'CEI_COMPLETA'!$B:$B, Ajustes!$R27) ) -> 445250 | AI27: =_xlfn.LET( _xlpm.intervaloSoma, IF($S27="R", 'CEI_COMPLETA'!$E:$E, 'CEI_COMPLETA'!$D:$D), SUMIFS(_xlpm.intervaloSoma, 'CEI_COMPLETA'!$A:$A, Ajustes!AI$1, 'CEI_COMPLETA'!$B:$B, Ajustes!$R27) ) -> 473185 | AJ27: =_xlfn.LET( _xlpm.intervaloSoma, IF($S27="R", 'CEI_COMPLETA'!$E:$E, 'CEI_COMPLETA'!$D:$D), SUMIFS(_xlpm.intervaloSoma, 'CEI_COMPLETA'!$A:$A, Ajustes!AJ$1, 'CEI_COMPLETA'!$B:$B, Ajustes!$R27) ) -> 494799 | AK27: =_xlfn.LET( _xlpm.intervaloSoma, IF($S27="R", 'CEI_COMPLETA'!$E:$E, 'CEI_COMPLETA'!$D:$D), SUMIFS(_xlpm.intervaloSoma, 'CEI_COMPLETA'!$A:$A, Ajustes!AK$1, 'CEI_COMPLETA'!$B:$B, Ajustes!$R27) ) -> 518850 | ... AO27: =_xlfn.LET( _xlpm.intervaloSoma, IF($S27="R", 'CEI_COMPLETA'!$E:$E, 'CEI_COMPLETA'!$D:$D), SUMIFS(_xlpm.intervaloSoma, 'CEI_COMPLETA'!$A:$A, Ajustes!AO$1, 'CEI_COMPLETA'!$B:$B, Ajustes!$R27) ) -> 634145
A28: Contribuições sociais imputadas dos empregadores | I28: {=_xlfn.SWITCH(B28,0,0,"-",-1,"+",1)} -> 0 | J28: {=_xlfn.SWITCH(C28,0,0,"-",-1,"+",1)} -> 0 | K28: {=_xlfn.SWITCH(D28,0,0,"-",-1,"+",1)} -> 0 | L28: {=_xlfn.SWITCH(E28,0,0,"-",-1,"+",1)} -> 0 | M28: {=_xlfn.SWITCH(F28,0,0,"-",-1,"+",1)} -> 0 | N28: {=_xlfn.SWITCH(G28,0,0,"-",-1,"+",1)} -> 0 | O28: {=_xlfn.SWITCH(H28,0,0,"-",-1,"+",1)} -> 0 | P28: CEI | Q28: D.612 | R28: D.612 | S28: U | T28: =_xlfn.LET( _xlpm.intervaloSoma, IF($S28="R", 'CEI_COMPLETA'!$E:$E, 'CEI_COMPLETA'!$D:$D), SUMIFS(_xlpm.intervaloSoma, 'CEI_COMPLETA'!$A:$A, Ajustes!T$1, 'CEI_COMPLETA'!$B:$B, Ajustes!$Q28) ) -> 21734 | U28: =_xlfn.LET( _xlpm.intervaloSoma, IF($S28="R", 'CEI_COMPLETA'!$E:$E, 'CEI_COMPLETA'!$D:$D), SUMIFS(_xlpm.intervaloSoma, 'CEI_COMPLETA'!$A:$A, Ajustes!U$1, 'CEI_COMPLETA'!$B:$B, Ajustes!$Q28) ) -> 25742 | V28: =_xlfn.LET( _xlpm.intervaloSoma, IF($S28="R", 'CEI_COMPLETA'!$E:$E, 'CEI_COMPLETA'!$D:$D), SUMIFS(_xlpm.intervaloSoma, 'CEI_COMPLETA'!$A:$A, Ajustes!V$1, 'CEI_COMPLETA'!$B:$B, Ajustes!$Q28) ) -> 28008 | W28: =_xlfn.LET( _xlpm.intervaloSoma, IF($S28="R", 'CEI_COMPLETA'!$E:$E, 'CEI_COMPLETA'!$D:$D), SUMIFS(_xlpm.intervaloSoma, 'CEI_COMPLETA'!$A:$A, Ajustes!W$1, 'CEI_COMPLETA'!$B:$B, Ajustes!$Q28) ) -> 31052 | X28: =_xlfn.LET( _xlpm.intervaloSoma, IF($S28="R", 'CEI_COMPLETA'!$E:$E, 'CEI_COMPLETA'!$D:$D), SUMIFS(_xlpm.intervaloSoma, 'CEI_COMPLETA'!$A:$A, Ajustes!X$1, 'CEI_COMPLETA'!$B:$B, Ajustes!$Q28) ) -> 31960 | Y28: =_xlfn.LET( _xlpm.intervaloSoma, IF($S28="R", 'CEI_COMPLETA'!$E:$E, 'CEI_COMPLETA'!$D:$D), SUMIFS(_xlpm.intervaloSoma, 'CEI_COMPLETA'!$A:$A, Ajustes!Y$1, 'CEI_COMPLETA'!$B:$B, Ajustes!$Q28) ) -> 38444 | Z28: =_xlfn.LET( _xlpm.intervaloSoma, IF($S28="R", 'CEI_COMPLETA'!$E:$E, 'CEI_COMPLETA'!$D:$D), SUMIFS(_xlpm.intervaloSoma, 'CEI_COMPLETA'!$A:$A, Ajustes!Z$1, 'CEI_COMPLETA'!$B:$B, Ajustes!$Q28) ) -> 34986 | AA28: =_xlfn.LET( _xlpm.intervaloSoma, IF($S28="R", 'CEI_COMPLETA'!$E:$E, 'CEI_COMPLETA'!$D:$D), SUMIFS(_xlpm.intervaloSoma, 'CEI_COMPLETA'!$A:$A, Ajustes!AA$1, 'CEI_COMPLETA'!$B:$B, Ajustes!$Q28) ) -> 37584 | ... AC28: =_xlfn.LET( _xlpm.intervaloSoma, IF($S28="R", 'CEI_COMPLETA'!$E:$E, 'CEI_COMPLETA'!$D:$D), SUMIFS(_xlpm.intervaloSoma, 'CEI_COMPLETA'!$A:$A, Ajustes!AC$1, 'CEI_COMPLETA'!$B:$B, Ajustes!$Q28) ) -> 46897 | AD28: =_xlfn.LET( _xlpm.intervaloSoma, IF($S28="R", 'CEI_COMPLETA'!$E:$E, 'CEI_COMPLETA'!$D:$D), SUMIFS(_xlpm.intervaloSoma, 'CEI_COMPLETA'!$A:$A, Ajustes!AD$1, 'CEI_COMPLETA'!$B:$B, Ajustes!$R28) ) -> 50712 | AE28: =_xlfn.LET( _xlpm.intervaloSoma, IF($S28="R", 'CEI_COMPLETA'!$E:$E, 'CEI_COMPLETA'!$D:$D), SUMIFS(_xlpm.intervaloSoma, 'CEI_COMPLETA'!$A:$A, Ajustes!AE$1, 'CEI_COMPLETA'!$B:$B, Ajustes!$R28) ) -> 54639 | AF28: =_xlfn.LET( _xlpm.intervaloSoma, IF($S28="R", 'CEI_COMPLETA'!$E:$E, 'CEI_COMPLETA'!$D:$D), SUMIFS(_xlpm.intervaloSoma, 'CEI_COMPLETA'!$A:$A, Ajustes!AF$1, 'CEI_COMPLETA'!$B:$B, Ajustes!$R28) ) -> 57224 | AG28: =_xlfn.LET( _xlpm.intervaloSoma, IF($S28="R", 'CEI_COMPLETA'!$E:$E, 'CEI_COMPLETA'!$D:$D), SUMIFS(_xlpm.intervaloSoma, 'CEI_COMPLETA'!$A:$A, Ajustes!AG$1, 'CEI_COMPLETA'!$B:$B, Ajustes!$R28) ) -> 62395 | AH28: =_xlfn.LET( _xlpm.intervaloSoma, IF($S28="R", 'CEI_COMPLETA'!$E:$E, 'CEI_COMPLETA'!$D:$D), SUMIFS(_xlpm.intervaloSoma, 'CEI_COMPLETA'!$A:$A, Ajustes!AH$1, 'CEI_COMPLETA'!$B:$B, Ajustes!$R28) ) -> 69710 | AI28: =_xlfn.LET( _xlpm.intervaloSoma, IF($S28="R", 'CEI_COMPLETA'!$E:$E, 'CEI_COMPLETA'!$D:$D), SUMIFS(_xlpm.intervaloSoma, 'CEI_COMPLETA'!$A:$A, Ajustes!AI$1, 'CEI_COMPLETA'!$B:$B, Ajustes!$R28) ) -> 71987 | AJ28: =_xlfn.LET( _xlpm.intervaloSoma, IF($S28="R", 'CEI_COMPLETA'!$E:$E, 'CEI_COMPLETA'!$D:$D), SUMIFS(_xlpm.intervaloSoma, 'CEI_COMPLETA'!$A:$A, Ajustes!AJ$1, 'CEI_COMPLETA'!$B:$B, Ajustes!$R28) ) -> 78345 | AK28: =_xlfn.LET( _xlpm.intervaloSoma, IF($S28="R", 'CEI_COMPLETA'!$E:$E, 'CEI_COMPLETA'!$D:$D), SUMIFS(_xlpm.intervaloSoma, 'CEI_COMPLETA'!$A:$A, Ajustes!AK$1, 'CEI_COMPLETA'!$B:$B, Ajustes!$R28) ) -> 89332 | ... AO28: =_xlfn.LET( _xlpm.intervaloSoma, IF($S28="R", 'CEI_COMPLETA'!$E:$E, 'CEI_COMPLETA'!$D:$D), SUMIFS(_xlpm.intervaloSoma, 'CEI_COMPLETA'!$A:$A, Ajustes!AO$1, 'CEI_COMPLETA'!$B:$B, Ajustes!$R28) ) -> 100625
A29: Contribuições sociais efetivas das famílias/empregados e suplemento às contribuições sociais | I29: {=_xlfn.SWITCH(B29,0,0,"-",-1,"+",1)} -> 0 | J29: {=_xlfn.SWITCH(C29,0,0,"-",-1,"+",1)} -> 0 | K29: {=_xlfn.SWITCH(D29,0,0,"-",-1,"+",1)} -> 0 | L29: {=_xlfn.SWITCH(E29,0,0,"-",-1,"+",1)} -> 0 | M29: {=_xlfn.SWITCH(F29,0,0,"-",-1,"+",1)} -> 0 | N29: {=_xlfn.SWITCH(G29,0,0,"-",-1,"+",1)} -> 0 | O29: {=_xlfn.SWITCH(H29,0,0,"-",-1,"+",1)} -> 0 | P29: CEI | Q29: D.613 | R29: D.613/614 | S29: U | T29: =_xlfn.LET( _xlpm.intervaloSoma, IF($S29="R", 'CEI_COMPLETA'!$E:$E, 'CEI_COMPLETA'!$D:$D), SUMIFS(_xlpm.intervaloSoma, 'CEI_COMPLETA'!$A:$A, Ajustes!T$1, 'CEI_COMPLETA'!$B:$B, Ajustes!$Q29) ) -> 40463 | U29: =_xlfn.LET( _xlpm.intervaloSoma, IF($S29="R", 'CEI_COMPLETA'!$E:$E, 'CEI_COMPLETA'!$D:$D), SUMIFS(_xlpm.intervaloSoma, 'CEI_COMPLETA'!$A:$A, Ajustes!U$1, 'CEI_COMPLETA'!$B:$B, Ajustes!$Q29) ) -> 49209 | V29: =_xlfn.LET( _xlpm.intervaloSoma, IF($S29="R", 'CEI_COMPLETA'!$E:$E, 'CEI_COMPLETA'!$D:$D), SUMIFS(_xlpm.intervaloSoma, 'CEI_COMPLETA'!$A:$A, Ajustes!V$1, 'CEI_COMPLETA'!$B:$B, Ajustes!$Q29) ) -> 58636 | W29: =_xlfn.LET( _xlpm.intervaloSoma, IF($S29="R", 'CEI_COMPLETA'!$E:$E, 'CEI_COMPLETA'!$D:$D), SUMIFS(_xlpm.intervaloSoma, 'CEI_COMPLETA'!$A:$A, Ajustes!W$1, 'CEI_COMPLETA'!$B:$B, Ajustes!$Q29) ) -> 63958 | X29: =_xlfn.LET( _xlpm.intervaloSoma, IF($S29="R", 'CEI_COMPLETA'!$E:$E, 'CEI_COMPLETA'!$D:$D), SUMIFS(_xlpm.intervaloSoma, 'CEI_COMPLETA'!$A:$A, Ajustes!X$1, 'CEI_COMPLETA'!$B:$B, Ajustes!$Q29) ) -> 64730 | Y29: =_xlfn.LET( _xlpm.intervaloSoma, IF($S29="R", 'CEI_COMPLETA'!$E:$E, 'CEI_COMPLETA'!$D:$D), SUMIFS(_xlpm.intervaloSoma, 'CEI_COMPLETA'!$A:$A, Ajustes!Y$1, 'CEI_COMPLETA'!$B:$B, Ajustes!$Q29) ) -> 79202 | Z29: =_xlfn.LET( _xlpm.intervaloSoma, IF($S29="R", 'CEI_COMPLETA'!$E:$E, 'CEI_COMPLETA'!$D:$D), SUMIFS(_xlpm.intervaloSoma, 'CEI_COMPLETA'!$A:$A, Ajustes!Z$1, 'CEI_COMPLETA'!$B:$B, Ajustes!$Q29) ) -> 95675 | AA29: =_xlfn.LET( _xlpm.intervaloSoma, IF($S29="R", 'CEI_COMPLETA'!$E:$E, 'CEI_COMPLETA'!$D:$D), SUMIFS(_xlpm.intervaloSoma, 'CEI_COMPLETA'!$A:$A, Ajustes!AA$1, 'CEI_COMPLETA'!$B:$B, Ajustes!$Q29) ) -> 98660 | ... AC29: =_xlfn.LET( _xlpm.intervaloSoma, IF($S29="R", 'CEI_COMPLETA'!$E:$E, 'CEI_COMPLETA'!$D:$D), SUMIFS(_xlpm.intervaloSoma, 'CEI_COMPLETA'!$A:$A, Ajustes!AC$1, 'CEI_COMPLETA'!$B:$B, Ajustes!$Q29) ) -> 107106 | AD29: =_xlfn.LET( _xlpm.intervaloSoma, IF($S29="R", 'CEI_COMPLETA'!$E:$E, 'CEI_COMPLETA'!$D:$D), SUMIFS(_xlpm.intervaloSoma, 'CEI_COMPLETA'!$A:$A, Ajustes!AD$1, 'CEI_COMPLETA'!$B:$B, Ajustes!$R29) ) -> 133417 | AE29: =_xlfn.LET( _xlpm.intervaloSoma, IF($S29="R", 'CEI_COMPLETA'!$E:$E, 'CEI_COMPLETA'!$D:$D), SUMIFS(_xlpm.intervaloSoma, 'CEI_COMPLETA'!$A:$A, Ajustes!AE$1, 'CEI_COMPLETA'!$B:$B, Ajustes!$R29) ) -> 136537 | AF29: =_xlfn.LET( _xlpm.intervaloSoma, IF($S29="R", 'CEI_COMPLETA'!$E:$E, 'CEI_COMPLETA'!$D:$D), SUMIFS(_xlpm.intervaloSoma, 'CEI_COMPLETA'!$A:$A, Ajustes!AF$1, 'CEI_COMPLETA'!$B:$B, Ajustes!$R29) ) -> 168073 | AG29: =_xlfn.LET( _xlpm.intervaloSoma, IF($S29="R", 'CEI_COMPLETA'!$E:$E, 'CEI_COMPLETA'!$D:$D), SUMIFS(_xlpm.intervaloSoma, 'CEI_COMPLETA'!$A:$A, Ajustes!AG$1, 'CEI_COMPLETA'!$B:$B, Ajustes!$R29) ) -> 157833 | AH29: =_xlfn.LET( _xlpm.intervaloSoma, IF($S29="R", 'CEI_COMPLETA'!$E:$E, 'CEI_COMPLETA'!$D:$D), SUMIFS(_xlpm.intervaloSoma, 'CEI_COMPLETA'!$A:$A, Ajustes!AH$1, 'CEI_COMPLETA'!$B:$B, Ajustes!$R29) ) -> 175153 | AI29: =_xlfn.LET( _xlpm.intervaloSoma, IF($S29="R", 'CEI_COMPLETA'!$E:$E, 'CEI_COMPLETA'!$D:$D), SUMIFS(_xlpm.intervaloSoma, 'CEI_COMPLETA'!$A:$A, Ajustes!AI$1, 'CEI_COMPLETA'!$B:$B, Ajustes!$R29) ) -> 222854 | AJ29: =_xlfn.LET( _xlpm.intervaloSoma, IF($S29="R", 'CEI_COMPLETA'!$E:$E, 'CEI_COMPLETA'!$D:$D), SUMIFS(_xlpm.intervaloSoma, 'CEI_COMPLETA'!$A:$A, Ajustes!AJ$1, 'CEI_COMPLETA'!$B:$B, Ajustes!$R29) ) -> 213948 | AK29: =_xlfn.LET( _xlpm.intervaloSoma, IF($S29="R", 'CEI_COMPLETA'!$E:$E, 'CEI_COMPLETA'!$D:$D), SUMIFS(_xlpm.intervaloSoma, 'CEI_COMPLETA'!$A:$A, Ajustes!AK$1, 'CEI_COMPLETA'!$B:$B, Ajustes!$R29) ) -> 199698 | ... AO29: =_xlfn.LET( _xlpm.intervaloSoma, IF($S29="R", 'CEI_COMPLETA'!$E:$E, 'CEI_COMPLETA'!$D:$D), SUMIFS(_xlpm.intervaloSoma, 'CEI_COMPLETA'!$A:$A, Ajustes!AO$1, 'CEI_COMPLETA'!$B:$B, Ajustes!$R29) ) -> 278416
A30: Benefícios sociais, exceto transferências sociais em espécie | I30: {=_xlfn.SWITCH(B30,0,0,"-",-1,"+",1)} -> 0 | J30: {=_xlfn.SWITCH(C30,0,0,"-",-1,"+",1)} -> 0 | K30: {=_xlfn.SWITCH(D30,0,0,"-",-1,"+",1)} -> 0 | L30: {=_xlfn.SWITCH(E30,0,0,"-",-1,"+",1)} -> 0 | M30: {=_xlfn.SWITCH(F30,0,0,"-",-1,"+",1)} -> 0 | N30: {=_xlfn.SWITCH(G30,0,0,"-",-1,"+",1)} -> 0 | O30: {=_xlfn.SWITCH(H30,0,0,"-",-1,"+",1)} -> 0 | P30: CEI | Q30: D.62 | R30: D.62 | S30: R | T30: =_xlfn.LET( _xlpm.intervaloSoma, IF($S30="R", 'CEI_COMPLETA'!$E:$E, 'CEI_COMPLETA'!$D:$D), SUMIFS(_xlpm.intervaloSoma, 'CEI_COMPLETA'!$A:$A, Ajustes!T$1, 'CEI_COMPLETA'!$B:$B, Ajustes!$Q30) ) -> 160298 | U30: =_xlfn.LET( _xlpm.intervaloSoma, IF($S30="R", 'CEI_COMPLETA'!$E:$E, 'CEI_COMPLETA'!$D:$D), SUMIFS(_xlpm.intervaloSoma, 'CEI_COMPLETA'!$A:$A, Ajustes!U$1, 'CEI_COMPLETA'!$B:$B, Ajustes!$Q30) ) -> 183633 | V30: =_xlfn.LET( _xlpm.intervaloSoma, IF($S30="R", 'CEI_COMPLETA'!$E:$E, 'CEI_COMPLETA'!$D:$D), SUMIFS(_xlpm.intervaloSoma, 'CEI_COMPLETA'!$A:$A, Ajustes!V$1, 'CEI_COMPLETA'!$B:$B, Ajustes!$Q30) ) -> 225609 | W30: =_xlfn.LET( _xlpm.intervaloSoma, IF($S30="R", 'CEI_COMPLETA'!$E:$E, 'CEI_COMPLETA'!$D:$D), SUMIFS(_xlpm.intervaloSoma, 'CEI_COMPLETA'!$A:$A, Ajustes!W$1, 'CEI_COMPLETA'!$B:$B, Ajustes!$Q30) ) -> 256543 | X30: =_xlfn.LET( _xlpm.intervaloSoma, IF($S30="R", 'CEI_COMPLETA'!$E:$E, 'CEI_COMPLETA'!$D:$D), SUMIFS(_xlpm.intervaloSoma, 'CEI_COMPLETA'!$A:$A, Ajustes!X$1, 'CEI_COMPLETA'!$B:$B, Ajustes!$Q30) ) -> 283348 | Y30: =_xlfn.LET( _xlpm.intervaloSoma, IF($S30="R", 'CEI_COMPLETA'!$E:$E, 'CEI_COMPLETA'!$D:$D), SUMIFS(_xlpm.intervaloSoma, 'CEI_COMPLETA'!$A:$A, Ajustes!Y$1, 'CEI_COMPLETA'!$B:$B, Ajustes!$Q30) ) -> 321654 | Z30: =_xlfn.LET( _xlpm.intervaloSoma, IF($S30="R", 'CEI_COMPLETA'!$E:$E, 'CEI_COMPLETA'!$D:$D), SUMIFS(_xlpm.intervaloSoma, 'CEI_COMPLETA'!$A:$A, Ajustes!Z$1, 'CEI_COMPLETA'!$B:$B, Ajustes!$Q30) ) -> 366398 | AA30: =_xlfn.LET( _xlpm.intervaloSoma, IF($S30="R", 'CEI_COMPLETA'!$E:$E, 'CEI_COMPLETA'!$D:$D), SUMIFS(_xlpm.intervaloSoma, 'CEI_COMPLETA'!$A:$A, Ajustes!AA$1, 'CEI_COMPLETA'!$B:$B, Ajustes!$Q30) ) -> 406702 | ... AC30: =_xlfn.LET( _xlpm.intervaloSoma, IF($S30="R", 'CEI_COMPLETA'!$E:$E, 'CEI_COMPLETA'!$D:$D), SUMIFS(_xlpm.intervaloSoma, 'CEI_COMPLETA'!$A:$A, Ajustes!AC$1, 'CEI_COMPLETA'!$B:$B, Ajustes!$Q30) ) -> 506919 | AD30: =_xlfn.LET( _xlpm.intervaloSoma, IF($S30="R", 'CEI_COMPLETA'!$E:$E, 'CEI_COMPLETA'!$D:$D), SUMIFS(_xlpm.intervaloSoma, 'CEI_COMPLETA'!$A:$A, Ajustes!AD$1, 'CEI_COMPLETA'!$B:$B, Ajustes!$R30) ) -> 568962 | AE30: =_xlfn.LET( _xlpm.intervaloSoma, IF($S30="R", 'CEI_COMPLETA'!$E:$E, 'CEI_COMPLETA'!$D:$D), SUMIFS(_xlpm.intervaloSoma, 'CEI_COMPLETA'!$A:$A, Ajustes!AE$1, 'CEI_COMPLETA'!$B:$B, Ajustes!$R30) ) -> 644810 | AF30: =_xlfn.LET( _xlpm.intervaloSoma, IF($S30="R", 'CEI_COMPLETA'!$E:$E, 'CEI_COMPLETA'!$D:$D), SUMIFS(_xlpm.intervaloSoma, 'CEI_COMPLETA'!$A:$A, Ajustes!AF$1, 'CEI_COMPLETA'!$B:$B, Ajustes!$R30) ) -> 721459 | AG30: =_xlfn.LET( _xlpm.intervaloSoma, IF($S30="R", 'CEI_COMPLETA'!$E:$E, 'CEI_COMPLETA'!$D:$D), SUMIFS(_xlpm.intervaloSoma, 'CEI_COMPLETA'!$A:$A, Ajustes!AG$1, 'CEI_COMPLETA'!$B:$B, Ajustes!$R30) ) -> 809849 | AH30: =_xlfn.LET( _xlpm.intervaloSoma, IF($S30="R", 'CEI_COMPLETA'!$E:$E, 'CEI_COMPLETA'!$D:$D), SUMIFS(_xlpm.intervaloSoma, 'CEI_COMPLETA'!$A:$A, Ajustes!AH$1, 'CEI_COMPLETA'!$B:$B, Ajustes!$R30) ) -> 911277 | AI30: =_xlfn.LET( _xlpm.intervaloSoma, IF($S30="R", 'CEI_COMPLETA'!$E:$E, 'CEI_COMPLETA'!$D:$D), SUMIFS(_xlpm.intervaloSoma, 'CEI_COMPLETA'!$A:$A, Ajustes!AI$1, 'CEI_COMPLETA'!$B:$B, Ajustes!$R30) ) -> 994425 | AJ30: =_xlfn.LET( _xlpm.intervaloSoma, IF($S30="R", 'CEI_COMPLETA'!$E:$E, 'CEI_COMPLETA'!$D:$D), SUMIFS(_xlpm.intervaloSoma, 'CEI_COMPLETA'!$A:$A, Ajustes!AJ$1, 'CEI_COMPLETA'!$B:$B, Ajustes!$R30) ) -> 1123676 | AK30: =_xlfn.LET( _xlpm.intervaloSoma, IF($S30="R", 'CEI_COMPLETA'!$E:$E, 'CEI_COMPLETA'!$D:$D), SUMIFS(_xlpm.intervaloSoma, 'CEI_COMPLETA'!$A:$A, Ajustes!AK$1, 'CEI_COMPLETA'!$B:$B, Ajustes!$R30) ) -> 1273787 | ... AO30: =_xlfn.LET( _xlpm.intervaloSoma, IF($S30="R", 'CEI_COMPLETA'!$E:$E, 'CEI_COMPLETA'!$D:$D), SUMIFS(_xlpm.intervaloSoma, 'CEI_COMPLETA'!$A:$A, Ajustes!AO$1, 'CEI_COMPLETA'!$B:$B, Ajustes!$R30) ) -> 1563021
A31: Benefícios de seguridade social em numerário | I31: {=_xlfn.SWITCH(B31,0,0,"-",-1,"+",1)} -> 0 | J31: {=_xlfn.SWITCH(C31,0,0,"-",-1,"+",1)} -> 0 | K31: {=_xlfn.SWITCH(D31,0,0,"-",-1,"+",1)} -> 0 | L31: {=_xlfn.SWITCH(E31,0,0,"-",-1,"+",1)} -> 0 | M31: {=_xlfn.SWITCH(F31,0,0,"-",-1,"+",1)} -> 0 | N31: {=_xlfn.SWITCH(G31,0,0,"-",-1,"+",1)} -> 0 | O31: {=_xlfn.SWITCH(H31,0,0,"-",-1,"+",1)} -> 0 | P31: CEI | Q31: D.621 | R31: D.621 | S31: R | T31: =_xlfn.LET( _xlpm.intervaloSoma, IF($S31="R", 'CEI_COMPLETA'!$E:$E, 'CEI_COMPLETA'!$D:$D), SUMIFS(_xlpm.intervaloSoma, 'CEI_COMPLETA'!$A:$A, Ajustes!T$1, 'CEI_COMPLETA'!$B:$B, Ajustes!$Q31) ) -> 70874 | U31: =_xlfn.LET( _xlpm.intervaloSoma, IF($S31="R", 'CEI_COMPLETA'!$E:$E, 'CEI_COMPLETA'!$D:$D), SUMIFS(_xlpm.intervaloSoma, 'CEI_COMPLETA'!$A:$A, Ajustes!U$1, 'CEI_COMPLETA'!$B:$B, Ajustes!$Q31) ) -> 81993 | V31: =_xlfn.LET( _xlpm.intervaloSoma, IF($S31="R", 'CEI_COMPLETA'!$E:$E, 'CEI_COMPLETA'!$D:$D), SUMIFS(_xlpm.intervaloSoma, 'CEI_COMPLETA'!$A:$A, Ajustes!V$1, 'CEI_COMPLETA'!$B:$B, Ajustes!$Q31) ) -> 94664 | W31: =_xlfn.LET( _xlpm.intervaloSoma, IF($S31="R", 'CEI_COMPLETA'!$E:$E, 'CEI_COMPLETA'!$D:$D), SUMIFS(_xlpm.intervaloSoma, 'CEI_COMPLETA'!$A:$A, Ajustes!W$1, 'CEI_COMPLETA'!$B:$B, Ajustes!$Q31) ) -> 116927 | X31: =_xlfn.LET( _xlpm.intervaloSoma, IF($S31="R", 'CEI_COMPLETA'!$E:$E, 'CEI_COMPLETA'!$D:$D), SUMIFS(_xlpm.intervaloSoma, 'CEI_COMPLETA'!$A:$A, Ajustes!X$1, 'CEI_COMPLETA'!$B:$B, Ajustes!$Q31) ) -> 132463 | Y31: =_xlfn.LET( _xlpm.intervaloSoma, IF($S31="R", 'CEI_COMPLETA'!$E:$E, 'CEI_COMPLETA'!$D:$D), SUMIFS(_xlpm.intervaloSoma, 'CEI_COMPLETA'!$A:$A, Ajustes!Y$1, 'CEI_COMPLETA'!$B:$B, Ajustes!$Q31) ) -> 153870 | Z31: =_xlfn.LET( _xlpm.intervaloSoma, IF($S31="R", 'CEI_COMPLETA'!$E:$E, 'CEI_COMPLETA'!$D:$D), SUMIFS(_xlpm.intervaloSoma, 'CEI_COMPLETA'!$A:$A, Ajustes!Z$1, 'CEI_COMPLETA'!$B:$B, Ajustes!$Q31) ) -> 176657 | AA31: =_xlfn.LET( _xlpm.intervaloSoma, IF($S31="R", 'CEI_COMPLETA'!$E:$E, 'CEI_COMPLETA'!$D:$D), SUMIFS(_xlpm.intervaloSoma, 'CEI_COMPLETA'!$A:$A, Ajustes!AA$1, 'CEI_COMPLETA'!$B:$B, Ajustes!$Q31) ) -> 195658 | ... AC31: =_xlfn.LET( _xlpm.intervaloSoma, IF($S31="R", 'CEI_COMPLETA'!$E:$E, 'CEI_COMPLETA'!$D:$D), SUMIFS(_xlpm.intervaloSoma, 'CEI_COMPLETA'!$A:$A, Ajustes!AC$1, 'CEI_COMPLETA'!$B:$B, Ajustes!$Q31) ) -> 245815 | AD31: =_xlfn.LET( _xlpm.intervaloSoma, IF($S31="R", 'CEI_COMPLETA'!$E:$E, 'CEI_COMPLETA'!$D:$D), SUMIFS(_xlpm.intervaloSoma, 'CEI_COMPLETA'!$A:$A, Ajustes!AD$1, 'CEI_COMPLETA'!$B:$B, Ajustes!$R31) ) -> 283363 | AE31: =_xlfn.LET( _xlpm.intervaloSoma, IF($S31="R", 'CEI_COMPLETA'!$E:$E, 'CEI_COMPLETA'!$D:$D), SUMIFS(_xlpm.intervaloSoma, 'CEI_COMPLETA'!$A:$A, Ajustes!AE$1, 'CEI_COMPLETA'!$B:$B, Ajustes!$R31) ) -> 315695 | AF31: =_xlfn.LET( _xlpm.intervaloSoma, IF($S31="R", 'CEI_COMPLETA'!$E:$E, 'CEI_COMPLETA'!$D:$D), SUMIFS(_xlpm.intervaloSoma, 'CEI_COMPLETA'!$A:$A, Ajustes!AF$1, 'CEI_COMPLETA'!$B:$B, Ajustes!$R31) ) -> 357722 | AG31: =_xlfn.LET( _xlpm.intervaloSoma, IF($S31="R", 'CEI_COMPLETA'!$E:$E, 'CEI_COMPLETA'!$D:$D), SUMIFS(_xlpm.intervaloSoma, 'CEI_COMPLETA'!$A:$A, Ajustes!AG$1, 'CEI_COMPLETA'!$B:$B, Ajustes!$R31) ) -> 402748 | AH31: =_xlfn.LET( _xlpm.intervaloSoma, IF($S31="R", 'CEI_COMPLETA'!$E:$E, 'CEI_COMPLETA'!$D:$D), SUMIFS(_xlpm.intervaloSoma, 'CEI_COMPLETA'!$A:$A, Ajustes!AH$1, 'CEI_COMPLETA'!$B:$B, Ajustes!$R31) ) -> 455821 | AI31: =_xlfn.LET( _xlpm.intervaloSoma, IF($S31="R", 'CEI_COMPLETA'!$E:$E, 'CEI_COMPLETA'!$D:$D), SUMIFS(_xlpm.intervaloSoma, 'CEI_COMPLETA'!$A:$A, Ajustes!AI$1, 'CEI_COMPLETA'!$B:$B, Ajustes!$R31) ) -> 493046 | AJ31: =_xlfn.LET( _xlpm.intervaloSoma, IF($S31="R", 'CEI_COMPLETA'!$E:$E, 'CEI_COMPLETA'!$D:$D), SUMIFS(_xlpm.intervaloSoma, 'CEI_COMPLETA'!$A:$A, Ajustes!AJ$1, 'CEI_COMPLETA'!$B:$B, Ajustes!$R31) ) -> 571610 | AK31: =_xlfn.LET( _xlpm.intervaloSoma, IF($S31="R", 'CEI_COMPLETA'!$E:$E, 'CEI_COMPLETA'!$D:$D), SUMIFS(_xlpm.intervaloSoma, 'CEI_COMPLETA'!$A:$A, Ajustes!AK$1, 'CEI_COMPLETA'!$B:$B, Ajustes!$R31) ) -> 622608 | ... AO31: =_xlfn.LET( _xlpm.intervaloSoma, IF($S31="R", 'CEI_COMPLETA'!$E:$E, 'CEI_COMPLETA'!$D:$D), SUMIFS(_xlpm.intervaloSoma, 'CEI_COMPLETA'!$A:$A, Ajustes!AO$1, 'CEI_COMPLETA'!$B:$B, Ajustes!$R31) ) -> 769970
A32: Outros benefícios de seguro social | I32: {=_xlfn.SWITCH(B32,0,0,"-",-1,"+",1)} -> 0 | J32: {=_xlfn.SWITCH(C32,0,0,"-",-1,"+",1)} -> 0 | K32: {=_xlfn.SWITCH(D32,0,0,"-",-1,"+",1)} -> 0 | L32: {=_xlfn.SWITCH(E32,0,0,"-",-1,"+",1)} -> 0 | M32: {=_xlfn.SWITCH(F32,0,0,"-",-1,"+",1)} -> 0 | N32: {=_xlfn.SWITCH(G32,0,0,"-",-1,"+",1)} -> 0 | O32: {=_xlfn.SWITCH(H32,0,0,"-",-1,"+",1)} -> 0 | P32: CEI | Q32: D.622 | R32: D.622 | S32: R | T32: =_xlfn.LET( _xlpm.intervaloSoma, IF($S32="R", 'CEI_COMPLETA'!$E:$E, 'CEI_COMPLETA'!$D:$D), SUMIFS(_xlpm.intervaloSoma, 'CEI_COMPLETA'!$A:$A, Ajustes!T$1, 'CEI_COMPLETA'!$B:$B, Ajustes!$Q32) ) -> 86655 | U32: =_xlfn.LET( _xlpm.intervaloSoma, IF($S32="R", 'CEI_COMPLETA'!$E:$E, 'CEI_COMPLETA'!$D:$D), SUMIFS(_xlpm.intervaloSoma, 'CEI_COMPLETA'!$A:$A, Ajustes!U$1, 'CEI_COMPLETA'!$B:$B, Ajustes!$Q32) ) -> 98537 | V32: =_xlfn.LET( _xlpm.intervaloSoma, IF($S32="R", 'CEI_COMPLETA'!$E:$E, 'CEI_COMPLETA'!$D:$D), SUMIFS(_xlpm.intervaloSoma, 'CEI_COMPLETA'!$A:$A, Ajustes!V$1, 'CEI_COMPLETA'!$B:$B, Ajustes!$Q32) ) -> 125036 | W32: =_xlfn.LET( _xlpm.intervaloSoma, IF($S32="R", 'CEI_COMPLETA'!$E:$E, 'CEI_COMPLETA'!$D:$D), SUMIFS(_xlpm.intervaloSoma, 'CEI_COMPLETA'!$A:$A, Ajustes!W$1, 'CEI_COMPLETA'!$B:$B, Ajustes!$Q32) ) -> 131626 | X32: =_xlfn.LET( _xlpm.intervaloSoma, IF($S32="R", 'CEI_COMPLETA'!$E:$E, 'CEI_COMPLETA'!$D:$D), SUMIFS(_xlpm.intervaloSoma, 'CEI_COMPLETA'!$A:$A, Ajustes!X$1, 'CEI_COMPLETA'!$B:$B, Ajustes!$Q32) ) -> 137903 | Y32: =_xlfn.LET( _xlpm.intervaloSoma, IF($S32="R", 'CEI_COMPLETA'!$E:$E, 'CEI_COMPLETA'!$D:$D), SUMIFS(_xlpm.intervaloSoma, 'CEI_COMPLETA'!$A:$A, Ajustes!Y$1, 'CEI_COMPLETA'!$B:$B, Ajustes!$Q32) ) -> 151885 | Z32: =_xlfn.LET( _xlpm.intervaloSoma, IF($S32="R", 'CEI_COMPLETA'!$E:$E, 'CEI_COMPLETA'!$D:$D), SUMIFS(_xlpm.intervaloSoma, 'CEI_COMPLETA'!$A:$A, Ajustes!Z$1, 'CEI_COMPLETA'!$B:$B, Ajustes!$Q32) ) -> 170469 | AA32: =_xlfn.LET( _xlpm.intervaloSoma, IF($S32="R", 'CEI_COMPLETA'!$E:$E, 'CEI_COMPLETA'!$D:$D), SUMIFS(_xlpm.intervaloSoma, 'CEI_COMPLETA'!$A:$A, Ajustes!AA$1, 'CEI_COMPLETA'!$B:$B, Ajustes!$Q32) ) -> 188363 | ... AC32: =_xlfn.LET( _xlpm.intervaloSoma, IF($S32="R", 'CEI_COMPLETA'!$E:$E, 'CEI_COMPLETA'!$D:$D), SUMIFS(_xlpm.intervaloSoma, 'CEI_COMPLETA'!$A:$A, Ajustes!AC$1, 'CEI_COMPLETA'!$B:$B, Ajustes!$Q32) ) -> 228980 | AD32: =_xlfn.LET( _xlpm.intervaloSoma, IF($S32="R", 'CEI_COMPLETA'!$E:$E, 'CEI_COMPLETA'!$D:$D), SUMIFS(_xlpm.intervaloSoma, 'CEI_COMPLETA'!$A:$A, Ajustes!AD$1, 'CEI_COMPLETA'!$B:$B, Ajustes!$R32) ) -> 245975 | AE32: =_xlfn.LET( _xlpm.intervaloSoma, IF($S32="R", 'CEI_COMPLETA'!$E:$E, 'CEI_COMPLETA'!$D:$D), SUMIFS(_xlpm.intervaloSoma, 'CEI_COMPLETA'!$A:$A, Ajustes!AE$1, 'CEI_COMPLETA'!$B:$B, Ajustes!$R32) ) -> 283445 | AF32: =_xlfn.LET( _xlpm.intervaloSoma, IF($S32="R", 'CEI_COMPLETA'!$E:$E, 'CEI_COMPLETA'!$D:$D), SUMIFS(_xlpm.intervaloSoma, 'CEI_COMPLETA'!$A:$A, Ajustes!AF$1, 'CEI_COMPLETA'!$B:$B, Ajustes!$R32) ) -> 307869 | AG32: =_xlfn.LET( _xlpm.intervaloSoma, IF($S32="R", 'CEI_COMPLETA'!$E:$E, 'CEI_COMPLETA'!$D:$D), SUMIFS(_xlpm.intervaloSoma, 'CEI_COMPLETA'!$A:$A, Ajustes!AG$1, 'CEI_COMPLETA'!$B:$B, Ajustes!$R32) ) -> 341641 | AH32: =_xlfn.LET( _xlpm.intervaloSoma, IF($S32="R", 'CEI_COMPLETA'!$E:$E, 'CEI_COMPLETA'!$D:$D), SUMIFS(_xlpm.intervaloSoma, 'CEI_COMPLETA'!$A:$A, Ajustes!AH$1, 'CEI_COMPLETA'!$B:$B, Ajustes!$R32) ) -> 382922 | AI32: =_xlfn.LET( _xlpm.intervaloSoma, IF($S32="R", 'CEI_COMPLETA'!$E:$E, 'CEI_COMPLETA'!$D:$D), SUMIFS(_xlpm.intervaloSoma, 'CEI_COMPLETA'!$A:$A, Ajustes!AI$1, 'CEI_COMPLETA'!$B:$B, Ajustes!$R32) ) -> 425477 | AJ32: =_xlfn.LET( _xlpm.intervaloSoma, IF($S32="R", 'CEI_COMPLETA'!$E:$E, 'CEI_COMPLETA'!$D:$D), SUMIFS(_xlpm.intervaloSoma, 'CEI_COMPLETA'!$A:$A, Ajustes!AJ$1, 'CEI_COMPLETA'!$B:$B, Ajustes!$R32) ) -> 469527 | AK32: =_xlfn.LET( _xlpm.intervaloSoma, IF($S32="R", 'CEI_COMPLETA'!$E:$E, 'CEI_COMPLETA'!$D:$D), SUMIFS(_xlpm.intervaloSoma, 'CEI_COMPLETA'!$A:$A, Ajustes!AK$1, 'CEI_COMPLETA'!$B:$B, Ajustes!$R32) ) -> 564185 | ... AO32: =_xlfn.LET( _xlpm.intervaloSoma, IF($S32="R", 'CEI_COMPLETA'!$E:$E, 'CEI_COMPLETA'!$D:$D), SUMIFS(_xlpm.intervaloSoma, 'CEI_COMPLETA'!$A:$A, Ajustes!AO$1, 'CEI_COMPLETA'!$B:$B, Ajustes!$R32) ) -> 623598
A33: Benefícios de assistência social em numerário | I33: {=_xlfn.SWITCH(B33,0,0,"-",-1,"+",1)} -> 0 | J33: {=_xlfn.SWITCH(C33,0,0,"-",-1,"+",1)} -> 0 | K33: {=_xlfn.SWITCH(D33,0,0,"-",-1,"+",1)} -> 0 | L33: {=_xlfn.SWITCH(E33,0,0,"-",-1,"+",1)} -> 0 | M33: {=_xlfn.SWITCH(F33,0,0,"-",-1,"+",1)} -> 0 | N33: {=_xlfn.SWITCH(G33,0,0,"-",-1,"+",1)} -> 0 | O33: {=_xlfn.SWITCH(H33,0,0,"-",-1,"+",1)} -> 0 | P33: CEI | Q33: D.623 | R33: D.623 | S33: R | T33: =_xlfn.LET( _xlpm.intervaloSoma, IF($S33="R", 'CEI_COMPLETA'!$E:$E, 'CEI_COMPLETA'!$D:$D), SUMIFS(_xlpm.intervaloSoma, 'CEI_COMPLETA'!$A:$A, Ajustes!T$1, 'CEI_COMPLETA'!$B:$B, Ajustes!$Q33) ) -> 2769 | U33: =_xlfn.LET( _xlpm.intervaloSoma, IF($S33="R", 'CEI_COMPLETA'!$E:$E, 'CEI_COMPLETA'!$D:$D), SUMIFS(_xlpm.intervaloSoma, 'CEI_COMPLETA'!$A:$A, Ajustes!U$1, 'CEI_COMPLETA'!$B:$B, Ajustes!$Q33) ) -> 3103 | V33: =_xlfn.LET( _xlpm.intervaloSoma, IF($S33="R", 'CEI_COMPLETA'!$E:$E, 'CEI_COMPLETA'!$D:$D), SUMIFS(_xlpm.intervaloSoma, 'CEI_COMPLETA'!$A:$A, Ajustes!V$1, 'CEI_COMPLETA'!$B:$B, Ajustes!$Q33) ) -> 5909 | W33: =_xlfn.LET( _xlpm.intervaloSoma, IF($S33="R", 'CEI_COMPLETA'!$E:$E, 'CEI_COMPLETA'!$D:$D), SUMIFS(_xlpm.intervaloSoma, 'CEI_COMPLETA'!$A:$A, Ajustes!W$1, 'CEI_COMPLETA'!$B:$B, Ajustes!$Q33) ) -> 7990 | X33: =_xlfn.LET( _xlpm.intervaloSoma, IF($S33="R", 'CEI_COMPLETA'!$E:$E, 'CEI_COMPLETA'!$D:$D), SUMIFS(_xlpm.intervaloSoma, 'CEI_COMPLETA'!$A:$A, Ajustes!X$1, 'CEI_COMPLETA'!$B:$B, Ajustes!$Q33) ) -> 12982 | Y33: =_xlfn.LET( _xlpm.intervaloSoma, IF($S33="R", 'CEI_COMPLETA'!$E:$E, 'CEI_COMPLETA'!$D:$D), SUMIFS(_xlpm.intervaloSoma, 'CEI_COMPLETA'!$A:$A, Ajustes!Y$1, 'CEI_COMPLETA'!$B:$B, Ajustes!$Q33) ) -> 15899 | Z33: =_xlfn.LET( _xlpm.intervaloSoma, IF($S33="R", 'CEI_COMPLETA'!$E:$E, 'CEI_COMPLETA'!$D:$D), SUMIFS(_xlpm.intervaloSoma, 'CEI_COMPLETA'!$A:$A, Ajustes!Z$1, 'CEI_COMPLETA'!$B:$B, Ajustes!$Q33) ) -> 19272 | AA33: =_xlfn.LET( _xlpm.intervaloSoma, IF($S33="R", 'CEI_COMPLETA'!$E:$E, 'CEI_COMPLETA'!$D:$D), SUMIFS(_xlpm.intervaloSoma, 'CEI_COMPLETA'!$A:$A, Ajustes!AA$1, 'CEI_COMPLETA'!$B:$B, Ajustes!$Q33) ) -> 22681 | ... AC33: =_xlfn.LET( _xlpm.intervaloSoma, IF($S33="R", 'CEI_COMPLETA'!$E:$E, 'CEI_COMPLETA'!$D:$D), SUMIFS(_xlpm.intervaloSoma, 'CEI_COMPLETA'!$A:$A, Ajustes!AC$1, 'CEI_COMPLETA'!$B:$B, Ajustes!$Q33) ) -> 32124 | AD33: =_xlfn.LET( _xlpm.intervaloSoma, IF($S33="R", 'CEI_COMPLETA'!$E:$E, 'CEI_COMPLETA'!$D:$D), SUMIFS(_xlpm.intervaloSoma, 'CEI_COMPLETA'!$A:$A, Ajustes!AD$1, 'CEI_COMPLETA'!$B:$B, Ajustes!$R33) ) -> 39624 | AE33: =_xlfn.LET( _xlpm.intervaloSoma, IF($S33="R", 'CEI_COMPLETA'!$E:$E, 'CEI_COMPLETA'!$D:$D), SUMIFS(_xlpm.intervaloSoma, 'CEI_COMPLETA'!$A:$A, Ajustes!AE$1, 'CEI_COMPLETA'!$B:$B, Ajustes!$R33) ) -> 45670 | AF33: =_xlfn.LET( _xlpm.intervaloSoma, IF($S33="R", 'CEI_COMPLETA'!$E:$E, 'CEI_COMPLETA'!$D:$D), SUMIFS(_xlpm.intervaloSoma, 'CEI_COMPLETA'!$A:$A, Ajustes!AF$1, 'CEI_COMPLETA'!$B:$B, Ajustes!$R33) ) -> 55868 | AG33: =_xlfn.LET( _xlpm.intervaloSoma, IF($S33="R", 'CEI_COMPLETA'!$E:$E, 'CEI_COMPLETA'!$D:$D), SUMIFS(_xlpm.intervaloSoma, 'CEI_COMPLETA'!$A:$A, Ajustes!AG$1, 'CEI_COMPLETA'!$B:$B, Ajustes!$R33) ) -> 65460 | AH33: =_xlfn.LET( _xlpm.intervaloSoma, IF($S33="R", 'CEI_COMPLETA'!$E:$E, 'CEI_COMPLETA'!$D:$D), SUMIFS(_xlpm.intervaloSoma, 'CEI_COMPLETA'!$A:$A, Ajustes!AH$1, 'CEI_COMPLETA'!$B:$B, Ajustes!$R33) ) -> 72534 | AI33: =_xlfn.LET( _xlpm.intervaloSoma, IF($S33="R", 'CEI_COMPLETA'!$E:$E, 'CEI_COMPLETA'!$D:$D), SUMIFS(_xlpm.intervaloSoma, 'CEI_COMPLETA'!$A:$A, Ajustes!AI$1, 'CEI_COMPLETA'!$B:$B, Ajustes!$R33) ) -> 75902 | AJ33: =_xlfn.LET( _xlpm.intervaloSoma, IF($S33="R", 'CEI_COMPLETA'!$E:$E, 'CEI_COMPLETA'!$D:$D), SUMIFS(_xlpm.intervaloSoma, 'CEI_COMPLETA'!$A:$A, Ajustes!AJ$1, 'CEI_COMPLETA'!$B:$B, Ajustes!$R33) ) -> 82539 | AK33: =_xlfn.LET( _xlpm.intervaloSoma, IF($S33="R", 'CEI_COMPLETA'!$E:$E, 'CEI_COMPLETA'!$D:$D), SUMIFS(_xlpm.intervaloSoma, 'CEI_COMPLETA'!$A:$A, Ajustes!AK$1, 'CEI_COMPLETA'!$B:$B, Ajustes!$R33) ) -> 86994 | ... AO33: =_xlfn.LET( _xlpm.intervaloSoma, IF($S33="R", 'CEI_COMPLETA'!$E:$E, 'CEI_COMPLETA'!$D:$D), SUMIFS(_xlpm.intervaloSoma, 'CEI_COMPLETA'!$A:$A, Ajustes!AO$1, 'CEI_COMPLETA'!$B:$B, Ajustes!$R33) ) -> 169453
A34: Juros | I34: {=_xlfn.SWITCH(B34,0,0,"-",-1,"+",1)} -> 0 | J34: {=_xlfn.SWITCH(C34,0,0,"-",-1,"+",1)} -> 0 | K34: {=_xlfn.SWITCH(D34,0,0,"-",-1,"+",1)} -> 0 | L34: {=_xlfn.SWITCH(E34,0,0,"-",-1,"+",1)} -> 0 | M34: {=_xlfn.SWITCH(F34,0,0,"-",-1,"+",1)} -> 0 | N34: {=_xlfn.SWITCH(G34,0,0,"-",-1,"+",1)} -> 0 | O34: {=_xlfn.SWITCH(H34,0,0,"-",-1,"+",1)} -> 0 | P34: CEI | T34: =T36-T35 -> 50122 | U34: =U36-U35 -> 53044 | V34: =V36-V35 -> 57051 | W34: =W36-W35 -> 58594 | X34: =X36-X35 -> 48614 | Y34: =Y36-Y35 -> 57713 | Z34: =Z36-Z35 -> 52663 | AA34: =AA36-AA35 -> 58695 | ... AO34: =AO36-AO35 -> 44522
A35: USOS | B35: + | F35: + | I35: {=_xlfn.SWITCH(B35,0,0,"-",-1,"+",1)} -> 1 | J35: {=_xlfn.SWITCH(C35,0,0,"-",-1,"+",1)} -> 0 | K35: {=_xlfn.SWITCH(D35,0,0,"-",-1,"+",1)} -> 0 | L35: {=_xlfn.SWITCH(E35,0,0,"-",-1,"+",1)} -> 0 | M35: {=_xlfn.SWITCH(F35,0,0,"-",-1,"+",1)} -> 1 | N35: {=_xlfn.SWITCH(G35,0,0,"-",-1,"+",1)} -> 0 | O35: {=_xlfn.SWITCH(H35,0,0,"-",-1,"+",1)} -> 0 | P35: CEI | Q35: D.41 | R35: D.41 | S35: U | T35: =_xlfn.LET( _xlpm.intervaloSoma, IF($S35="R", 'CEI_COMPLETA'!$E:$E, 'CEI_COMPLETA'!$D:$D), SUMIFS(_xlpm.intervaloSoma, 'CEI_COMPLETA'!$A:$A, Ajustes!T$1, 'CEI_COMPLETA'!$B:$B, Ajustes!$Q35) ) -> 17027 | U35: =_xlfn.LET( _xlpm.intervaloSoma, IF($S35="R", 'CEI_COMPLETA'!$E:$E, 'CEI_COMPLETA'!$D:$D), SUMIFS(_xlpm.intervaloSoma, 'CEI_COMPLETA'!$A:$A, Ajustes!U$1, 'CEI_COMPLETA'!$B:$B, Ajustes!$Q35) ) -> 18273 | V35: =_xlfn.LET( _xlpm.intervaloSoma, IF($S35="R", 'CEI_COMPLETA'!$E:$E, 'CEI_COMPLETA'!$D:$D), SUMIFS(_xlpm.intervaloSoma, 'CEI_COMPLETA'!$A:$A, Ajustes!V$1, 'CEI_COMPLETA'!$B:$B, Ajustes!$Q35) ) -> 19915 | W35: =_xlfn.LET( _xlpm.intervaloSoma, IF($S35="R", 'CEI_COMPLETA'!$E:$E, 'CEI_COMPLETA'!$D:$D), SUMIFS(_xlpm.intervaloSoma, 'CEI_COMPLETA'!$A:$A, Ajustes!W$1, 'CEI_COMPLETA'!$B:$B, Ajustes!$Q35) ) -> 26186 | X35: =_xlfn.LET( _xlpm.intervaloSoma, IF($S35="R", 'CEI_COMPLETA'!$E:$E, 'CEI_COMPLETA'!$D:$D), SUMIFS(_xlpm.intervaloSoma, 'CEI_COMPLETA'!$A:$A, Ajustes!X$1, 'CEI_COMPLETA'!$B:$B, Ajustes!$Q35) ) -> 25666 | Y35: =_xlfn.LET( _xlpm.intervaloSoma, IF($S35="R", 'CEI_COMPLETA'!$E:$E, 'CEI_COMPLETA'!$D:$D), SUMIFS(_xlpm.intervaloSoma, 'CEI_COMPLETA'!$A:$A, Ajustes!Y$1, 'CEI_COMPLETA'!$B:$B, Ajustes!$Q35) ) -> 44740 | Z35: =_xlfn.LET( _xlpm.intervaloSoma, IF($S35="R", 'CEI_COMPLETA'!$E:$E, 'CEI_COMPLETA'!$D:$D), SUMIFS(_xlpm.intervaloSoma, 'CEI_COMPLETA'!$A:$A, Ajustes!Z$1, 'CEI_COMPLETA'!$B:$B, Ajustes!$Q35) ) -> 62973 | AA35: =_xlfn.LET( _xlpm.intervaloSoma, IF($S35="R", 'CEI_COMPLETA'!$E:$E, 'CEI_COMPLETA'!$D:$D), SUMIFS(_xlpm.intervaloSoma, 'CEI_COMPLETA'!$A:$A, Ajustes!AA$1, 'CEI_COMPLETA'!$B:$B, Ajustes!$Q35) ) -> 78078 | ... AC35: =_xlfn.LET( _xlpm.intervaloSoma, IF($S35="R", 'CEI_COMPLETA'!$E:$E, 'CEI_COMPLETA'!$D:$D), SUMIFS(_xlpm.intervaloSoma, 'CEI_COMPLETA'!$A:$A, Ajustes!AC$1, 'CEI_COMPLETA'!$B:$B, Ajustes!$Q35) ) -> 174552 | AD35: =_xlfn.LET( _xlpm.intervaloSoma, IF($S35="R", 'CEI_COMPLETA'!$E:$E, 'CEI_COMPLETA'!$D:$D), SUMIFS(_xlpm.intervaloSoma, 'CEI_COMPLETA'!$A:$A, Ajustes!AD$1, 'CEI_COMPLETA'!$B:$B, Ajustes!$R35) ) -> 181183 | AE35: =_xlfn.LET( _xlpm.intervaloSoma, IF($S35="R", 'CEI_COMPLETA'!$E:$E, 'CEI_COMPLETA'!$D:$D), SUMIFS(_xlpm.intervaloSoma, 'CEI_COMPLETA'!$A:$A, Ajustes!AE$1, 'CEI_COMPLETA'!$B:$B, Ajustes!$R35) ) -> 249840 | AF35: =_xlfn.LET( _xlpm.intervaloSoma, IF($S35="R", 'CEI_COMPLETA'!$E:$E, 'CEI_COMPLETA'!$D:$D), SUMIFS(_xlpm.intervaloSoma, 'CEI_COMPLETA'!$A:$A, Ajustes!AF$1, 'CEI_COMPLETA'!$B:$B, Ajustes!$R35) ) -> 252365 | AG35: =_xlfn.LET( _xlpm.intervaloSoma, IF($S35="R", 'CEI_COMPLETA'!$E:$E, 'CEI_COMPLETA'!$D:$D), SUMIFS(_xlpm.intervaloSoma, 'CEI_COMPLETA'!$A:$A, Ajustes!AG$1, 'CEI_COMPLETA'!$B:$B, Ajustes!$R35) ) -> 243020 | AH35: =_xlfn.LET( _xlpm.intervaloSoma, IF($S35="R", 'CEI_COMPLETA'!$E:$E, 'CEI_COMPLETA'!$D:$D), SUMIFS(_xlpm.intervaloSoma, 'CEI_COMPLETA'!$A:$A, Ajustes!AH$1, 'CEI_COMPLETA'!$B:$B, Ajustes!$R35) ) -> 299515 | AI35: =_xlfn.LET( _xlpm.intervaloSoma, IF($S35="R", 'CEI_COMPLETA'!$E:$E, 'CEI_COMPLETA'!$D:$D), SUMIFS(_xlpm.intervaloSoma, 'CEI_COMPLETA'!$A:$A, Ajustes!AI$1, 'CEI_COMPLETA'!$B:$B, Ajustes!$R35) ) -> 361884 | AJ35: =_xlfn.LET( _xlpm.intervaloSoma, IF($S35="R", 'CEI_COMPLETA'!$E:$E, 'CEI_COMPLETA'!$D:$D), SUMIFS(_xlpm.intervaloSoma, 'CEI_COMPLETA'!$A:$A, Ajustes!AJ$1, 'CEI_COMPLETA'!$B:$B, Ajustes!$R35) ) -> 387739 | AK35: =_xlfn.LET( _xlpm.intervaloSoma, IF($S35="R", 'CEI_COMPLETA'!$E:$E, 'CEI_COMPLETA'!$D:$D), SUMIFS(_xlpm.intervaloSoma, 'CEI_COMPLETA'!$A:$A, Ajustes!AK$1, 'CEI_COMPLETA'!$B:$B, Ajustes!$R35) ) -> 345699 | ... AO35: =_xlfn.LET( _xlpm.intervaloSoma, IF($S35="R", 'CEI_COMPLETA'!$E:$E, 'CEI_COMPLETA'!$D:$D), SUMIFS(_xlpm.intervaloSoma, 'CEI_COMPLETA'!$A:$A, Ajustes!AO$1, 'CEI_COMPLETA'!$B:$B, Ajustes!$R35) ) -> 280195
A36: RECURSOS | I36: {=_xlfn.SWITCH(B36,0,0,"-",-1,"+",1)} -> 0 | J36: {=_xlfn.SWITCH(C36,0,0,"-",-1,"+",1)} -> 0 | K36: {=_xlfn.SWITCH(D36,0,0,"-",-1,"+",1)} -> 0 | L36: {=_xlfn.SWITCH(E36,0,0,"-",-1,"+",1)} -> 0 | M36: {=_xlfn.SWITCH(F36,0,0,"-",-1,"+",1)} -> 0 | N36: {=_xlfn.SWITCH(G36,0,0,"-",-1,"+",1)} -> 0 | O36: {=_xlfn.SWITCH(H36,0,0,"-",-1,"+",1)} -> 0 | P36: CEI | Q36: D.41 | R36: D.41 | S36: R | T36: =_xlfn.LET( _xlpm.intervaloSoma, IF($S36="R", 'CEI_COMPLETA'!$E:$E, 'CEI_COMPLETA'!$D:$D), SUMIFS(_xlpm.intervaloSoma, 'CEI_COMPLETA'!$A:$A, Ajustes!T$1, 'CEI_COMPLETA'!$B:$B, Ajustes!$Q36) ) -> 67149 | U36: =_xlfn.LET( _xlpm.intervaloSoma, IF($S36="R", 'CEI_COMPLETA'!$E:$E, 'CEI_COMPLETA'!$D:$D), SUMIFS(_xlpm.intervaloSoma, 'CEI_COMPLETA'!$A:$A, Ajustes!U$1, 'CEI_COMPLETA'!$B:$B, Ajustes!$Q36) ) -> 71317 | V36: =_xlfn.LET( _xlpm.intervaloSoma, IF($S36="R", 'CEI_COMPLETA'!$E:$E, 'CEI_COMPLETA'!$D:$D), SUMIFS(_xlpm.intervaloSoma, 'CEI_COMPLETA'!$A:$A, Ajustes!V$1, 'CEI_COMPLETA'!$B:$B, Ajustes!$Q36) ) -> 76966 | W36: =_xlfn.LET( _xlpm.intervaloSoma, IF($S36="R", 'CEI_COMPLETA'!$E:$E, 'CEI_COMPLETA'!$D:$D), SUMIFS(_xlpm.intervaloSoma, 'CEI_COMPLETA'!$A:$A, Ajustes!W$1, 'CEI_COMPLETA'!$B:$B, Ajustes!$Q36) ) -> 84780 | X36: =_xlfn.LET( _xlpm.intervaloSoma, IF($S36="R", 'CEI_COMPLETA'!$E:$E, 'CEI_COMPLETA'!$D:$D), SUMIFS(_xlpm.intervaloSoma, 'CEI_COMPLETA'!$A:$A, Ajustes!X$1, 'CEI_COMPLETA'!$B:$B, Ajustes!$Q36) ) -> 74280 | Y36: =_xlfn.LET( _xlpm.intervaloSoma, IF($S36="R", 'CEI_COMPLETA'!$E:$E, 'CEI_COMPLETA'!$D:$D), SUMIFS(_xlpm.intervaloSoma, 'CEI_COMPLETA'!$A:$A, Ajustes!Y$1, 'CEI_COMPLETA'!$B:$B, Ajustes!$Q36) ) -> 102453 | Z36: =_xlfn.LET( _xlpm.intervaloSoma, IF($S36="R", 'CEI_COMPLETA'!$E:$E, 'CEI_COMPLETA'!$D:$D), SUMIFS(_xlpm.intervaloSoma, 'CEI_COMPLETA'!$A:$A, Ajustes!Z$1, 'CEI_COMPLETA'!$B:$B, Ajustes!$Q36) ) -> 115636 | AA36: =_xlfn.LET( _xlpm.intervaloSoma, IF($S36="R", 'CEI_COMPLETA'!$E:$E, 'CEI_COMPLETA'!$D:$D), SUMIFS(_xlpm.intervaloSoma, 'CEI_COMPLETA'!$A:$A, Ajustes!AA$1, 'CEI_COMPLETA'!$B:$B, Ajustes!$Q36) ) -> 136773 | ... AC36: =_xlfn.LET( _xlpm.intervaloSoma, IF($S36="R", 'CEI_COMPLETA'!$E:$E, 'CEI_COMPLETA'!$D:$D), SUMIFS(_xlpm.intervaloSoma, 'CEI_COMPLETA'!$A:$A, Ajustes!AC$1, 'CEI_COMPLETA'!$B:$B, Ajustes!$Q36) ) -> 250244 | AD36: =_xlfn.LET( _xlpm.intervaloSoma, IF($S36="R", 'CEI_COMPLETA'!$E:$E, 'CEI_COMPLETA'!$D:$D), SUMIFS(_xlpm.intervaloSoma, 'CEI_COMPLETA'!$A:$A, Ajustes!AD$1, 'CEI_COMPLETA'!$B:$B, Ajustes!$R36) ) -> 265829 | AE36: =_xlfn.LET( _xlpm.intervaloSoma, IF($S36="R", 'CEI_COMPLETA'!$E:$E, 'CEI_COMPLETA'!$D:$D), SUMIFS(_xlpm.intervaloSoma, 'CEI_COMPLETA'!$A:$A, Ajustes!AE$1, 'CEI_COMPLETA'!$B:$B, Ajustes!$R36) ) -> 332315 | AF36: =_xlfn.LET( _xlpm.intervaloSoma, IF($S36="R", 'CEI_COMPLETA'!$E:$E, 'CEI_COMPLETA'!$D:$D), SUMIFS(_xlpm.intervaloSoma, 'CEI_COMPLETA'!$A:$A, Ajustes!AF$1, 'CEI_COMPLETA'!$B:$B, Ajustes!$R36) ) -> 337723 | AG36: =_xlfn.LET( _xlpm.intervaloSoma, IF($S36="R", 'CEI_COMPLETA'!$E:$E, 'CEI_COMPLETA'!$D:$D), SUMIFS(_xlpm.intervaloSoma, 'CEI_COMPLETA'!$A:$A, Ajustes!AG$1, 'CEI_COMPLETA'!$B:$B, Ajustes!$R36) ) -> 319710 | AH36: =_xlfn.LET( _xlpm.intervaloSoma, IF($S36="R", 'CEI_COMPLETA'!$E:$E, 'CEI_COMPLETA'!$D:$D), SUMIFS(_xlpm.intervaloSoma, 'CEI_COMPLETA'!$A:$A, Ajustes!AH$1, 'CEI_COMPLETA'!$B:$B, Ajustes!$R36) ) -> 396713 | AI36: =_xlfn.LET( _xlpm.intervaloSoma, IF($S36="R", 'CEI_COMPLETA'!$E:$E, 'CEI_COMPLETA'!$D:$D), SUMIFS(_xlpm.intervaloSoma, 'CEI_COMPLETA'!$A:$A, Ajustes!AI$1, 'CEI_COMPLETA'!$B:$B, Ajustes!$R36) ) -> 481361 | AJ36: =_xlfn.LET( _xlpm.intervaloSoma, IF($S36="R", 'CEI_COMPLETA'!$E:$E, 'CEI_COMPLETA'!$D:$D), SUMIFS(_xlpm.intervaloSoma, 'CEI_COMPLETA'!$A:$A, Ajustes!AJ$1, 'CEI_COMPLETA'!$B:$B, Ajustes!$R36) ) -> 483297 | AK36: =_xlfn.LET( _xlpm.intervaloSoma, IF($S36="R", 'CEI_COMPLETA'!$E:$E, 'CEI_COMPLETA'!$D:$D), SUMIFS(_xlpm.intervaloSoma, 'CEI_COMPLETA'!$A:$A, Ajustes!AK$1, 'CEI_COMPLETA'!$B:$B, Ajustes!$R36) ) -> 436148 | ... AO36: =_xlfn.LET( _xlpm.intervaloSoma, IF($S36="R", 'CEI_COMPLETA'!$E:$E, 'CEI_COMPLETA'!$D:$D), SUMIFS(_xlpm.intervaloSoma, 'CEI_COMPLETA'!$A:$A, Ajustes!AO$1, 'CEI_COMPLETA'!$B:$B, Ajustes!$R36) ) -> 324717
A37: Outras transferências correntes | I37: {=_xlfn.SWITCH(B37,0,0,"-",-1,"+",1)} -> 0 | J37: {=_xlfn.SWITCH(C37,0,0,"-",-1,"+",1)} -> 0 | K37: {=_xlfn.SWITCH(D37,0,0,"-",-1,"+",1)} -> 0 | L37: {=_xlfn.SWITCH(E37,0,0,"-",-1,"+",1)} -> 0 | M37: {=_xlfn.SWITCH(F37,0,0,"-",-1,"+",1)} -> 0 | N37: {=_xlfn.SWITCH(G37,0,0,"-",-1,"+",1)} -> 0 | O37: {=_xlfn.SWITCH(H37,0,0,"-",-1,"+",1)} -> 0 | P37: CEI | T37: =T39-T38 -> -8598 | U37: =U39-U38 -> -9410 | V37: =V39-V38 -> -9696 | W37: =W39-W38 -> -4361 | X37: =X39-X38 -> -5989 | Y37: =Y39-Y38 -> -9572 | Z37: =Z39-Z38 -> -13357 | AA37: =AA39-AA38 -> -17196 | ... AO37: =AO39-AO38 -> -30357
A38: USOS | B38: + | G38: + | I38: {=_xlfn.SWITCH(B38,0,0,"-",-1,"+",1)} -> 1 | J38: {=_xlfn.SWITCH(C38,0,0,"-",-1,"+",1)} -> 0 | K38: {=_xlfn.SWITCH(D38,0,0,"-",-1,"+",1)} -> 0 | L38: {=_xlfn.SWITCH(E38,0,0,"-",-1,"+",1)} -> 0 | M38: {=_xlfn.SWITCH(F38,0,0,"-",-1,"+",1)} -> 0 | N38: {=_xlfn.SWITCH(G38,0,0,"-",-1,"+",1)} -> 1 | O38: {=_xlfn.SWITCH(H38,0,0,"-",-1,"+",1)} -> 0 | P38: CEI | Q38: D.7 | R38: D.7 | S38: U | T38: =_xlfn.LET( _xlpm.intervaloSoma, IF($S38="R", 'CEI_COMPLETA'!$E:$E, 'CEI_COMPLETA'!$D:$D), SUMIFS(_xlpm.intervaloSoma, 'CEI_COMPLETA'!$A:$A, Ajustes!T$1, 'CEI_COMPLETA'!$B:$B, Ajustes!$Q38) ) -> 15190 | U38: =_xlfn.LET( _xlpm.intervaloSoma, IF($S38="R", 'CEI_COMPLETA'!$E:$E, 'CEI_COMPLETA'!$D:$D), SUMIFS(_xlpm.intervaloSoma, 'CEI_COMPLETA'!$A:$A, Ajustes!U$1, 'CEI_COMPLETA'!$B:$B, Ajustes!$Q38) ) -> 18577 | V38: =_xlfn.LET( _xlpm.intervaloSoma, IF($S38="R", 'CEI_COMPLETA'!$E:$E, 'CEI_COMPLETA'!$D:$D), SUMIFS(_xlpm.intervaloSoma, 'CEI_COMPLETA'!$A:$A, Ajustes!V$1, 'CEI_COMPLETA'!$B:$B, Ajustes!$Q38) ) -> 19448 | W38: =_xlfn.LET( _xlpm.intervaloSoma, IF($S38="R", 'CEI_COMPLETA'!$E:$E, 'CEI_COMPLETA'!$D:$D), SUMIFS(_xlpm.intervaloSoma, 'CEI_COMPLETA'!$A:$A, Ajustes!W$1, 'CEI_COMPLETA'!$B:$B, Ajustes!$Q38) ) -> 18414 | X38: =_xlfn.LET( _xlpm.intervaloSoma, IF($S38="R", 'CEI_COMPLETA'!$E:$E, 'CEI_COMPLETA'!$D:$D), SUMIFS(_xlpm.intervaloSoma, 'CEI_COMPLETA'!$A:$A, Ajustes!X$1, 'CEI_COMPLETA'!$B:$B, Ajustes!$Q38) ) -> 20109 | Y38: =_xlfn.LET( _xlpm.intervaloSoma, IF($S38="R", 'CEI_COMPLETA'!$E:$E, 'CEI_COMPLETA'!$D:$D), SUMIFS(_xlpm.intervaloSoma, 'CEI_COMPLETA'!$A:$A, Ajustes!Y$1, 'CEI_COMPLETA'!$B:$B, Ajustes!$Q38) ) -> 24340 | Z38: =_xlfn.LET( _xlpm.intervaloSoma, IF($S38="R", 'CEI_COMPLETA'!$E:$E, 'CEI_COMPLETA'!$D:$D), SUMIFS(_xlpm.intervaloSoma, 'CEI_COMPLETA'!$A:$A, Ajustes!Z$1, 'CEI_COMPLETA'!$B:$B, Ajustes!$Q38) ) -> 28375 | AA38: =_xlfn.LET( _xlpm.intervaloSoma, IF($S38="R", 'CEI_COMPLETA'!$E:$E, 'CEI_COMPLETA'!$D:$D), SUMIFS(_xlpm.intervaloSoma, 'CEI_COMPLETA'!$A:$A, Ajustes!AA$1, 'CEI_COMPLETA'!$B:$B, Ajustes!$Q38) ) -> 32747 | ... AC38: =_xlfn.LET( _xlpm.intervaloSoma, IF($S38="R", 'CEI_COMPLETA'!$E:$E, 'CEI_COMPLETA'!$D:$D), SUMIFS(_xlpm.intervaloSoma, 'CEI_COMPLETA'!$A:$A, Ajustes!AC$1, 'CEI_COMPLETA'!$B:$B, Ajustes!$Q38) ) -> 30753 | AD38: =_xlfn.LET( _xlpm.intervaloSoma, IF($S38="R", 'CEI_COMPLETA'!$E:$E, 'CEI_COMPLETA'!$D:$D), SUMIFS(_xlpm.intervaloSoma, 'CEI_COMPLETA'!$A:$A, Ajustes!AD$1, 'CEI_COMPLETA'!$B:$B, Ajustes!$R38) ) -> 54719 | AE38: =_xlfn.LET( _xlpm.intervaloSoma, IF($S38="R", 'CEI_COMPLETA'!$E:$E, 'CEI_COMPLETA'!$D:$D), SUMIFS(_xlpm.intervaloSoma, 'CEI_COMPLETA'!$A:$A, Ajustes!AE$1, 'CEI_COMPLETA'!$B:$B, Ajustes!$R38) ) -> 52635 | AF38: =_xlfn.LET( _xlpm.intervaloSoma, IF($S38="R", 'CEI_COMPLETA'!$E:$E, 'CEI_COMPLETA'!$D:$D), SUMIFS(_xlpm.intervaloSoma, 'CEI_COMPLETA'!$A:$A, Ajustes!AF$1, 'CEI_COMPLETA'!$B:$B, Ajustes!$R38) ) -> 66769 | AG38: =_xlfn.LET( _xlpm.intervaloSoma, IF($S38="R", 'CEI_COMPLETA'!$E:$E, 'CEI_COMPLETA'!$D:$D), SUMIFS(_xlpm.intervaloSoma, 'CEI_COMPLETA'!$A:$A, Ajustes!AG$1, 'CEI_COMPLETA'!$B:$B, Ajustes!$R38) ) -> 76459 | AH38: =_xlfn.LET( _xlpm.intervaloSoma, IF($S38="R", 'CEI_COMPLETA'!$E:$E, 'CEI_COMPLETA'!$D:$D), SUMIFS(_xlpm.intervaloSoma, 'CEI_COMPLETA'!$A:$A, Ajustes!AH$1, 'CEI_COMPLETA'!$B:$B, Ajustes!$R38) ) -> 78162 | AI38: =_xlfn.LET( _xlpm.intervaloSoma, IF($S38="R", 'CEI_COMPLETA'!$E:$E, 'CEI_COMPLETA'!$D:$D), SUMIFS(_xlpm.intervaloSoma, 'CEI_COMPLETA'!$A:$A, Ajustes!AI$1, 'CEI_COMPLETA'!$B:$B, Ajustes!$R38) ) -> 101688 | AJ38: =_xlfn.LET( _xlpm.intervaloSoma, IF($S38="R", 'CEI_COMPLETA'!$E:$E, 'CEI_COMPLETA'!$D:$D), SUMIFS(_xlpm.intervaloSoma, 'CEI_COMPLETA'!$A:$A, Ajustes!AJ$1, 'CEI_COMPLETA'!$B:$B, Ajustes!$R38) ) -> 109541 | AK38: =_xlfn.LET( _xlpm.intervaloSoma, IF($S38="R", 'CEI_COMPLETA'!$E:$E, 'CEI_COMPLETA'!$D:$D), SUMIFS(_xlpm.intervaloSoma, 'CEI_COMPLETA'!$A:$A, Ajustes!AK$1, 'CEI_COMPLETA'!$B:$B, Ajustes!$R38) ) -> 101744 | ... AO38: =_xlfn.LET( _xlpm.intervaloSoma, IF($S38="R", 'CEI_COMPLETA'!$E:$E, 'CEI_COMPLETA'!$D:$D), SUMIFS(_xlpm.intervaloSoma, 'CEI_COMPLETA'!$A:$A, Ajustes!AO$1, 'CEI_COMPLETA'!$B:$B, Ajustes!$R38) ) -> 100089
A39: RECURSOS | I39: {=_xlfn.SWITCH(B39,0,0,"-",-1,"+",1)} -> 0 | J39: {=_xlfn.SWITCH(C39,0,0,"-",-1,"+",1)} -> 0 | K39: {=_xlfn.SWITCH(D39,0,0,"-",-1,"+",1)} -> 0 | L39: {=_xlfn.SWITCH(E39,0,0,"-",-1,"+",1)} -> 0 | M39: {=_xlfn.SWITCH(F39,0,0,"-",-1,"+",1)} -> 0 | N39: {=_xlfn.SWITCH(G39,0,0,"-",-1,"+",1)} -> 0 | O39: {=_xlfn.SWITCH(H39,0,0,"-",-1,"+",1)} -> 0 | P39: CEI | Q39: D.7 | R39: D.7 | S39: R | T39: =_xlfn.LET( _xlpm.intervaloSoma, IF($S39="R", 'CEI_COMPLETA'!$E:$E, 'CEI_COMPLETA'!$D:$D), SUMIFS(_xlpm.intervaloSoma, 'CEI_COMPLETA'!$A:$A, Ajustes!T$1, 'CEI_COMPLETA'!$B:$B, Ajustes!$Q39) ) -> 6592 | U39: =_xlfn.LET( _xlpm.intervaloSoma, IF($S39="R", 'CEI_COMPLETA'!$E:$E, 'CEI_COMPLETA'!$D:$D), SUMIFS(_xlpm.intervaloSoma, 'CEI_COMPLETA'!$A:$A, Ajustes!U$1, 'CEI_COMPLETA'!$B:$B, Ajustes!$Q39) ) -> 9167 | V39: =_xlfn.LET( _xlpm.intervaloSoma, IF($S39="R", 'CEI_COMPLETA'!$E:$E, 'CEI_COMPLETA'!$D:$D), SUMIFS(_xlpm.intervaloSoma, 'CEI_COMPLETA'!$A:$A, Ajustes!V$1, 'CEI_COMPLETA'!$B:$B, Ajustes!$Q39) ) -> 9752 | W39: =_xlfn.LET( _xlpm.intervaloSoma, IF($S39="R", 'CEI_COMPLETA'!$E:$E, 'CEI_COMPLETA'!$D:$D), SUMIFS(_xlpm.intervaloSoma, 'CEI_COMPLETA'!$A:$A, Ajustes!W$1, 'CEI_COMPLETA'!$B:$B, Ajustes!$Q39) ) -> 14053 | X39: =_xlfn.LET( _xlpm.intervaloSoma, IF($S39="R", 'CEI_COMPLETA'!$E:$E, 'CEI_COMPLETA'!$D:$D), SUMIFS(_xlpm.intervaloSoma, 'CEI_COMPLETA'!$A:$A, Ajustes!X$1, 'CEI_COMPLETA'!$B:$B, Ajustes!$Q39) ) -> 14120 | Y39: =_xlfn.LET( _xlpm.intervaloSoma, IF($S39="R", 'CEI_COMPLETA'!$E:$E, 'CEI_COMPLETA'!$D:$D), SUMIFS(_xlpm.intervaloSoma, 'CEI_COMPLETA'!$A:$A, Ajustes!Y$1, 'CEI_COMPLETA'!$B:$B, Ajustes!$Q39) ) -> 14768 | Z39: =_xlfn.LET( _xlpm.intervaloSoma, IF($S39="R", 'CEI_COMPLETA'!$E:$E, 'CEI_COMPLETA'!$D:$D), SUMIFS(_xlpm.intervaloSoma, 'CEI_COMPLETA'!$A:$A, Ajustes!Z$1, 'CEI_COMPLETA'!$B:$B, Ajustes!$Q39) ) -> 15018 | AA39: =_xlfn.LET( _xlpm.intervaloSoma, IF($S39="R", 'CEI_COMPLETA'!$E:$E, 'CEI_COMPLETA'!$D:$D), SUMIFS(_xlpm.intervaloSoma, 'CEI_COMPLETA'!$A:$A, Ajustes!AA$1, 'CEI_COMPLETA'!$B:$B, Ajustes!$Q39) ) -> 15551 | ... AC39: =_xlfn.LET( _xlpm.intervaloSoma, IF($S39="R", 'CEI_COMPLETA'!$E:$E, 'CEI_COMPLETA'!$D:$D), SUMIFS(_xlpm.intervaloSoma, 'CEI_COMPLETA'!$A:$A, Ajustes!AC$1, 'CEI_COMPLETA'!$B:$B, Ajustes!$Q39) ) -> 18890 | AD39: =_xlfn.LET( _xlpm.intervaloSoma, IF($S39="R", 'CEI_COMPLETA'!$E:$E, 'CEI_COMPLETA'!$D:$D), SUMIFS(_xlpm.intervaloSoma, 'CEI_COMPLETA'!$A:$A, Ajustes!AD$1, 'CEI_COMPLETA'!$B:$B, Ajustes!$R39) ) -> 18824 | AE39: =_xlfn.LET( _xlpm.intervaloSoma, IF($S39="R", 'CEI_COMPLETA'!$E:$E, 'CEI_COMPLETA'!$D:$D), SUMIFS(_xlpm.intervaloSoma, 'CEI_COMPLETA'!$A:$A, Ajustes!AE$1, 'CEI_COMPLETA'!$B:$B, Ajustes!$R39) ) -> 15047 | AF39: =_xlfn.LET( _xlpm.intervaloSoma, IF($S39="R", 'CEI_COMPLETA'!$E:$E, 'CEI_COMPLETA'!$D:$D), SUMIFS(_xlpm.intervaloSoma, 'CEI_COMPLETA'!$A:$A, Ajustes!AF$1, 'CEI_COMPLETA'!$B:$B, Ajustes!$R39) ) -> 25851 | AG39: =_xlfn.LET( _xlpm.intervaloSoma, IF($S39="R", 'CEI_COMPLETA'!$E:$E, 'CEI_COMPLETA'!$D:$D), SUMIFS(_xlpm.intervaloSoma, 'CEI_COMPLETA'!$A:$A, Ajustes!AG$1, 'CEI_COMPLETA'!$B:$B, Ajustes!$R39) ) -> 31160 | AH39: =_xlfn.LET( _xlpm.intervaloSoma, IF($S39="R", 'CEI_COMPLETA'!$E:$E, 'CEI_COMPLETA'!$D:$D), SUMIFS(_xlpm.intervaloSoma, 'CEI_COMPLETA'!$A:$A, Ajustes!AH$1, 'CEI_COMPLETA'!$B:$B, Ajustes!$R39) ) -> 33242 | AI39: =_xlfn.LET( _xlpm.intervaloSoma, IF($S39="R", 'CEI_COMPLETA'!$E:$E, 'CEI_COMPLETA'!$D:$D), SUMIFS(_xlpm.intervaloSoma, 'CEI_COMPLETA'!$A:$A, Ajustes!AI$1, 'CEI_COMPLETA'!$B:$B, Ajustes!$R39) ) -> 40563 | AJ39: =_xlfn.LET( _xlpm.intervaloSoma, IF($S39="R", 'CEI_COMPLETA'!$E:$E, 'CEI_COMPLETA'!$D:$D), SUMIFS(_xlpm.intervaloSoma, 'CEI_COMPLETA'!$A:$A, Ajustes!AJ$1, 'CEI_COMPLETA'!$B:$B, Ajustes!$R39) ) -> 45391 | AK39: =_xlfn.LET( _xlpm.intervaloSoma, IF($S39="R", 'CEI_COMPLETA'!$E:$E, 'CEI_COMPLETA'!$D:$D), SUMIFS(_xlpm.intervaloSoma, 'CEI_COMPLETA'!$A:$A, Ajustes!AK$1, 'CEI_COMPLETA'!$B:$B, Ajustes!$R39) ) -> 46625 | ... AO39: =_xlfn.LET( _xlpm.intervaloSoma, IF($S39="R", 'CEI_COMPLETA'!$E:$E, 'CEI_COMPLETA'!$D:$D), SUMIFS(_xlpm.intervaloSoma, 'CEI_COMPLETA'!$A:$A, Ajustes!AO$1, 'CEI_COMPLETA'!$B:$B, Ajustes!$R39) ) -> 69732
A40: Prêmios líquidos de seguros não-vida | I40: {=_xlfn.SWITCH(B40,0,0,"-",-1,"+",1)} -> 0 | J40: {=_xlfn.SWITCH(C40,0,0,"-",-1,"+",1)} -> 0 | K40: {=_xlfn.SWITCH(D40,0,0,"-",-1,"+",1)} -> 0 | L40: {=_xlfn.SWITCH(E40,0,0,"-",-1,"+",1)} -> 0 | M40: {=_xlfn.SWITCH(F40,0,0,"-",-1,"+",1)} -> 0 | N40: {=_xlfn.SWITCH(G40,0,0,"-",-1,"+",1)} -> 0 | O40: {=_xlfn.SWITCH(H40,0,0,"-",-1,"+",1)} -> 0 | P40: CEI
A41: Transferências sociais em espécie | I41: {=_xlfn.SWITCH(B41,0,0,"-",-1,"+",1)} -> 0 | J41: {=_xlfn.SWITCH(C41,0,0,"-",-1,"+",1)} -> 0 | K41: {=_xlfn.SWITCH(D41,0,0,"-",-1,"+",1)} -> 0 | L41: {=_xlfn.SWITCH(E41,0,0,"-",-1,"+",1)} -> 0 | M41: {=_xlfn.SWITCH(F41,0,0,"-",-1,"+",1)} -> 0 | N41: {=_xlfn.SWITCH(G41,0,0,"-",-1,"+",1)} -> 0 | O41: {=_xlfn.SWITCH(H41,0,0,"-",-1,"+",1)} -> 0 | P41: CEI | Q41: D.63 | R41: D.63 | S41: R | T41: =_xlfn.LET( _xlpm.intervaloSoma, IF($S41="R", 'CEI_COMPLETA'!$E:$E, 'CEI_COMPLETA'!$D:$D), SUMIFS(_xlpm.intervaloSoma, 'CEI_COMPLETA'!$A:$A, Ajustes!T$1, 'CEI_COMPLETA'!$B:$B, Ajustes!$Q41) ) -> 107799 | U41: =_xlfn.LET( _xlpm.intervaloSoma, IF($S41="R", 'CEI_COMPLETA'!$E:$E, 'CEI_COMPLETA'!$D:$D), SUMIFS(_xlpm.intervaloSoma, 'CEI_COMPLETA'!$A:$A, Ajustes!U$1, 'CEI_COMPLETA'!$B:$B, Ajustes!$Q41) ) -> 115533 | V41: =_xlfn.LET( _xlpm.intervaloSoma, IF($S41="R", 'CEI_COMPLETA'!$E:$E, 'CEI_COMPLETA'!$D:$D), SUMIFS(_xlpm.intervaloSoma, 'CEI_COMPLETA'!$A:$A, Ajustes!V$1, 'CEI_COMPLETA'!$B:$B, Ajustes!$Q41) ) -> 138143 | W41: =_xlfn.LET( _xlpm.intervaloSoma, IF($S41="R", 'CEI_COMPLETA'!$E:$E, 'CEI_COMPLETA'!$D:$D), SUMIFS(_xlpm.intervaloSoma, 'CEI_COMPLETA'!$A:$A, Ajustes!W$1, 'CEI_COMPLETA'!$B:$B, Ajustes!$Q41) ) -> 150926 | X41: =_xlfn.LET( _xlpm.intervaloSoma, IF($S41="R", 'CEI_COMPLETA'!$E:$E, 'CEI_COMPLETA'!$D:$D), SUMIFS(_xlpm.intervaloSoma, 'CEI_COMPLETA'!$A:$A, Ajustes!X$1, 'CEI_COMPLETA'!$B:$B, Ajustes!$Q41) ) -> 165425 | Y41: =_xlfn.LET( _xlpm.intervaloSoma, IF($S41="R", 'CEI_COMPLETA'!$E:$E, 'CEI_COMPLETA'!$D:$D), SUMIFS(_xlpm.intervaloSoma, 'CEI_COMPLETA'!$A:$A, Ajustes!Y$1, 'CEI_COMPLETA'!$B:$B, Ajustes!$Q41) ) -> 184332 | Z41: =_xlfn.LET( _xlpm.intervaloSoma, IF($S41="R", 'CEI_COMPLETA'!$E:$E, 'CEI_COMPLETA'!$D:$D), SUMIFS(_xlpm.intervaloSoma, 'CEI_COMPLETA'!$A:$A, Ajustes!Z$1, 'CEI_COMPLETA'!$B:$B, Ajustes!$Q41) ) -> 216239 | AA41: =_xlfn.LET( _xlpm.intervaloSoma, IF($S41="R", 'CEI_COMPLETA'!$E:$E, 'CEI_COMPLETA'!$D:$D), SUMIFS(_xlpm.intervaloSoma, 'CEI_COMPLETA'!$A:$A, Ajustes!AA$1, 'CEI_COMPLETA'!$B:$B, Ajustes!$Q41) ) -> 238126 | ... AO41: =_xlfn.LET( _xlpm.intervaloSoma, IF($S41="R", 'CEI_COMPLETA'!$E:$E, 'CEI_COMPLETA'!$D:$D), SUMIFS(_xlpm.intervaloSoma, 'CEI_COMPLETA'!$A:$A, Ajustes!AO$1, 'CEI_COMPLETA'!$B:$B, Ajustes!$Q41) ) -> 863167
A42: Intermediação financeira e seguros | C42: - | F42: + | I42: {=_xlfn.SWITCH(B42,0,0,"-",-1,"+",1)} -> 0 | J42: {=_xlfn.SWITCH(C42,0,0,"-",-1,"+",1)} -> -1 | K42: {=_xlfn.SWITCH(D42,0,0,"-",-1,"+",1)} -> 0 | L42: {=_xlfn.SWITCH(E42,0,0,"-",-1,"+",1)} -> 0 | M42: {=_xlfn.SWITCH(F42,0,0,"-",-1,"+",1)} -> 1 | N42: {=_xlfn.SWITCH(G42,0,0,"-",-1,"+",1)} -> 0 | O42: {=_xlfn.SWITCH(H42,0,0,"-",-1,"+",1)} -> 0 | P42: TRU_51 | T42: 30060 | U42: 34712 | V42: 40956 | W42: 42859 | X42: 41910 | Y42: 53855 | Z42: 67101 | AA42: 89816 | AB42: 111688 | AC42: 145529 | AD42: 183445 | AE42: 207329 | AF42: 209581 | AG42: 222059 | AH42: 252453 | AI42: 285322 | AJ42: 320468 | AK42: 329896 | AL42: 334777 | AM42: 369544 | AN42: 379659 | AO42: 396491
A43: Ajustamento pela variação da participação líquida das famílias nos fundos de pensões | H43: - | I43: {=_xlfn.SWITCH(B43,0,0,"-",-1,"+",1)} -> 0 | J43: {=_xlfn.SWITCH(C43,0,0,"-",-1,"+",1)} -> 0 | K43: {=_xlfn.SWITCH(D43,0,0,"-",-1,"+",1)} -> 0 | L43: {=_xlfn.SWITCH(E43,0,0,"-",-1,"+",1)} -> 0 | M43: {=_xlfn.SWITCH(F43,0,0,"-",-1,"+",1)} -> 0 | N43: {=_xlfn.SWITCH(G43,0,0,"-",-1,"+",1)} -> 0 | O43: {=_xlfn.SWITCH(H43,0,0,"-",-1,"+",1)} -> -1 | P43: CEI | Q43: D.8 | R43: D.8 | S43: R | T43: =_xlfn.LET( _xlpm.intervaloSoma, IF($S43="R", 'CEI_COMPLETA'!$E:$E, 'CEI_COMPLETA'!$D:$D), SUMIFS(_xlpm.intervaloSoma, 'CEI_COMPLETA'!$A:$A, Ajustes!T$1, 'CEI_COMPLETA'!$B:$B, Ajustes!$Q43) ) -> 12561 | U43: =_xlfn.LET( _xlpm.intervaloSoma, IF($S43="R", 'CEI_COMPLETA'!$E:$E, 'CEI_COMPLETA'!$D:$D), SUMIFS(_xlpm.intervaloSoma, 'CEI_COMPLETA'!$A:$A, Ajustes!U$1, 'CEI_COMPLETA'!$B:$B, Ajustes!$Q43) ) -> 17532 | V43: =_xlfn.LET( _xlpm.intervaloSoma, IF($S43="R", 'CEI_COMPLETA'!$E:$E, 'CEI_COMPLETA'!$D:$D), SUMIFS(_xlpm.intervaloSoma, 'CEI_COMPLETA'!$A:$A, Ajustes!V$1, 'CEI_COMPLETA'!$B:$B, Ajustes!$Q43) ) -> 20392 | W43: =_xlfn.LET( _xlpm.intervaloSoma, IF($S43="R", 'CEI_COMPLETA'!$E:$E, 'CEI_COMPLETA'!$D:$D), SUMIFS(_xlpm.intervaloSoma, 'CEI_COMPLETA'!$A:$A, Ajustes!W$1, 'CEI_COMPLETA'!$B:$B, Ajustes!$Q43) ) -> 29065 | X43: =_xlfn.LET( _xlpm.intervaloSoma, IF($S43="R", 'CEI_COMPLETA'!$E:$E, 'CEI_COMPLETA'!$D:$D), SUMIFS(_xlpm.intervaloSoma, 'CEI_COMPLETA'!$A:$A, Ajustes!X$1, 'CEI_COMPLETA'!$B:$B, Ajustes!$Q43) ) -> 31691 | Y43: =_xlfn.LET( _xlpm.intervaloSoma, IF($S43="R", 'CEI_COMPLETA'!$E:$E, 'CEI_COMPLETA'!$D:$D), SUMIFS(_xlpm.intervaloSoma, 'CEI_COMPLETA'!$A:$A, Ajustes!Y$1, 'CEI_COMPLETA'!$B:$B, Ajustes!$Q43) ) -> 34489 | Z43: =_xlfn.LET( _xlpm.intervaloSoma, IF($S43="R", 'CEI_COMPLETA'!$E:$E, 'CEI_COMPLETA'!$D:$D), SUMIFS(_xlpm.intervaloSoma, 'CEI_COMPLETA'!$A:$A, Ajustes!Z$1, 'CEI_COMPLETA'!$B:$B, Ajustes!$Q43) ) -> 40716 | AA43: =_xlfn.LET( _xlpm.intervaloSoma, IF($S43="R", 'CEI_COMPLETA'!$E:$E, 'CEI_COMPLETA'!$D:$D), SUMIFS(_xlpm.intervaloSoma, 'CEI_COMPLETA'!$A:$A, Ajustes!AA$1, 'CEI_COMPLETA'!$B:$B, Ajustes!$Q43) ) -> 37250 | ... AO43: =_xlfn.LET( _xlpm.intervaloSoma, IF($S43="R", 'CEI_COMPLETA'!$E:$E, 'CEI_COMPLETA'!$D:$D), SUMIFS(_xlpm.intervaloSoma, 'CEI_COMPLETA'!$A:$A, Ajustes!AO$1, 'CEI_COMPLETA'!$B:$B, Ajustes!$Q43) ) -> 69769
A45: AJUSTADO | T45: 2000 | U45: 2001 | V45: 2002 | W45: 2003 | X45: 2004 | Y45: 2005 | Z45: 2006 | AA45: 2007 | AB45: 2008 | AC45: 2009 | AD45: 2010 | AE45: 2011 | AF45: 2012 | AG45: 2013 | AH45: 2014 | AI45: 2015 | AJ45: 2016 | AK45: 2017 | AL45: 2018 | AM45: 2019 | AN45: 2020 | AO45: 2021
A46: Renda nacional disponível bruta | T46: =T$2+SUMPRODUCT($I$11:$I$43,T$11:T$43) -> 742905.38 | U46: =U$2+SUMPRODUCT($I$11:$I$43,U$11:U$43) -> 812378.06 | V46: =V$2+SUMPRODUCT($I$11:$I$43,V$11:V$43) -> 891579.01 | W46: =W$2+SUMPRODUCT($I$11:$I$43,W$11:W$43) -> 1015404.7 | X46: =X$2+SUMPRODUCT($I$11:$I$43,X$11:X$43) -> 1131726.9 | Y46: =Y$2+SUMPRODUCT($I$11:$I$43,Y$11:Y$43) -> 1272368 | Z46: =Z$2+SUMPRODUCT($I$11:$I$43,Z$11:Z$43) -> 1421826.3 | AA46: =AA$2+SUMPRODUCT($I$11:$I$43,AA$11:AA$43) -> 1614160.8 | ... AO46: =AO$2+SUMPRODUCT($I$11:$I$43,AO$11:AO$43) -> 5565230.9
A47: Despesa de consumo final | T47: =T$3+SUMPRODUCT($J$11:$J$43,T$11:T$43) -> 596971.38 | U47: =U$3+SUMPRODUCT($J$11:$J$43,U$11:U$43) -> 656187.06 | V47: =V$3+SUMPRODUCT($J$11:$J$43,V$11:V$43) -> 710589.01 | W47: =W$3+SUMPRODUCT($J$11:$J$43,W$11:W$43) -> 835687.75 | X47: =X$3+SUMPRODUCT($J$11:$J$43,X$11:X$43) -> 939307.91 | Y47: =Y$3+SUMPRODUCT($J$11:$J$43,Y$11:Y$43) -> 1044557 | Z47: =Z$3+SUMPRODUCT($J$11:$J$43,Z$11:Z$43) -> 1157118.3 | AA47: =AA$3+SUMPRODUCT($J$11:$J$43,AA$11:AA$43) -> 1291779.8 | ... AO47: =AO$3+SUMPRODUCT($J$11:$J$43,AO$11:AO$43) -> 4348621.9
A48: Formação Bruta de Capital Fixo | T48: =T$4+SUMPRODUCT($K$11:$K$43,T$11:T$43) -> 14581.225 | U48: =U$4+SUMPRODUCT($K$11:$K$43,U$11:U$43) -> 14580.993 | V48: =V$4+SUMPRODUCT($K$11:$K$43,V$11:V$43) -> 16920.663 | W48: =W$4+SUMPRODUCT($K$11:$K$43,W$11:W$43) -> 18298.288 | X48: =X$4+SUMPRODUCT($K$11:$K$43,X$11:X$43) -> 20260.727 | Y48: =Y$4+SUMPRODUCT($K$11:$K$43,Y$11:Y$43) -> 20808.232 | Z48: =Z$4+SUMPRODUCT($K$11:$K$43,Z$11:Z$43) -> 22408.259 | AA48: =AA$4+SUMPRODUCT($K$11:$K$43,AA$11:AA$43) -> 25180.203 | ... AO48: =AO$4+SUMPRODUCT($K$11:$K$43,AO$11:AO$43) -> 123144.33
A49: Investimento Residencial | T49: =T$5+SUMPRODUCT($L$11:$L$43,T$11:T$43) -> 59344.987 | U49: =U$5+SUMPRODUCT($L$11:$L$43,U$11:U$43) -> 59346.97 | V49: =V$5+SUMPRODUCT($L$11:$L$43,V$11:V$43) -> 68867.819 | W49: =W$5+SUMPRODUCT($L$11:$L$43,W$11:W$43) -> 74475.166 | X49: =X$5+SUMPRODUCT($L$11:$L$43,X$11:X$43) -> 82461.707 | Y49: =Y$5+SUMPRODUCT($L$11:$L$43,Y$11:Y$43) -> 84691.099 | Z49: =Z$5+SUMPRODUCT($L$11:$L$43,Z$11:Z$43) -> 91204.766 | AA49: =AA$5+SUMPRODUCT($L$11:$L$43,AA$11:AA$43) -> 102484.56 | ... AO49: =AO$5+SUMPRODUCT($L$11:$L$43,AO$11:AO$43) -> 329239.26
A50: Juros pessoais | T50: =T$6+SUMPRODUCT($M$11:$M$43,T$11:T$43) -> 47087 | U50: =U$6+SUMPRODUCT($M$11:$M$43,U$11:U$43) -> 52985 | V50: =V$6+SUMPRODUCT($M$11:$M$43,V$11:V$43) -> 60871 | W50: =W$6+SUMPRODUCT($M$11:$M$43,W$11:W$43) -> 69045 | X50: =X$6+SUMPRODUCT($M$11:$M$43,X$11:X$43) -> 67576 | Y50: =Y$6+SUMPRODUCT($M$11:$M$43,Y$11:Y$43) -> 98595 | Z50: =Z$6+SUMPRODUCT($M$11:$M$43,Z$11:Z$43) -> 130074 | AA50: =AA$6+SUMPRODUCT($M$11:$M$43,AA$11:AA$43) -> 167894 | ... AO50: =AO$6+SUMPRODUCT($M$11:$M$43,AO$11:AO$43) -> 676686
A51: Transferências | T51: =T$7+SUMPRODUCT($N$11:$N$43,T$11:T$43) -> 15190 | U51: =U$7+SUMPRODUCT($N$11:$N$43,U$11:U$43) -> 18577 | V51: =V$7+SUMPRODUCT($N$11:$N$43,V$11:V$43) -> 19448 | W51: =W$7+SUMPRODUCT($N$11:$N$43,W$11:W$43) -> 18414 | X51: =X$7+SUMPRODUCT($N$11:$N$43,X$11:X$43) -> 20109 | Y51: =Y$7+SUMPRODUCT($N$11:$N$43,Y$11:Y$43) -> 24340 | Z51: =Z$7+SUMPRODUCT($N$11:$N$43,Z$11:Z$43) -> 28375 | AA51: =AA$7+SUMPRODUCT($N$11:$N$43,AA$11:AA$43) -> 32747 | ... AO51: =AO$7+SUMPRODUCT($N$11:$N$43,AO$11:AO$43) -> 100089
A52: Poupança Financeira | T52: =T$8+SUMPRODUCT($O$11:$O$43,T$11:T$43) -> 16829.225 | U52: =U$8+SUMPRODUCT($O$11:$O$43,U$11:U$43) -> 17799.993 | V52: =V$8+SUMPRODUCT($O$11:$O$43,V$11:V$43) -> 23119.663 | W52: =W$8+SUMPRODUCT($O$11:$O$43,W$11:W$43) -> 8392.2877 | X52: =X$8+SUMPRODUCT($O$11:$O$43,X$11:X$43) -> 11874.727 | Y52: =Y$8+SUMPRODUCT($O$11:$O$43,Y$11:Y$43) -> 9506.2317 | Z52: =Z$8+SUMPRODUCT($O$11:$O$43,Z$11:Z$43) -> 3554.2588 | AA52: =AA$8+SUMPRODUCT($O$11:$O$43,AA$11:AA$43) -> 6333.2033 | ... AO52: =AO$8+SUMPRODUCT($O$11:$O$43,AO$11:AO$43) -> 63279.331
A54: %RNDBF ajustada
A55: Despesa de consumo final | T55: =T47/T$46 -> 0.80356314 | U55: =U47/U$46 -> 0.80773607 | V55: =V47/V$46 -> 0.7970006 | W55: =W47/W$46 -> 0.82300949 | X55: =X47/X$46 -> 0.82997753 | Y55: =Y47/Y$46 -> 0.8209551 | Z55: =Z47/Z$46 -> 0.81382536 | AA55: =AA47/AA$46 -> 0.8002795 | ... AO55: =AO47/AO$46 -> 0.7813911
A56: Formação Bruta de Capital Fixo | T56: =T48/T$46 -> 0.019627298 | U56: =U48/U$46 -> 0.017948532 | V56: =V48/V$46 -> 0.01897831 | W56: =W48/W$46 -> 0.018020684 | X56: =X48/X$46 -> 0.017902488 | Y56: =Y48/Y$46 -> 0.016353941 | Z56: =Z48/Z$46 -> 0.015760195 | AA56: =AA48/AA$46 -> 0.015599564 | ... AO56: =AO48/AO$46 -> 0.022127443
A57: Investimento Residencial | T57: =T49/T$46 -> 0.079882296 | U57: =U49/U$46 -> 0.073053388 | V57: =V49/V$46 -> 0.077242531 | W57: =W49/W$46 -> 0.073345301 | X57: =X49/X$46 -> 0.072863609 | Y57: =Y49/Y$46 -> 0.066561795 | Z57: =Z49/Z$46 -> 0.06414621 | AA57: =AA49/AA$46 -> 0.063490924 | ... AO57: =AO49/AO$46 -> 0.059160036
A58: Juros pessoais | T58: =T50/T$46 -> 0.06338223 | U58: =U50/U$46 -> 0.065222096 | V58: =V50/V$46 -> 0.068273254 | W58: =W50/W$46 -> 0.067997515 | X58: =X50/X$46 -> 0.059710518 | Y58: =Y50/Y$46 -> 0.077489373 | Z58: =Z50/Z$46 -> 0.09148375 | AA58: =AA50/AA$46 -> 0.10401318 | ... AO58: =AO50/AO$46 -> 0.12159172
A59: Transferências | T59: =T51/T$46 -> 0.020446749 | U59: =U51/U$46 -> 0.022867432 | V59: =V51/V$46 -> 0.021812986 | W59: =W51/W$46 -> 0.01813464 | X59: =X51/X$46 -> 0.017768421 | Y59: =Y51/Y$46 -> 0.019129685 | Z59: =Z51/Z$46 -> 0.019956728 | AA59: =AA51/AA$46 -> 0.020287323 | ... AO59: =AO51/AO$46 -> 0.017984698
A60: Poupança Financeira | T60: =T52/T$46 -> 0.022653255 | U60: =U52/U$46 -> 0.021910972 | V60: =V52/V$46 -> 0.025931143 | W60: =W52/W$46 -> 0.008264968 | X60: =X52/X$46 -> 0.010492573 | Y60: =Y52/Y$46 -> 0.007471291 | Z60: =Z52/Z$46 -> 0.0024997841 | AA60: =AA52/AA$46 -> 0.003923527 | ... AO60: =AO52/AO$46 -> 0.011370477

Sheet Gráficos
A2: ORIGINAL | B2: 2000 | C2: 2001 | D2: 2002 | E2: 2003 | F2: 2004 | G2: 2005 | H2: 2006 | I2: 2007 | J2: 2008 | K2: 2009 | L2: 2010 | M2: 2011 | N2: 2012 | O2: 2013 | P2: 2014 | Q2: 2015 | R2: 2016 | S2: 2017 | T2: 2018 | U2: 2019 | V2: 2020 | W2: 2021
A3: Renda nacional disponível bruta | B3: =Ajustes!T2 -> 849321 | C3: =Ajustes!U2 -> 921972 | D3: =Ajustes!V2 -> 1011475 | E3: =Ajustes!W2 -> 1154362 | F3: =Ajustes!X2 -> 1276698 | G3: =Ajustes!Y2 -> 1406510 | H3: =Ajustes!Z2 -> 1546184 | I3: =Ajustes!AA2 -> 1737958 | ... W3: =Ajustes!AO2 -> 5937056
A4: Despesa de consumo final | B4: =Ajustes!T3 -> 754333 | C4: =Ajustes!U3 -> 822656 | D4: =Ajustes!V3 -> 895614 | E4: =Ajustes!W3 -> 1035030 | F4: =Ajustes!X3 -> 1147362 | G4: =Ajustes!Y3 -> 1277027 | H4: =Ajustes!Z3 -> 1411686 | I4: =Ajustes!AA3 -> 1585632 | ... W4: =Ajustes!AO3 -> 5415523
A5: AJUSTADO | B5: 2000 | C5: 2001 | D5: 2002 | E5: 2003 | F5: 2004 | G5: 2005 | H5: 2006 | I5: 2007 | J5: 2008 | K5: 2009 | L5: 2010 | M5: 2011 | N5: 2012 | O5: 2013 | P5: 2014 | Q5: 2015 | R5: 2016 | S5: 2017 | T5: 2018 | U5: 2019 | V5: 2020 | W5: 2021
A6: Renda nacional disponível bruta | B6: =Ajustes!T46 -> 742905.38 | C6: =Ajustes!U46 -> 812378.06 | D6: =Ajustes!V46 -> 891579.01 | E6: =Ajustes!W46 -> 1015404.7 | F6: =Ajustes!X46 -> 1131726.9 | G6: =Ajustes!Y46 -> 1272368 | H6: =Ajustes!Z46 -> 1421826.3 | I6: =Ajustes!AA46 -> 1614160.8 | ... W6: =Ajustes!AO46 -> 5565230.9
A7: Despesa de consumo final | B7: =Ajustes!T47 -> 596971.38 | C7: =Ajustes!U47 -> 656187.06 | D7: =Ajustes!V47 -> 710589.01 | E7: =Ajustes!W47 -> 835687.75 | F7: =Ajustes!X47 -> 939307.91 | G7: =Ajustes!Y47 -> 1044557 | H7: =Ajustes!Z47 -> 1157118.3 | I7: =Ajustes!AA47 -> 1291779.8 | ... W7: =Ajustes!AO47 -> 4348621.9
A9: Aluguel Imputado | B9: =Ajustes!T12 -> 107290 | C9: =Ajustes!U12 -> 111313 | D9: =Ajustes!V12 -> 120331 | E9: =Ajustes!W12 -> 130517 | F9: =Ajustes!X12 -> 137783 | G9: =Ajustes!Y12 -> 149147 | H9: =Ajustes!Z12 -> 155582 | I9: =Ajustes!AA12 -> 168313 | ... W9: =Ajustes!AO12 -> 547406
B10: 2000 | C10: 2001 | D10: 2002 | E10: 2003 | F10: 2004 | G10: 2005 | H10: 2006 | I10: 2007 | J10: 2008 | K10: 2009 | L10: 2010 | M10: 2011 | N10: 2012 | O10: 2013 | P10: 2014 | Q10: 2015 | R10: 2016 | S10: 2017 | T10: 2018 | U10: 2019 | V10: 2020 | W10: 2021
A11: %Aluguel Imputado/RNDB | B11: =B9/B3 -> 0.12632444 | C11: =C9/C3 -> 0.1207336 | D11: =D9/D3 -> 0.11896587 | E11: =E9/E3 -> 0.11306419 | F11: =F9/F3 -> 0.10792137 | G11: =G9/G3 -> 0.10604048 | H11: =H9/H3 -> 0.10062321 | I11: =I9/I3 -> 0.096845263 | ... W11: =W9/W3 -> 0.092201589
A12: %Aluguel Imputado/DCF | B12: =B9/B4 -> 0.14223161 | C12: =C9/C4 -> 0.13530929 | D12: =D9/D4 -> 0.13435587 | E12: =E9/E4 -> 0.12609973 | F12: =F9/F4 -> 0.12008677 | G12: =G9/G4 -> 0.11679236 | H12: =H9/H4 -> 0.11021006 | I12: =I9/I4 -> 0.10614884 | ... W12: =W9/W4 -> 0.10108091
A14: Produção não-mercantil
A15: Agropecuária | B15: =Ajustes!T13 -> 4490.548 | C15: =Ajustes!U13 -> 4922.3507 | D15: =Ajustes!V13 -> 5726.3239 | E15: =Ajustes!W13 -> 6488.0395 | F15: =Ajustes!X13 -> 6794.0781 | G15: =Ajustes!Y13 -> 7317.8925 | H15: =Ajustes!Z13 -> 8031.0548 | I15: =Ajustes!AA13 -> 8919.4675 | ... W15: =Ajustes!AO13 -> 39050.084
A16: Construção | B16: =Ajustes!T14 -> 15521.071 | C16: =Ajustes!U14 -> 15521.589 | D16: =Ajustes!V14 -> 18011.669 | E16: =Ajustes!W14 -> 19478.213 | F16: =Ajustes!X14 -> 21567.01 | G16: =Ajustes!Y14 -> 22150.085 | H16: =Ajustes!Z14 -> 23853.668 | I16: =Ajustes!AA14 -> 26803.781 | ... W16: =Ajustes!AO14 -> 83954
B17: 2000 | C17: 2001 | D17: 2002 | E17: 2003 | F17: 2004 | G17: 2005 | H17: 2006 | I17: 2007 | J17: 2008 | K17: 2009 | L17: 2010 | M17: 2011 | N17: 2012 | O17: 2013 | P17: 2014 | Q17: 2015 | R17: 2016 | S17: 2017 | T17: 2018 | U17: 2019 | V17: 2020 | W17: 2021
A18: % Prod. Agropecuária não-mercantil/RNDB | B18: =B15/B$3 -> 0.0052872212 | C18: =C15/C$3 -> 0.0053389373 | D18: =D15/D$3 -> 0.0056613598 | E18: =E15/E$3 -> 0.0056204548 | F18: =F15/F$3 -> 0.0053216016 | G18: =G15/G$3 -> 0.0052028727 | H18: =H15/H$3 -> 0.0051941132 | I18: =I15/I$3 -> 0.0051321537 | ... W18: =W15/W$3 -> 0.0065773482
A19: % Prod. Construção não-mercantil/RNDB | B19: =B16/B$3 -> 0.018274681 | C19: =C16/C$3 -> 0.016835206 | D19: =D16/D$3 -> 0.01780733 | E19: =E16/E$3 -> 0.016873574 | F19: =F16/F$3 -> 0.016892805 | G19: =G16/G$3 -> 0.01574826 | H19: =H16/H$3 -> 0.015427444 | I19: =I16/I$3 -> 0.015422571 | ... W19: =W16/W$3 -> 0.014140678
A21: Juros
A22: Juros Líquidos | B22: =B24-B23 -> 50122 | C22: =C24-C23 -> 53044 | D22: =D24-D23 -> 57051 | E22: =E24-E23 -> 58594 | F22: =F24-F23 -> 48614 | G22: =G24-G23 -> 57713 | H22: =H24-H23 -> 52663 | I22: =I24-I23 -> 58695 | ... W22: =W24-W23 -> 44522
A23: Juros (usos) | B23: =Ajustes!T35 -> 17027 | C23: =Ajustes!U35 -> 18273 | D23: =Ajustes!V35 -> 19915 | E23: =Ajustes!W35 -> 26186 | F23: =Ajustes!X35 -> 25666 | G23: =Ajustes!Y35 -> 44740 | H23: =Ajustes!Z35 -> 62973 | I23: =Ajustes!AA35 -> 78078 | ... W23: =Ajustes!AO35 -> 280195
A24: Juros (recursos) | B24: =Ajustes!T36 -> 67149 | C24: =Ajustes!U36 -> 71317 | D24: =Ajustes!V36 -> 76966 | E24: =Ajustes!W36 -> 84780 | F24: =Ajustes!X36 -> 74280 | G24: =Ajustes!Y36 -> 102453 | H24: =Ajustes!Z36 -> 115636 | I24: =Ajustes!AA36 -> 136773 | ... W24: =Ajustes!AO36 -> 324717
A25: Intermediação financeira e seguros | B25: =Ajustes!T42 -> 30060 | C25: =Ajustes!U42 -> 34712 | D25: =Ajustes!V42 -> 40956 | E25: =Ajustes!W42 -> 42859 | F25: =Ajustes!X42 -> 41910 | G25: =Ajustes!Y42 -> 53855 | H25: =Ajustes!Z42 -> 67101 | I25: =Ajustes!AA42 -> 89816 | ... W25: =Ajustes!AO42 -> 396491
A26: Juros pessoais | B26: =B25+B23 -> 47087 | C26: =C25+C23 -> 52985 | D26: =D25+D23 -> 60871 | E26: =E25+E23 -> 69045 | F26: =F25+F23 -> 67576 | G26: =G25+G23 -> 98595 | H26: =H25+H23 -> 130074 | I26: =I25+I23 -> 167894 | ... W26: =W25+W23 -> 676686
B27: 2000 | C27: 2001 | D27: 2002 | E27: 2003 | F27: 2004 | G27: 2005 | H27: 2006 | I27: 2007 | J27: 2008 | K27: 2009 | L27: 2010 | M27: 2011 | N27: 2012 | O27: 2013 | P27: 2014 | Q27: 2015 | R27: 2016 | S27: 2017 | T27: 2018 | U27: 2019 | V27: 2020 | W27: 2021
A28: % Juros Líquidos/RNDB | B28: =B22/B$3 -> 0.059014201 | C28: =C22/C$3 -> 0.057533201 | D28: =D22/D$3 -> 0.056403767 | E28: =E22/E$3 -> 0.050758774 | F28: =F22/F$3 -> 0.038077917 | G28: =G22/G$3 -> 0.041032769 | H28: =H22/H$3 -> 0.034059983 | I28: =I22/I$3 -> 0.033772393 | ... W28: =W22/W$3 -> 0.0074990029
A29: % Juros (usos)/RNDB | B29: =B23/B$3 -> 0.020047779 | C29: =C23/C$3 -> 0.019819474 | D29: =D23/D$3 -> 0.019689068 | E29: =E23/E$3 -> 0.022684392 | F29: =F23/F$3 -> 0.020103423 | G29: =G23/G$3 -> 0.03180923 | H29: =H23/H$3 -> 0.040728012 | I29: =I23/I$3 -> 0.044925136 | ... W29: =W23/W$3 -> 0.047194266
A30: % Juros (recursos)/RNDB | B30: =B24/B$3 -> 0.07906198 | C30: =C24/C$3 -> 0.077352674 | D30: =D24/D$3 -> 0.076092835 | E30: =E24/E$3 -> 0.073443166 | F30: =F24/F$3 -> 0.05818134 | G30: =G24/G$3 -> 0.072841999 | H30: =H24/H$3 -> 0.074787994 | I30: =I24/I$3 -> 0.078697529 | ... W30: =W24/W$3 -> 0.054693269
A31: % Intermediação financeira e seguros/RNDB | B31: =B25/B$3 -> 0.035392979 | C31: =C25/C$3 -> 0.037649733 | D31: =D25/D$3 -> 0.040491362 | E31: =E25/E$3 -> 0.037127868 | F31: =F25/F$3 -> 0.032826871 | G31: =G25/G$3 -> 0.03828981 | H31: =H25/H$3 -> 0.04339781 | I31: =I25/I$3 -> 0.051679039 | ... W31: =W25/W$3 -> 0.066782425
A32: %Juros pessoais/RNDB | B32: =B26/B$3 -> 0.055440758 | C32: =C26/C$3 -> 0.057469207 | D32: =D26/D$3 -> 0.06018043 | E32: =E26/E$3 -> 0.05981226 | F32: =F26/F$3 -> 0.052930294 | G32: =G26/G$3 -> 0.070099039 | H32: =H26/H$3 -> 0.084125822 | I32: =I26/I$3 -> 0.096604176 | ... W32: =W26/W$3 -> 0.11397669
A34: Desembolso por rendas de Investimento | B34: =Ajustes!T18 -> 11331 | C34: =Ajustes!U18 -> 14687 | D34: =Ajustes!V18 -> 15190 | E34: =Ajustes!W18 -> 27074 | F34: =Ajustes!X18 -> 24602 | G34: =Ajustes!Y18 -> 24607 | H34: =Ajustes!Z18 -> 28239 | I34: =Ajustes!AA18 -> 30586 | ... W34: =Ajustes!AO18 -> 81699
B35: 2000 | C35: 2001 | D35: 2002 | E35: 2003 | F35: 2004 | G35: 2005 | H35: 2006 | I35: 2007 | J35: 2008 | K35: 2009 | L35: 2010 | M35: 2011 | N35: 2012 | O35: 2013 | P35: 2014 | Q35: 2015 | R35: 2016 | S35: 2017 | T35: 2018 | U35: 2019 | V35: 2020 | W35: 2021
A36: %DRI/RNDB | B36: =B34/B3 -> 0.013341246 | C36: =C34/C3 -> 0.015929985 | D36: =D34/D3 -> 0.015017672 | E36: =E34/E3 -> 0.023453648 | F36: =F34/F3 -> 0.019270023 | G36: =G34/G3 -> 0.017495076 | H36: =H34/H3 -> 0.018263674 | I36: =I34/I3 -> 0.017598814 | ... W36: =W34/W3 -> 0.013760861
A38: Construção Residencial | B38: =Ajustes!T16 -> 66827.775 | C38: =Ajustes!U16 -> 66830.007 | D38: =Ajustes!V16 -> 77551.337 | E38: =Ajustes!W16 -> 83865.712 | F38: =Ajustes!X16 -> 92859.273 | G38: =Ajustes!Y16 -> 95369.768 | H38: =Ajustes!Z16 -> 102704.74 | I38: =Ajustes!AA16 -> 115406.8 | ... W38: =Ajustes!AO16 -> 376554.67
B39: 2000 | C39: 2001 | D39: 2002 | E39: 2003 | F39: 2004 | G39: 2005 | H39: 2006 | I39: 2007 | J39: 2008 | K39: 2009 | L39: 2010 | M39: 2011 | N39: 2012 | O39: 2013 | P39: 2014 | Q39: 2015 | R39: 2016 | S39: 2017 | T39: 2018 | U39: 2019 | V39: 2020 | W39: 2021
A40: %Investimento Residencial | B40: =B38/B3 -> 0.078683766 | C40: =C38/C3 -> 0.07248594 | D40: =D38/D3 -> 0.076671531 | E40: =E38/E3 -> 0.072651137 | F40: =F38/F3 -> 0.072733938 | G40: =G38/G3 -> 0.067805965 | H40: =H38/H3 -> 0.066424657 | I40: =I38/I3 -> 0.066403674 | ... W40: =W38/W3 -> 0.063424477
A42: Transferências
A43: Transferências (líquidas) | B43: =Ajustes!T37 -> -8598 | C43: =Ajustes!U37 -> -9410 | D43: =Ajustes!V37 -> -9696 | E43: =Ajustes!W37 -> -4361 | F43: =Ajustes!X37 -> -5989 | G43: =Ajustes!Y37 -> -9572 | H43: =Ajustes!Z37 -> -13357 | I43: =Ajustes!AA37 -> -17196 | ... W43: =Ajustes!AO37 -> -30357
A44: Transferências (usos) | B44: =Ajustes!T38 -> 15190 | C44: =Ajustes!U38 -> 18577 | D44: =Ajustes!V38 -> 19448 | E44: =Ajustes!W38 -> 18414 | F44: =Ajustes!X38 -> 20109 | G44: =Ajustes!Y38 -> 24340 | H44: =Ajustes!Z38 -> 28375 | I44: =Ajustes!AA38 -> 32747 | ... W44: =Ajustes!AO38 -> 100089
A45: Transferências (recursos) | B45: =Ajustes!T39 -> 6592 | C45: =Ajustes!U39 -> 9167 | D45: =Ajustes!V39 -> 9752 | E45: =Ajustes!W39 -> 14053 | F45: =Ajustes!X39 -> 14120 | G45: =Ajustes!Y39 -> 14768 | H45: =Ajustes!Z39 -> 15018 | I45: =Ajustes!AA39 -> 15551 | ... W45: =Ajustes!AO39 -> 69732
B46: 2000 | C46: 2001 | D46: 2002 | E46: 2003 | F46: 2004 | G46: 2005 | H46: 2006 | I46: 2007 | J46: 2008 | K46: 2009 | L46: 2010 | M46: 2011 | N46: 2012 | O46: 2013 | P46: 2014 | Q46: 2015 | R46: 2016 | S46: 2017 | T46: 2018 | U46: 2019 | V46: 2020 | W46: 2021
A47: % Transferências (usos)/RNDB | B47: =B44/B3 -> 0.017884875 | C47: =C44/C3 -> 0.020149202 | D47: =D44/D3 -> 0.019227366 | E47: =E44/E3 -> 0.015951669 | F47: =F44/F3 -> 0.015750788 | G47: =G44/G3 -> 0.017305245 | H47: =H44/H3 -> 0.018351632 | I47: =I44/I3 -> 0.018842227 | ... W47: =W44/W3 -> 0.016858355
A49: Poupança
A50: Poupança bruta | B50: =Ajustes!T8 -> 107549 | C50: =Ajustes!U8 -> 116849 | D50: =Ajustes!V8 -> 136253 | E50: =Ajustes!W8 -> 148397 | F50: =Ajustes!X8 -> 161027 | G50: =Ajustes!Y8 -> 163972 | H50: =Ajustes!Z8 -> 175214 | I50: =Ajustes!AA8 -> 189576 | ... W50: =Ajustes!AO8 -> 591302
A51: Poupança Financeira | B51: =Ajustes!T52 -> 16829.225 | C51: =Ajustes!U52 -> 17799.993 | D51: =Ajustes!V52 -> 23119.663 | E51: =Ajustes!W52 -> 8392.2877 | F51: =Ajustes!X52 -> 11874.727 | G51: =Ajustes!Y52 -> 9506.2317 | H51: =Ajustes!Z52 -> 3554.2588 | I51: =Ajustes!AA52 -> 6333.2033 | ... W51: =Ajustes!AO52 -> 63279.331
A52: Poupança Financeira + Investimento Residencial | B52: =B51+B38 -> 83657 | C52: =C51+C38 -> 84630 | D52: =D51+D38 -> 100671 | E52: =E51+E38 -> 92258 | F52: =F51+F38 -> 104734 | G52: =G51+G38 -> 104876 | H52: =H51+H38 -> 106259 | I52: =I51+I38 -> 121740 | ... W52: =W51+W38 -> 439834
B53: 2000 | C53: 2001 | D53: 2002 | E53: 2003 | F53: 2004 | G53: 2005 | H53: 2006 | I53: 2007 | J53: 2008 | K53: 2009 | L53: 2010 | M53: 2011 | N53: 2012 | O53: 2013 | P53: 2014 | Q53: 2015 | R53: 2016 | S53: 2017 | T53: 2018 | U53: 2019 | V53: 2020 | W53: 2021
A54: Poupança bruta/RNDB | B54: =B50/B$3 -> 0.12662939 | C54: =C50/C$3 -> 0.12673812 | D54: =D50/D$3 -> 0.13470723 | E54: =E50/E$3 -> 0.12855326 | F54: =F50/F$3 -> 0.12612771 | G54: =G50/G$3 -> 0.11658076 | H54: =H50/H$3 -> 0.11332028 | I54: =I50/I$3 -> 0.10907974 | ... W54: =W50/W$3 -> 0.099595153
A55: Poupança Financeira/RNDB | B55: =B51/B$3 -> 0.019814917 | C55: =C51/C$3 -> 0.019306436 | D55: =D51/D$3 -> 0.022857375 | E55: =E51/E$3 -> 0.0072700658 | F55: =F51/F$3 -> 0.0093011247 | G55: =G51/G$3 -> 0.0067587374 | H55: =H51/H$3 -> 0.0022987295 | I55: =I51/I$3 -> 0.0036440486 | ... W55: =W51/W$3 -> 0.010658369
A56: Poupança Financeira + Investimento Residencial/RNDB | B56: =B52/B$3 -> 0.098498683 | C56: =C52/C$3 -> 0.091792375 | D56: =D52/D$3 -> 0.099528906 | E56: =E52/E$3 -> 0.079921203 | F56: =F52/F$3 -> 0.082035062 | G56: =G52/G$3 -> 0.074564703 | H56: =H52/H$3 -> 0.068723386 | I56: =I52/I$3 -> 0.070047723 | ... W56: =W52/W$3 -> 0.074082845
B58: 2000 | C58: 2001 | D58: 2002 | E58: 2003 | F58: 2004 | G58: 2005 | H58: 2006 | I58: 2007 | J58: 2008 | K58: 2009 | L58: 2010 | M58: 2011 | N58: 2012 | O58: 2013 | P58: 2014 | Q58: 2015 | R58: 2016 | S58: 2017 | T58: 2018 | U58: 2019 | V58: 2020 | W58: 2021
A59: %Investimento Residencial | B59: =B38/B6 -> 0.089954625 | C59: =C38/C6 -> 0.082264662 | D59: =D38/D6 -> 0.086982013 | E59: =E38/E6 -> 0.082593382 | F59: =F38/F6 -> 0.082050954 | G59: =G38/G6 -> 0.074954547 | H59: =H38/H6 -> 0.072234381 | I59: =I38/I6 -> 0.071496471 | ... W59: =W38/W6 -> 0.067662003
A60: % Transferências (usos)/RNDB | B60: =B44/B6 -> 0.020446749 | C60: =C44/C6 -> 0.022867432 | D60: =D44/D6 -> 0.021812986 | E60: =E44/E6 -> 0.01813464 | F60: =F44/F6 -> 0.017768421 | G60: =G44/G6 -> 0.019129685 | H60: =H44/H6 -> 0.019956728 | I60: =I44/I6 -> 0.020287323 | ... W60: =W44/W6 -> 0.017984698
A61: %Juros Pessoais/RNDB | B61: =B26/B6 -> 0.06338223 | C61: =C26/C6 -> 0.065222096 | D61: =D26/D6 -> 0.068273254 | E61: =E26/E6 -> 0.067997515 | F61: =F26/F6 -> 0.059710518 | G61: =G26/G6 -> 0.077489373 | H61: =H26/H6 -> 0.09148375 | I61: =I26/I6 -> 0.10401318 | ... W61: =W26/W6 -> 0.12159172
A62: %Despesa de consumo final | B62: =B7/B6 -> 0.80356314 | C62: =C7/C6 -> 0.80773607 | D62: =D7/D6 -> 0.7970006 | E62: =E7/E6 -> 0.82300949 | F62: =F7/F6 -> 0.82997753 | G62: =G7/G6 -> 0.8209551 | H62: =H7/H6 -> 0.81382536 | I62: =I7/I6 -> 0.8002795 | ... W62: =W7/W6 -> 0.7813911
